Workbook

Sheet LISTAS
B2: Estado | D2: Broker | E2: Plazo_max_horas | G2: Doctor | H2: Correo | J2: Plazo | L2: DIAS_NO_LABORABLES
B3: FINALIZADO | D3: ARTHUR GALLAGHER | E3: 6 | G3: DR PEREZ | H3: jlperez@mapfre.com.pe | J3: Dentro | L3: {=_xlfn.LET(_xlpm.y,YEAR(TODAY()),_xlpm.i,_xlfn.SEQUENCE(64),_xlpm.a,_xlpm.y-INT((_xlpm.i-1)/16),_xlpm.h,MOD(_xlpm.i-1,16)+1,_xlpm.pas,ROUND(DATE(_xlpm.a,4,1)/7+MOD(19*MOD(_xlpm.a,19)-7,30)*0.14,0)*7-6,_xlpm.m,CHOOSE(_xlpm.h,1,1,1,5,6,6,7,7,7,8,8,10,11,12,12,12),_xlpm.d,CHOOSE(_xlpm.h,1,1,1,1,7,29,23,28,29,6,30,8,1,8,9,25),IF(_xlpm.h=2,_xlpm.pas-3,IF(_xlpm.h=3,_xlpm.pas-2,DATE(_xlpm.a,_xlpm.m,_xlpm.d))))} -> 46023 | M3: <-- Automático: feriados de Perú del año actual y los 3 anteriores (64 fechas). No escribir aquí abajo. Para más años, en L3 cambiar SECUENCIA(64) por 80, 96, etc. (16 por año).
B4: SOLICITA INFORMACIÓN | D4: GABEL | E4: <-- E3 es el plazo en horas. Cambia ese número si cambia el SeviceLevelAgreement. | G4: DRA ANA | H4: anavf2110@gmail.com | J4: Fuera | L4: 46114
B5: INFORMACIÓN ENVIADA | D5: HOWDEN | L5: 46115
D6: MARSH | L6: 46143
B7: (en blanco = PENDIENTE) | D7: UIB | L7: 46180
L8: 46202
L9: 46226
L10: 46231
L11: 46232
L12: 46240
L13: 46264
L14: 46303
L15: 46327
L16: 46364
L17: 46365
L18: 46381
L19: 45658
... L66: 45285

Sheet INDICADORES
B2: INDICADORES BROKERS
B4: CORREOS POR BROKER
B5: ARTHUR GALLAGHER | C5: =COUNTIF(SCTR_Brokers[Broker],"ARTHUR GALLAGHER") -> 102
B6: GABEL | C6: =COUNTIF(SCTR_Brokers[Broker],"GABEL") -> 53
B7: HOWDEN | C7: =COUNTIF(SCTR_Brokers[Broker],"HOWDEN") -> 73
B8: MARSH | C8: =COUNTIF(SCTR_Brokers[Broker],"MARSH") -> 250
B9: UIB | C9: =COUNTIF(SCTR_Brokers[Broker],"UIB") -> 51
B10: TOTAL | C10: =COUNTA(SCTR_Brokers[ConversationId]) -> 531
B12: ESTADO
B13: PENDIENTE (en blanco) | C13: =COUNTA(SCTR_Brokers[ConversationId])-COUNTIF(SCTR_Brokers[Estado],"FINALIZADO")-COUNTIF(SCTR_Brokers[Estado],"SOLICITA INFORMACIÓN")-COUNTIF(SCTR_Brokers[Estado],"INFORMACIÓN ENVIADA") -> 18
B14: SOLICITA INFORMACIÓN | C14: =COUNTIF(SCTR_Brokers[Estado],"SOLICITA INFORMACIÓN") -> 1
B15: INFORMACIÓN ENVIADA | C15: =COUNTIF(SCTR_Brokers[Estado],"INFORMACIÓN ENVIADA") -> 1
B16: FINALIZADO | C16: =COUNTIF(SCTR_Brokers[Estado],"FINALIZADO") -> 511
B19: ="PLAZO ("&LISTAS!E3&" h)" -> PLAZO (6 h)
B20: Finalizados DENTRO | C20: =SUM(SCTR_Brokers[DentroPlazo_Finalizado]) -> 379
B21: Finalizados FUERA | C21: =SUM(SCTR_Brokers[FueraPlazo_Finalizado]) -> 132
B22: Pendientes FUERA | C22: =SUM(SCTR_Brokers[PendienteFueraPlazo]) -> 5
B23: % cumplimiento | C23: =IFERROR(SUM(SCTR_Brokers[DentroPlazo_Finalizado])/SUM(SCTR_Brokers[EsFinalizado]),"") -> 0.74168297
B26: ÁREA MÉDICA
B27: Solicitudes al doctor | C27: =SUM(SCTR_Brokers[SolicitoInforme]) -> 36
B28: Informes recibidos | C28: =SUM(SCTR_Brokers[InformeRecibido]) -> 24
B29: Pendientes de doctor | C29: =SUM(SCTR_Brokers[PendienteDoctor]) -> 14
B30: Horas prom. respuesta | C30: =IFERROR(AVERAGE(SCTR_Brokers[HorasRespuestaDoctor]),"") -> 3.6863636

Sheet SEGUIMIENTO
A1: ConversationId | B1: ConversationId_Alt | C1: CasoId | D1: Asunto | E1: Broker | F1: FechaRecepcion | G1: FechaUltimaRespuesta | H1: PersonaUltimaRespuesta | I1: Estado | J1: Observaciones | K1: Encargado | L1: CorreoDoctor | M1: DoctorEncargado | N1: Horas_Transcurridas | O1: Fecha_Solic_Informe | P1: Fecha_Informe | Q1: Fecha_Cierre | R1: Plazo | S1: Derivado | T1: Mes | U1: EsFinalizado | V1: EsPendiente | W1: DentroPlazo_Finalizado | X1: FueraPlazo_Finalizado | Y1: PendienteFueraPlazo | Z1: SolicitoInforme | AA1: InformeRecibido | AB1: PendienteDoctor | AC1: HorasRespuestaDoctor
A2: AAQkADdkNThjNzFkLWM0ZmMtNDJhYS04MDVlLTIwNzE4ZDI1Mzg4YgAQAJce04pfmOxCjc66JQ_YqAI= | C2: =IF(SCTR_Brokers[[#This Row],[FechaRecepcion]]="","",SCTR_Brokers[[#This Row],[ConversationId]]&"-"&TEXT(SCTR_Brokers[[#This Row],[FechaRecepcion]],"aaaammddhhmmss")) -> AAQkADdkNThjNzFkLWM0ZmMtNDJhYS04MDVlLTIwNzE4ZDI1Mzg4YgAQAJce04pfmOxCjc66JQ_YqAI=-20260813130900 | D2: RE: TAMSHI: ACCIDENTE LABORAL_REATEGUI CURICHIMBA MARCOS (mordedura de serpiente) | E2: MARSH | F2: 46247.548 | G2: 46247.617 | H2: Katherine.Andrade@marsh.com | I2: FINALIZADO | K2: SCTR SALUD | N2: =IF(SCTR_Brokers[[#This Row],[FechaRecepcion]]="","",IF(SCTR_Brokers[[#This Row],[Estado]]="FINALIZADO","",IF(SCTR_Brokers[[#This Row],[FechaUltimaRespuesta]]="","",_xlfn.LET(_xlpm.fer,LISTAS!$L$3:$L$100,_xlpm.ep,DATE(2000,1,1),_xlpm.ini,SCTR_Brokers[[#This Row],[FechaUltimaRespuesta]],_xlpm.fin,NOW(),_xlpm.dini,INT(_xlpm.ini),_xlpm.dfin,INT(_xlpm.fin),_xlpm.hini,9.5*NETWORKDAYS.INTL(_xlpm.ep,_xlpm.dini-1,"0000111",_xlpm.fer)+6*NETWORKDAYS.INTL(_xlpm.ep,_xlpm.dini-1,"1111011",_xlpm.fer)+IF(OR(WEEKDAY(_xlpm.dini,2)>5,COUNTIF(_xlpm.fer,_xlpm.dini)>0),0,MAX(0,MIN(_xlpm.ini-_xlpm.dini,IF(WEEKDAY(_xlpm.dini,2)=5,14/24,17.5/24))-8/24)*24),_xlpm.hfin,9.5*NETWORKDAYS.INTL(_xlpm.ep,_xlpm.dfin-1,"0000111",_xlpm.fer)+6*NETWORKDAYS.INTL(_xlpm.ep,_xlpm.dfin-1,"1111011",_xlpm.fer)+IF(OR(WEEKDAY(_xlpm.dfin,2)>5,COUNTIF(_xlpm.fer,_xlpm.dfin)>0),0,MAX(0,MIN(_xlpm.fin-_xlpm.dfin,IF(WEEKDAY(_xlpm.dfin,2)=5,14/24,17.5/24))-8/24)*24),ROUND(MAX(0,_xlpm.hfin-_xlpm.hini),1))))) | Q2: 46247.618 | R2: =IF(SCTR_Brokers[[#This Row],[FechaRecepcion]]="","",_xlfn.LET(_xlpm.fer,LISTAS!$L$3:$L$100,_xlpm.ep,DATE(2000,1,1),_xlpm.ini,SCTR_Brokers[[#This Row],[FechaRecepcion]],_xlpm.fin,IF(SCTR_Brokers[[#This Row],[Fecha_Cierre]]<>"",SCTR_Brokers[[#This Row],[Fecha_Cierre]],NOW()),_xlpm.dini,INT(_xlpm.ini),_xlpm.dfin,INT(_xlpm.fin),_xlpm.hini,9.5*NETWORKDAYS.INTL(_xlpm.ep,_xlpm.dini-1,"0000111",_xlpm.fer)+6*NETWORKDAYS.INTL(_xlpm.ep,_xlpm.dini-1,"1111011",_xlpm.fer)+IF(OR(WEEKDAY(_xlpm.dini,2)>5,COUNTIF(_xlpm.fer,_xlpm.dini)>0),0,MAX(0,MIN(_xlpm.ini-_xlpm.dini,IF(WEEKDAY(_xlpm.dini,2)=5,14/24,17.5/24))-8/24)*24),_xlpm.hfin,9.5*NETWORKDAYS.INTL(_xlpm.ep,_xlpm.dfin-1,"0000111",_xlpm.fer)+6*NETWORKDAYS.INTL(_xlpm.ep,_xlpm.dfin-1,"1111011",_xlpm.fer)+IF(OR(WEEKDAY(_xlpm.dfin,2)>5,COUNTIF(_xlpm.fer,_xlpm.dfin)>0),0,MAX(0,MIN(_xlpm.fin-_xlpm.dfin,IF(WEEKDAY(_xlpm.dfin,2)=5,14/24,17.5/24))-8/24)*24),_xlpm.hrs,IF(SCTR_Brokers[[#This Row],[Estado]]="FINALIZADO",MAX(0,_xlpm.hfin-_xlpm.hini),IF(SCTR_Brokers[[#This Row],[Horas_Transcurridas]]="",MAX(0,_xlpm.hfin-_xlpm.hini),SCTR_Brokers[[#This Row],[Horas_Transcurridas]])),IF(_xlpm.hrs<=LISTAS!$E$3,LISTAS!$J$3,LISTAS!$J$4))) -> Dentro | T2: =IF(SCTR_Brokers[[#This Row],[FechaRecepcion]]="","",TEXT(SCTR_Brokers[[#This Row],[FechaRecepcion]],"mmmm")&" "&YEAR(SCTR_Brokers[[#This Row],[FechaRecepcion]])) -> agosto 2026 | U2: =IF(SCTR_Brokers[[#This Row],[Estado]]="FINALIZADO",1,0) -> 1 | V2: =IF(SCTR_Brokers[[#This Row],[FechaRecepcion]]="","",IF(SCTR_Brokers[[#This Row],[Estado]]="FINALIZADO",0,1)) -> 0 | W2: =IF(AND(SCTR_Brokers[[#This Row],[Estado]]="FINALIZADO",SCTR_Brokers[[#This Row],[Plazo]]=LISTAS!$J$3),1,0) -> 1 | X2: =IF(AND(SCTR_Brokers[[#This Row],[Estado]]="FINALIZADO",SCTR_Brokers[[#This Row],[Plazo]]=LISTAS!$J$4),1,0) -> 0 | Y2: =IF(AND(SCTR_Brokers[[#This Row],[Estado]]<>"FINALIZADO",SCTR_Brokers[[#This Row],[Plazo]]=LISTAS!$J$4),1,0) -> 0 | Z2: =IF(SCTR_Brokers[[#This Row],[Fecha_Solic_Informe]]="",0,1) -> 0 | AA2: =IF(SCTR_Brokers[[#This Row],[Fecha_Informe]]="",0,1) -> 0 | AB2: =IF(AND(SCTR_Brokers[[#This Row],[Fecha_Solic_Informe]]<>"",SCTR_Brokers[[#This Row],[Fecha_Informe]]=""),1,0) -> 0 | AC2: =IF(AND(SCTR_Brokers[[#This Row],[Fecha_Solic_Informe]]<>"",SCTR_Brokers[[#This Row],[Fecha_Informe]]<>""),ROUND((SCTR_Brokers[[#This Row],[Fecha_Informe]]-SCTR_Brokers[[#This Row],[Fecha_Solic_Informe]])*24,1),"")
A3: AAQkADdkNThjNzFkLWM0ZmMtNDJhYS04MDVlLTIwNzE4ZDI1Mzg4YgAQAH-nDgfBdEb_vQ6M26ET90Q= | C3: =IF(SCTR_Brokers[[#This Row],[FechaRecepcion]]="","",SCTR_Brokers[[#This Row],[ConversationId]]&"-"&TEXT(SCTR_Brokers[[#This Row],[FechaRecepcion]],"aaaammddhhmmss")) -> AAQkADdkNThjNzFkLWM0ZmMtNDJhYS04MDVlLTIwNzE4ZDI1Mzg4YgAQAH-nDgfBdEb_vQ6M26ET90Q=-20260813150331 | D3: MOTIVO DEL RECHAZO DE CG _ DNI 10615639 _ PAREDES CANDELA DANIEL WALTER _REPRESENTACIONES YAGO SAC _ RUC 20505006675 _ SCTR | E3: GABEL | F3: 46247.627 | G3: 46247.694 | H3: sctrsalud@mapfre.com.pe | I3: FINALIZADO | K3: SCTR SALUD | N3: =IF(SCTR_Brokers[[#This Row],[FechaRecepcion]]="","",IF(SCTR_Brokers[[#This Row],[Estado]]="FINALIZADO","",IF(SCTR_Brokers[[#This Row],[FechaUltimaRespuesta]]="","",_xlfn.LET(_xlpm.fer,LISTAS!$L$3:$L$100,_xlpm.ep,DATE(2000,1,1),_xlpm.ini,SCTR_Brokers[[#This Row],[FechaUltimaRespuesta]],_xlpm.fin,NOW(),_xlpm.dini,INT(_xlpm.ini),_xlpm.dfin,INT(_xlpm.fin),_xlpm.hini,9.5*NETWORKDAYS.INTL(_xlpm.ep,_xlpm.dini-1,"0000111",_xlpm.fer)+6*NETWORKDAYS.INTL(_xlpm.ep,_xlpm.dini-1,"1111011",_xlpm.fer)+IF(OR(WEEKDAY(_xlpm.dini,2)>5,COUNTIF(_xlpm.fer,_xlpm.dini)>0),0,MAX(0,MIN(_xlpm.ini-_xlpm.dini,IF(WEEKDAY(_xlpm.dini,2)=5,14/24,17.5/24))-8/24)*24),_xlpm.hfin,9.5*NETWORKDAYS.INTL(_xlpm.ep,_xlpm.dfin-1,"0000111",_xlpm.fer)+6*NETWORKDAYS.INTL(_xlpm.ep,_xlpm.dfin-1,"1111011",_xlpm.fer)+IF(OR(WEEKDAY(_xlpm.dfin,2)>5,COUNTIF(_xlpm.fer,_xlpm.dfin)>0),0,MAX(0,MIN(_xlpm.fin-_xlpm.dfin,IF(WEEKDAY(_xlpm.dfin,2)=5,14/24,17.5/24))-8/24)*24),ROUND(MAX(0,_xlpm.hfin-_xlpm.hini),1))))) | Q3: 46247.694 | R3: =IF(SCTR_Brokers[[#This Row],[FechaRecepcion]]="","",_xlfn.LET(_xlpm.fer,LISTAS!$L$3:$L$100,_xlpm.ep,DATE(2000,1,1),_xlpm.ini,SCTR_Brokers[[#This Row],[FechaRecepcion]],_xlpm.fin,IF(SCTR_Brokers[[#This Row],[Fecha_Cierre]]<>"",SCTR_Brokers[[#This Row],[Fecha_Cierre]],NOW()),_xlpm.dini,INT(_xlpm.ini),_xlpm.dfin,INT(_xlpm.fin),_xlpm.hini,9.5*NETWORKDAYS.INTL(_xlpm.ep,_xlpm.dini-1,"0000111",_xlpm.fer)+6*NETWORKDAYS.INTL(_xlpm.ep,_xlpm.dini-1,"1111011",_xlpm.fer)+IF(OR(WEEKDAY(_xlpm.dini,2)>5,COUNTIF(_xlpm.fer,_xlpm.dini)>0),0,MAX(0,MIN(_xlpm.ini-_xlpm.dini,IF(WEEKDAY(_xlpm.dini,2)=5,14/24,17.5/24))-8/24)*24),_xlpm.hfin,9.5*NETWORKDAYS.INTL(_xlpm.ep,_xlpm.dfin-1,"0000111",_xlpm.fer)+6*NETWORKDAYS.INTL(_xlpm.ep,_xlpm.dfin-1,"1111011",_xlpm.fer)+IF(OR(WEEKDAY(_xlpm.dfin,2)>5,COUNTIF(_xlpm.fer,_xlpm.dfin)>0),0,MAX(0,MIN(_xlpm.fin-_xlpm.dfin,IF(WEEKDAY(_xlpm.dfin,2)=5,14/24,17.5/24))-8/24)*24),_xlpm.hrs,IF(SCTR_Brokers[[#This Row],[Estado]]="FINALIZADO",MAX(0,_xlpm.hfin-_xlpm.hini),IF(SCTR_Brokers[[#This Row],[Horas_Transcurridas]]="",MAX(0,_xlpm.hfin-_xlpm.hini),SCTR_Brokers[[#This Row],[Horas_Transcurridas]])),IF(_xlpm.hrs<=LISTAS!$E$3,LISTAS!$J$3,LISTAS!$J$4))) -> Dentro | T3: =IF(SCTR_Brokers[[#This Row],[FechaRecepcion]]="","",TEXT(SCTR_Brokers[[#This Row],[FechaRecepcion]],"mmmm")&" "&YEAR(SCTR_Brokers[[#This Row],[FechaRecepcion]])) -> agosto 2026 | U3: =IF(SCTR_Brokers[[#This Row],[Estado]]="FINALIZADO",1,0) -> 1 | V3: =IF(SCTR_Brokers[[#This Row],[FechaRecepcion]]="","",IF(SCTR_Brokers[[#This Row],[Estado]]="FINALIZADO",0,1)) -> 0 | W3: =IF(AND(SCTR_Brokers[[#This Row],[Estado]]="FINALIZADO",SCTR_Brokers[[#This Row],[Plazo]]=LISTAS!$J$3),1,0) -> 1 | X3: =IF(AND(SCTR_Brokers[[#This Row],[Estado]]="FINALIZADO",SCTR_Brokers[[#This Row],[Plazo]]=LISTAS!$J$4),1,0) -> 0 | Y3: =IF(AND(SCTR_Brokers[[#This Row],[Estado]]<>"FINALIZADO",SCTR_Brokers[[#This Row],[Plazo]]=LISTAS!$J$4),1,0) -> 0 | Z3: =IF(SCTR_Brokers[[#This Row],[Fecha_Solic_Informe]]="",0,1) -> 0 | AA3: =IF(SCTR_Brokers[[#This Row],[Fecha_Informe]]="",0,1) -> 0 | AB3: =IF(AND(SCTR_Brokers[[#This Row],[Fecha_Solic_Informe]]<>"",SCTR_Brokers[[#This Row],[Fecha_Informe]]=""),1,0) -> 0 | AC3: =IF(AND(SCTR_Brokers[[#This Row],[Fecha_Solic_Informe]]<>"",SCTR_Brokers[[#This Row],[Fecha_Informe]]<>""),ROUND((SCTR_Brokers[[#This Row],[Fecha_Informe]]-SCTR_Brokers[[#This Row],[Fecha_Solic_Informe]])*24,1),"")
A4: AAQkADdkNThjNzFkLWM0ZmMtNDJhYS04MDVlLTIwNzE4ZDI1Mzg4YgAQAJt1sQcA00SYr0ix69nzDCs= | C4: =IF(SCTR_Brokers[[#This Row],[FechaRecepcion]]="","",SCTR_Brokers[[#This Row],[ConversationId]]&"-"&TEXT(SCTR_Brokers[[#This Row],[FechaRecepcion]],"aaaammddhhmmss")) -> AAQkADdkNThjNzFkLWM0ZmMtNDJhYS04MDVlLTIwNzE4ZDI1Mzg4YgAQAJt1sQcA00SYr0ix69nzDCs=-20260813152212 | D4: DERIVACION PROVEEDOR ECOGRAFIA CODO - CONTRATISTAS MINEROS ALFA - SCTR SALUD | E4: ARTHUR GALLAGHER | F4: 46247.64 | G4: 46251.334 | H4: Jackeline_Murayari@ajg.com | I4: FINALIZADO | K4: SCTR SALUD | N4: =IF(SCTR_Brokers[[#This Row],[FechaRecepcion]]="","",IF(SCTR_Brokers[[#This Row],[Estado]]="FINALIZADO","",IF(SCTR_Brokers[[#This Row],[FechaUltimaRespuesta]]="","",_xlfn.LET(_xlpm.fer,LISTAS!$L$3:$L$100,_xlpm.ep,DATE(2000,1,1),_xlpm.ini,SCTR_Brokers[[#This Row],[FechaUltimaRespuesta]],_xlpm.fin,NOW(),_xlpm.dini,INT(_xlpm.ini),_xlpm.dfin,INT(_xlpm.fin),_xlpm.hini,9.5*NETWORKDAYS.INTL(_xlpm.ep,_xlpm.dini-1,"0000111",_xlpm.fer)+6*NETWORKDAYS.INTL(_xlpm.ep,_xlpm.dini-1,"1111011",_xlpm.fer)+IF(OR(WEEKDAY(_xlpm.dini,2)>5,COUNTIF(_xlpm.fer,_xlpm.dini)>0),0,MAX(0,MIN(_xlpm.ini-_xlpm.dini,IF(WEEKDAY(_xlpm.dini,2)=5,14/24,17.5/24))-8/24)*24),_xlpm.hfin,9.5*NETWORKDAYS.INTL(_xlpm.ep,_xlpm.dfin-1,"0000111",_xlpm.fer)+6*NETWORKDAYS.INTL(_xlpm.ep,_xlpm.dfin-1,"1111011",_xlpm.fer)+IF(OR(WEEKDAY(_xlpm.dfin,2)>5,COUNTIF(_xlpm.fer,_xlpm.dfin)>0),0,MAX(0,MIN(_xlpm.fin-_xlpm.dfin,IF(WEEKDAY(_xlpm.dfin,2)=5,14/24,17.5/24))-8/24)*24),ROUND(MAX(0,_xlpm.hfin-_xlpm.hini),1))))) | Q4: 46251.334 | R4: =IF(SCTR_Brokers[[#This Row],[FechaRecepcion]]="","",_xlfn.LET(_xlpm.fer,LISTAS!$L$3:$L$100,_xlpm.ep,DATE(2000,1,1),_xlpm.ini,SCTR_Brokers[[#This Row],[FechaRecepcion]],_xlpm.fin,IF(SCTR_Brokers[[#This Row],[Fecha_Cierre]]<>"",SCTR_Brokers[[#This Row],[Fecha_Cierre]],NOW()),_xlpm.dini,INT(_xlpm.ini),_xlpm.dfin,INT(_xlpm.fin),_xlpm.hini,9.5*NETWORKDAYS.INTL(_xlpm.ep,_xlpm.dini-1,"0000111",_xlpm.fer)+6*NETWORKDAYS.INTL(_xlpm.ep,_xlpm.dini-1,"1111011",_xlpm.fer)+IF(OR(WEEKDAY(_xlpm.dini,2)>5,COUNTIF(_xlpm.fer,_xlpm.dini)>0),0,MAX(0,MIN(_xlpm.ini-_xlpm.dini,IF(WEEKDAY(_xlpm.dini,2)=5,14/24,17.5/24))-8/24)*24),_xlpm.hfin,9.5*NETWORKDAYS.INTL(_xlpm.ep,_xlpm.dfin-1,"0000111",_xlpm.fer)+6*NETWORKDAYS.INTL(_xlpm.ep,_xlpm.dfin-1,"1111011",_xlpm.fer)+IF(OR(WEEKDAY(_xlpm.dfin,2)>5,COUNTIF(_xlpm.fer,_xlpm.dfin)>0),0,MAX(0,MIN(_xlpm.fin-_xlpm.dfin,IF(WEEKDAY(_xlpm.dfin,2)=5,14/24,17.5/24))-8/24)*24),_xlpm.hrs,IF(SCTR_Brokers[[#This Row],[Estado]]="FINALIZADO",MAX(0,_xlpm.hfin-_xlpm.hini),IF(SCTR_Brokers[[#This Row],[Horas_Transcurridas]]="",MAX(0,_xlpm.hfin-_xlpm.hini),SCTR_Brokers[[#This Row],[Horas_Transcurridas]])),IF(_xlpm.hrs<=LISTAS!$E$3,LISTAS!$J$3,LISTAS!$J$4))) -> Fuera | T4: =IF(SCTR_Brokers[[#This Row],[FechaRecepcion]]="","",TEXT(SCTR_Brokers[[#This Row],[FechaRecepcion]],"mmmm")&" "&YEAR(SCTR_Brokers[[#This Row],[FechaRecepcion]])) -> agosto 2026 | U4: =IF(SCTR_Brokers[[#This Row],[Estado]]="FINALIZADO",1,0) -> 1 | V4: =IF(SCTR_Brokers[[#This Row],[FechaRecepcion]]="","",IF(SCTR_Brokers[[#This Row],[Estado]]="FINALIZADO",0,1)) -> 0 | W4: =IF(AND(SCTR_Brokers[[#This Row],[Estado]]="FINALIZADO",SCTR_Brokers[[#This Row],[Plazo]]=LISTAS!$J$3),1,0) -> 0 | X4: =IF(AND(SCTR_Brokers[[#This Row],[Estado]]="FINALIZADO",SCTR_Brokers[[#This Row],[Plazo]]=LISTAS!$J$4),1,0) -> 1 | Y4: =IF(AND(SCTR_Brokers[[#This Row],[Estado]]<>"FINALIZADO",SCTR_Brokers[[#This Row],[Plazo]]=LISTAS!$J$4),1,0) -> 0 | Z4: =IF(SCTR_Brokers[[#This Row],[Fecha_Solic_Informe]]="",0,1) -> 0 | AA4: =IF(SCTR_Brokers[[#This Row],[Fecha_Informe]]="",0,1) -> 0 | AB4: =IF(AND(SCTR_Brokers[[#This Row],[Fecha_Solic_Informe]]<>"",SCTR_Brokers[[#This Row],[Fecha_Informe]]=""),1,0) -> 0 | AC4: =IF(AND(SCTR_Brokers[[#This Row],[Fecha_Solic_Informe]]<>"",SCTR_Brokers[[#This Row],[Fecha_Informe]]<>""),ROUND((SCTR_Brokers[[#This Row],[Fecha_Informe]]-SCTR_Brokers[[#This Row],[Fecha_Solic_Informe]])*24,1),"")
A5: AAQkADdkNThjNzFkLWM0ZmMtNDJhYS04MDVlLTIwNzE4ZDI1Mzg4YgAQAO6d2gmjtd5Kpw0zInaJXh8= | C5: =IF(SCTR_Brokers[[#This Row],[FechaRecepcion]]="","",SCTR_Brokers[[#This Row],[ConversationId]]&"-"&TEXT(SCTR_Brokers[[#This Row],[FechaRecepcion]],"aaaammddhhmmss")) -> AAQkADdkNThjNzFkLWM0ZmMtNDJhYS04MDVlLTIwNzE4ZDI1Mzg4YgAQAO6d2gmjtd5Kpw0zInaJXh8=-20260813160806 | D5: Re: GRUPO INTERCORP // HOMECENTER // SOLICITUD DE FERULA - ACCIDENTE DE TRABAJO | E5: MARSH | F5: 46247.672 | G5: 46247.706 | H5: sctrsalud@mapfre.com.pe | I5: FINALIZADO | K5: SCTR SALUD | N5: =IF(SCTR_Brokers[[#This Row],[FechaRecepcion]]="","",IF(SCTR_Brokers[[#This Row],[Estado]]="FINALIZADO","",IF(SCTR_Brokers[[#This Row],[FechaUltimaRespuesta]]="","",_xlfn.LET(_xlpm.fer,LISTAS!$L$3:$L$100,_xlpm.ep,DATE(2000,1,1),_xlpm.ini,SCTR_Brokers[[#This Row],[FechaUltimaRespuesta]],_xlpm.fin,NOW(),_xlpm.dini,INT(_xlpm.ini),_xlpm.dfin,INT(_xlpm.fin),_xlpm.hini,9.5*NETWORKDAYS.INTL(_xlpm.ep,_xlpm.dini-1,"0000111",_xlpm.fer)+6*NETWORKDAYS.INTL(_xlpm.ep,_xlpm.dini-1,"1111011",_xlpm.fer)+IF(OR(WEEKDAY(_xlpm.dini,2)>5,COUNTIF(_xlpm.fer,_xlpm.dini)>0),0,MAX(0,MIN(_xlpm.ini-_xlpm.dini,IF(WEEKDAY(_xlpm.dini,2)=5,14/24,17.5/24))-8/24)*24),_xlpm.hfin,9.5*NETWORKDAYS.INTL(_xlpm.ep,_xlpm.dfin-1,"0000111",_xlpm.fer)+6*NETWORKDAYS.INTL(_xlpm.ep,_xlpm.dfin-1,"1111011",_xlpm.fer)+IF(OR(WEEKDAY(_xlpm.dfin,2)>5,COUNTIF(_xlpm.fer,_xlpm.dfin)>0),0,MAX(0,MIN(_xlpm.fin-_xlpm.dfin,IF(WEEKDAY(_xlpm.dfin,2)=5,14/24,17.5/24))-8/24)*24),ROUND(MAX(0,_xlpm.hfin-_xlpm.hini),1))))) | Q5: 46247.706 | R5: =IF(SCTR_Brokers[[#This Row],[FechaRecepcion]]="","",_xlfn.LET(_xlpm.fer,LISTAS!$L$3:$L$100,_xlpm.ep,DATE(2000,1,1),_xlpm.ini,SCTR_Brokers[[#This Row],[FechaRecepcion]],_xlpm.fin,IF(SCTR_Brokers[[#This Row],[Fecha_Cierre]]<>"",SCTR_Brokers[[#This Row],[Fecha_Cierre]],NOW()),_xlpm.dini,INT(_xlpm.ini),_xlpm.dfin,INT(_xlpm.fin),_xlpm.hini,9.5*NETWORKDAYS.INTL(_xlpm.ep,_xlpm.dini-1,"0000111",_xlpm.fer)+6*NETWORKDAYS.INTL(_xlpm.ep,_xlpm.dini-1,"1111011",_xlpm.fer)+IF(OR(WEEKDAY(_xlpm.dini,2)>5,COUNTIF(_xlpm.fer,_xlpm.dini)>0),0,MAX(0,MIN(_xlpm.ini-_xlpm.dini,IF(WEEKDAY(_xlpm.dini,2)=5,14/24,17.5/24))-8/24)*24),_xlpm.hfin,9.5*NETWORKDAYS.INTL(_xlpm.ep,_xlpm.dfin-1,"0000111",_xlpm.fer)+6*NETWORKDAYS.INTL(_xlpm.ep,_xlpm.dfin-1,"1111011",_xlpm.fer)+IF(OR(WEEKDAY(_xlpm.dfin,2)>5,COUNTIF(_xlpm.fer,_xlpm.dfin)>0),0,MAX(0,MIN(_xlpm.fin-_xlpm.dfin,IF(WEEKDAY(_xlpm.dfin,2)=5,14/24,17.5/24))-8/24)*24),_xlpm.hrs,IF(SCTR_Brokers[[#This Row],[Estado]]="FINALIZADO",MAX(0,_xlpm.hfin-_xlpm.hini),IF(SCTR_Brokers[[#This Row],[Horas_Transcurridas]]="",MAX(0,_xlpm.hfin-_xlpm.hini),SCTR_Brokers[[#This Row],[Horas_Transcurridas]])),IF(_xlpm.hrs<=LISTAS!$E$3,LISTAS!$J$3,LISTAS!$J$4))) -> Dentro | T5: =IF(SCTR_Brokers[[#This Row],[FechaRecepcion]]="","",TEXT(SCTR_Brokers[[#This Row],[FechaRecepcion]],"mmmm")&" "&YEAR(SCTR_Brokers[[#This Row],[FechaRecepcion]])) -> agosto 2026 | U5: =IF(SCTR_Brokers[[#This Row],[Estado]]="FINALIZADO",1,0) -> 1 | V5: =IF(SCTR_Brokers[[#This Row],[FechaRecepcion]]="","",IF(SCTR_Brokers[[#This Row],[Estado]]="FINALIZADO",0,1)) -> 0 | W5: =IF(AND(SCTR_Brokers[[#This Row],[Estado]]="FINALIZADO",SCTR_Brokers[[#This Row],[Plazo]]=LISTAS!$J$3),1,0) -> 1 | X5: =IF(AND(SCTR_Brokers[[#This Row],[Estado]]="FINALIZADO",SCTR_Brokers[[#This Row],[Plazo]]=LISTAS!$J$4),1,0) -> 0 | Y5: =IF(AND(SCTR_Brokers[[#This Row],[Estado]]<>"FINALIZADO",SCTR_Brokers[[#This Row],[Plazo]]=LISTAS!$J$4),1,0) -> 0 | Z5: =IF(SCTR_Brokers[[#This Row],[Fecha_Solic_Informe]]="",0,1) -> 0 | AA5: =IF(SCTR_Brokers[[#This Row],[Fecha_Informe]]="",0,1) -> 0 | AB5: =IF(AND(SCTR_Brokers[[#This Row],[Fecha_Solic_Informe]]<>"",SCTR_Brokers[[#This Row],[Fecha_Informe]]=""),1,0) -> 0 | AC5: =IF(AND(SCTR_Brokers[[#This Row],[Fecha_Solic_Informe]]<>"",SCTR_Brokers[[#This Row],[Fecha_Informe]]<>""),ROUND((SCTR_Brokers[[#This Row],[Fecha_Informe]]-SCTR_Brokers[[#This Row],[Fecha_Solic_Informe]])*24,1),"")
A6: AAQkADdkNThjNzFkLWM0ZmMtNDJhYS04MDVlLTIwNzE4ZDI1Mzg4YgAQAJbH0u8xpU60thd9UB-4onM= | C6: =IF(SCTR_Brokers[[#This Row],[FechaRecepcion]]="","",SCTR_Brokers[[#This Row],[ConversationId]]&"-"&TEXT(SCTR_Brokers[[#This Row],[FechaRecepcion]],"aaaammddhhmmss")) -> AAQkADdkNThjNzFkLWM0ZmMtNDJhYS04MDVlLTIwNzE4ZDI1Mzg4YgAQAJbH0u8xpU60thd9UB-4onM=-20260813165004 | D6: RV: PUMARRUMI CASTILLO, BRYGEL: Solicitud 1131705 | E6: MARSH | F6: 46247.701 | G6: 46247.711 | H6: sctrsalud@mapfre.com.pe | I6: FINALIZADO | K6: SCTR SALUD | N6: =IF(SCTR_Brokers[[#This Row],[FechaRecepcion]]="","",IF(SCTR_Brokers[[#This Row],[Estado]]="FINALIZADO","",IF(SCTR_Brokers[[#This Row],[FechaUltimaRespuesta]]="","",_xlfn.LET(_xlpm.fer,LISTAS!$L$3:$L$100,_xlpm.ep,DATE(2000,1,1),_xlpm.ini,SCTR_Brokers[[#This Row],[FechaUltimaRespuesta]],_xlpm.fin,NOW(),_xlpm.dini,INT(_xlpm.ini),_xlpm.dfin,INT(_xlpm.fin),_xlpm.hini,9.5*NETWORKDAYS.INTL(_xlpm.ep,_xlpm.dini-1,"0000111",_xlpm.fer)+6*NETWORKDAYS.INTL(_xlpm.ep,_xlpm.dini-1,"1111011",_xlpm.fer)+IF(OR(WEEKDAY(_xlpm.dini,2)>5,COUNTIF(_xlpm.fer,_xlpm.dini)>0),0,MAX(0,MIN(_xlpm.ini-_xlpm.dini,IF(WEEKDAY(_xlpm.dini,2)=5,14/24,17.5/24))-8/24)*24),_xlpm.hfin,9.5*NETWORKDAYS.INTL(_xlpm.ep,_xlpm.dfin-1,"0000111",_xlpm.fer)+6*NETWORKDAYS.INTL(_xlpm.ep,_xlpm.dfin-1,"1111011",_xlpm.fer)+IF(OR(WEEKDAY(_xlpm.dfin,2)>5,COUNTIF(_xlpm.fer,_xlpm.dfin)>0),0,MAX(0,MIN(_xlpm.fin-_xlpm.dfin,IF(WEEKDAY(_xlpm.dfin,2)=5,14/24,17.5/24))-8/24)*24),ROUND(MAX(0,_xlpm.hfin-_xlpm.hini),1))))) | Q6: 46247.711 | R6: =IF(SCTR_Brokers[[#This Row],[FechaRecepcion]]="","",_xlfn.LET(_xlpm.fer,LISTAS!$L$3:$L$100,_xlpm.ep,DATE(2000,1,1),_xlpm.ini,SCTR_Brokers[[#This Row],[FechaRecepcion]],_xlpm.fin,IF(SCTR_Brokers[[#This Row],[Fecha_Cierre]]<>"",SCTR_Brokers[[#This Row],[Fecha_Cierre]],NOW()),_xlpm.dini,INT(_xlpm.ini),_xlpm.dfin,INT(_xlpm.fin),_xlpm.hini,9.5*NETWORKDAYS.INTL(_xlpm.ep,_xlpm.dini-1,"0000111",_xlpm.fer)+6*NETWORKDAYS.INTL(_xlpm.ep,_xlpm.dini-1,"1111011",_xlpm.fer)+IF(OR(WEEKDAY(_xlpm.dini,2)>5,COUNTIF(_xlpm.fer,_xlpm.dini)>0),0,MAX(0,MIN(_xlpm.ini-_xlpm.dini,IF(WEEKDAY(_xlpm.dini,2)=5,14/24,17.5/24))-8/24)*24),_xlpm.hfin,9.5*NETWORKDAYS.INTL(_xlpm.ep,_xlpm.dfin-1,"0000111",_xlpm.fer)+6*NETWORKDAYS.INTL(_xlpm.ep,_xlpm.dfin-1,"1111011",_xlpm.fer)+IF(OR(WEEKDAY(_xlpm.dfin,2)>5,COUNTIF(_xlpm.fer,_xlpm.dfin)>0),0,MAX(0,MIN(_xlpm.fin-_xlpm.dfin,IF(WEEKDAY(_xlpm.dfin,2)=5,14/24,17.5/24))-8/24)*24),_xlpm.hrs,IF(SCTR_Brokers[[#This Row],[Estado]]="FINALIZADO",MAX(0,_xlpm.hfin-_xlpm.hini),IF(SCTR_Brokers[[#This Row],[Horas_Transcurridas]]="",MAX(0,_xlpm.hfin-_xlpm.hini),SCTR_Brokers[[#This Row],[Horas_Transcurridas]])),IF(_xlpm.hrs<=LISTAS!$E$3,LISTAS!$J$3,LISTAS!$J$4))) -> Dentro | T6: =IF(SCTR_Brokers[[#This Row],[FechaRecepcion]]="","",TEXT(SCTR_Brokers[[#This Row],[FechaRecepcion]],"mmmm")&" "&YEAR(SCTR_Brokers[[#This Row],[FechaRecepcion]])) -> agosto 2026 | U6: =IF(SCTR_Brokers[[#This Row],[Estado]]="FINALIZADO",1,0) -> 1 | V6: =IF(SCTR_Brokers[[#This Row],[FechaRecepcion]]="","",IF(SCTR_Brokers[[#This Row],[Estado]]="FINALIZADO",0,1)) -> 0 | W6: =IF(AND(SCTR_Brokers[[#This Row],[Estado]]="FINALIZADO",SCTR_Brokers[[#This Row],[Plazo]]=LISTAS!$J$3),1,0) -> 1 | X6: =IF(AND(SCTR_Brokers[[#This Row],[Estado]]="FINALIZADO",SCTR_Brokers[[#This Row],[Plazo]]=LISTAS!$J$4),1,0) -> 0 | Y6: =IF(AND(SCTR_Brokers[[#This Row],[Estado]]<>"FINALIZADO",SCTR_Brokers[[#This Row],[Plazo]]=LISTAS!$J$4),1,0) -> 0 | Z6: =IF(SCTR_Brokers[[#This Row],[Fecha_Solic_Informe]]="",0,1) -> 0 | AA6: =IF(SCTR_Brokers[[#This Row],[Fecha_Informe]]="",0,1) -> 0 | AB6: =IF(AND(SCTR_Brokers[[#This Row],[Fecha_Solic_Informe]]<>"",SCTR_Brokers[[#This Row],[Fecha_Informe]]=""),1,0) -> 0 | AC6: =IF(AND(SCTR_Brokers[[#This Row],[Fecha_Solic_Informe]]<>"",SCTR_Brokers[[#This Row],[Fecha_Informe]]<>""),ROUND((SCTR_Brokers[[#This Row],[Fecha_Informe]]-SCTR_Brokers[[#This Row],[Fecha_Solic_Informe]])*24,1),"")
A7: AAQkADdkNThjNzFkLWM0ZmMtNDJhYS04MDVlLTIwNzE4ZDI1Mzg4YgAQAKj4wOyC3j1JjF2bNr2RW68= | C7: =IF(SCTR_Brokers[[#This Row],[FechaRecepcion]]="","",SCTR_Brokers[[#This Row],[ConversationId]]&"-"&TEXT(SCTR_Brokers[[#This Row],[FechaRecepcion]],"aaaammddhhmmss")) -> AAQkADdkNThjNzFkLWM0ZmMtNDJhYS04MDVlLTIwNzE4ZDI1Mzg4YgAQAKj4wOyC3j1JjF2bNr2RW68=-20260813172429 | D7: RV: ACCIDENTE DE TRABAJO- COLABORADOR COCINA EDDY AGUILAR VIZCARRA // APROBACION CARTA DE GARANTIA // SCTR SALUD - NESSUS HOTELES PERU | E7: MARSH | F7: 46247.725 | G7: 46248.498 | H7: sctrsalud@mapfre.com.pe | I7: FINALIZADO | K7: SCTR SALUD | N7: =IF(SCTR_Brokers[[#This Row],[FechaRecepcion]]="","",IF(SCTR_Brokers[[#This Row],[Estado]]="FINALIZADO","",IF(SCTR_Brokers[[#This Row],[FechaUltimaRespuesta]]="","",_xlfn.LET(_xlpm.fer,LISTAS!$L$3:$L$100,_xlpm.ep,DATE(2000,1,1),_xlpm.ini,SCTR_Brokers[[#This Row],[FechaUltimaRespuesta]],_xlpm.fin,NOW(),_xlpm.dini,INT(_xlpm.ini),_xlpm.dfin,INT(_xlpm.fin),_xlpm.hini,9.5*NETWORKDAYS.INTL(_xlpm.ep,_xlpm.dini-1,"0000111",_xlpm.fer)+6*NETWORKDAYS.INTL(_xlpm.ep,_xlpm.dini-1,"1111011",_xlpm.fer)+IF(OR(WEEKDAY(_xlpm.dini,2)>5,COUNTIF(_xlpm.fer,_xlpm.dini)>0),0,MAX(0,MIN(_xlpm.ini-_xlpm.dini,IF(WEEKDAY(_xlpm.dini,2)=5,14/24,17.5/24))-8/24)*24),_xlpm.hfin,9.5*NETWORKDAYS.INTL(_xlpm.ep,_xlpm.dfin-1,"0000111",_xlpm.fer)+6*NETWORKDAYS.INTL(_xlpm.ep,_xlpm.dfin-1,"1111011",_xlpm.fer)+IF(OR(WEEKDAY(_xlpm.dfin,2)>5,COUNTIF(_xlpm.fer,_xlpm.dfin)>0),0,MAX(0,MIN(_xlpm.fin-_xlpm.dfin,IF(WEEKDAY(_xlpm.dfin,2)=5,14/24,17.5/24))-8/24)*24),ROUND(MAX(0,_xlpm.hfin-_xlpm.hini),1))))) | Q7: 46248.498 | R7: =IF(SCTR_Brokers[[#This Row],[FechaRecepcion]]="","",_xlfn.LET(_xlpm.fer,LISTAS!$L$3:$L$100,_xlpm.ep,DATE(2000,1,1),_xlpm.ini,SCTR_Brokers[[#This Row],[FechaRecepcion]],_xlpm.fin,IF(SCTR_Brokers[[#This Row],[Fecha_Cierre]]<>"",SCTR_Brokers[[#This Row],[Fecha_Cierre]],NOW()),_xlpm.dini,INT(_xlpm.ini),_xlpm.dfin,INT(_xlpm.fin),_xlpm.hini,9.5*NETWORKDAYS.INTL(_xlpm.ep,_xlpm.dini-1,"0000111",_xlpm.fer)+6*NETWORKDAYS.INTL(_xlpm.ep,_xlpm.dini-1,"1111011",_xlpm.fer)+IF(OR(WEEKDAY(_xlpm.dini,2)>5,COUNTIF(_xlpm.fer,_xlpm.dini)>0),0,MAX(0,MIN(_xlpm.ini-_xlpm.dini,IF(WEEKDAY(_xlpm.dini,2)=5,14/24,17.5/24))-8/24)*24),_xlpm.hfin,9.5*NETWORKDAYS.INTL(_xlpm.ep,_xlpm.dfin-1,"0000111",_xlpm.fer)+6*NETWORKDAYS.INTL(_xlpm.ep,_xlpm.dfin-1,"1111011",_xlpm.fer)+IF(OR(WEEKDAY(_xlpm.dfin,2)>5,COUNTIF(_xlpm.fer,_xlpm.dfin)>0),0,MAX(0,MIN(_xlpm.fin-_xlpm.dfin,IF(WEEKDAY(_xlpm.dfin,2)=5,14/24,17.5/24))-8/24)*24),_xlpm.hrs,IF(SCTR_Brokers[[#This Row],[Estado]]="FINALIZADO",MAX(0,_xlpm.hfin-_xlpm.hini),IF(SCTR_Brokers[[#This Row],[Horas_Transcurridas]]="",MAX(0,_xlpm.hfin-_xlpm.hini),SCTR_Brokers[[#This Row],[Horas_Transcurridas]])),IF(_xlpm.hrs<=LISTAS!$E$3,LISTAS!$J$3,LISTAS!$J$4))) -> Dentro | T7: =IF(SCTR_Brokers[[#This Row],[FechaRecepcion]]="","",TEXT(SCTR_Brokers[[#This Row],[FechaRecepcion]],"mmmm")&" "&YEAR(SCTR_Brokers[[#This Row],[FechaRecepcion]])) -> agosto 2026 | U7: =IF(SCTR_Brokers[[#This Row],[Estado]]="FINALIZADO",1,0) -> 1 | V7: =IF(SCTR_Brokers[[#This Row],[FechaRecepcion]]="","",IF(SCTR_Brokers[[#This Row],[Estado]]="FINALIZADO",0,1)) -> 0 | W7: =IF(AND(SCTR_Brokers[[#This Row],[Estado]]="FINALIZADO",SCTR_Brokers[[#This Row],[Plazo]]=LISTAS!$J$3),1,0) -> 1 | X7: =IF(AND(SCTR_Brokers[[#This Row],[Estado]]="FINALIZADO",SCTR_Brokers[[#This Row],[Plazo]]=LISTAS!$J$4),1,0) -> 0 | Y7: =IF(AND(SCTR_Brokers[[#This Row],[Estado]]<>"FINALIZADO",SCTR_Brokers[[#This Row],[Plazo]]=LISTAS!$J$4),1,0) -> 0 | Z7: =IF(SCTR_Brokers[[#This Row],[Fecha_Solic_Informe]]="",0,1) -> 0 | AA7: =IF(SCTR_Brokers[[#This Row],[Fecha_Informe]]="",0,1) -> 0 | AB7: =IF(AND(SCTR_Brokers[[#This Row],[Fecha_Solic_Informe]]<>"",SCTR_Brokers[[#This Row],[Fecha_Informe]]=""),1,0) -> 0 | AC7: =IF(AND(SCTR_Brokers[[#This Row],[Fecha_Solic_Informe]]<>"",SCTR_Brokers[[#This Row],[Fecha_Informe]]<>""),ROUND((SCTR_Brokers[[#This Row],[Fecha_Informe]]-SCTR_Brokers[[#This Row],[Fecha_Solic_Informe]])*24,1),"")
A8: AAQkADdkNThjNzFkLWM0ZmMtNDJhYS04MDVlLTIwNzE4ZDI1Mzg4YgAQAEWL9Z2HU35Ah8_6EELq5Sc= | C8: =IF(SCTR_Brokers[[#This Row],[FechaRecepcion]]="","",SCTR_Brokers[[#This Row],[ConversationId]]&"-"&TEXT(SCTR_Brokers[[#This Row],[FechaRecepcion]],"aaaammddhhmmss")) -> AAQkADdkNThjNzFkLWM0ZmMtNDJhYS04MDVlLTIwNzE4ZDI1Mzg4YgAQAEWL9Z2HU35Ah8_6EELq5Sc=-20260813173727 | D8: CENCOSUD RETAIL PERU S.A. - AP - BACALLA GUTIERREZ LEYZI CAROLA - CONSULTA DE ACTIVACION AP | E8: ARTHUR GALLAGHER | F8: 46247.734 | G8: 46247.749 | H8: sctrsalud@mapfre.com.pe | I8: FINALIZADO | K8: SCTR SALUD | N8: =IF(SCTR_Brokers[[#This Row],[FechaRecepcion]]="","",IF(SCTR_Brokers[[#This Row],[Estado]]="FINALIZADO","",IF(SCTR_Brokers[[#This Row],[FechaUltimaRespuesta]]="","",_xlfn.LET(_xlpm.fer,LISTAS!$L$3:$L$100,_xlpm.ep,DATE(2000,1,1),_xlpm.ini,SCTR_Brokers[[#This Row],[FechaUltimaRespuesta]],_xlpm.fin,NOW(),_xlpm.dini,INT(_xlpm.ini),_xlpm.dfin,INT(_xlpm.fin),_xlpm.hini,9.5*NETWORKDAYS.INTL(_xlpm.ep,_xlpm.dini-1,"0000111",_xlpm.fer)+6*NETWORKDAYS.INTL(_xlpm.ep,_xlpm.dini-1,"1111011",_xlpm.fer)+IF(OR(WEEKDAY(_xlpm.dini,2)>5,COUNTIF(_xlpm.fer,_xlpm.dini)>0),0,MAX(0,MIN(_xlpm.ini-_xlpm.dini,IF(WEEKDAY(_xlpm.dini,2)=5,14/24,17.5/24))-8/24)*24),_xlpm.hfin,9.5*NETWORKDAYS.INTL(_xlpm.ep,_xlpm.dfin-1,"0000111",_xlpm.fer)+6*NETWORKDAYS.INTL(_xlpm.ep,_xlpm.dfin-1,"1111011",_xlpm.fer)+IF(OR(WEEKDAY(_xlpm.dfin,2)>5,COUNTIF(_xlpm.fer,_xlpm.dfin)>0),0,MAX(0,MIN(_xlpm.fin-_xlpm.dfin,IF(WEEKDAY(_xlpm.dfin,2)=5,14/24,17.5/24))-8/24)*24),ROUND(MAX(0,_xlpm.hfin-_xlpm.hini),1))))) | Q8: 46247.749 | R8: =IF(SCTR_Brokers[[#This Row],[FechaRecepcion]]="","",_xlfn.LET(_xlpm.fer,LISTAS!$L$3:$L$100,_xlpm.ep,DATE(2000,1,1),_xlpm.ini,SCTR_Brokers[[#This Row],[FechaRecepcion]],_xlpm.fin,IF(SCTR_Brokers[[#This Row],[Fecha_Cierre]]<>"",SCTR_Brokers[[#This Row],[Fecha_Cierre]],NOW()),_xlpm.dini,INT(_xlpm.ini),_xlpm.dfin,INT(_xlpm.fin),_xlpm.hini,9.5*NETWORKDAYS.INTL(_xlpm.ep,_xlpm.dini-1,"0000111",_xlpm.fer)+6*NETWORKDAYS.INTL(_xlpm.ep,_xlpm.dini-1,"1111011",_xlpm.fer)+IF(OR(WEEKDAY(_xlpm.dini,2)>5,COUNTIF(_xlpm.fer,_xlpm.dini)>0),0,MAX(0,MIN(_xlpm.ini-_xlpm.dini,IF(WEEKDAY(_xlpm.dini,2)=5,14/24,17.5/24))-8/24)*24),_xlpm.hfin,9.5*NETWORKDAYS.INTL(_xlpm.ep,_xlpm.dfin-1,"0000111",_xlpm.fer)+6*NETWORKDAYS.INTL(_xlpm.ep,_xlpm.dfin-1,"1111011",_xlpm.fer)+IF(OR(WEEKDAY(_xlpm.dfin,2)>5,COUNTIF(_xlpm.fer,_xlpm.dfin)>0),0,MAX(0,MIN(_xlpm.fin-_xlpm.dfin,IF(WEEKDAY(_xlpm.dfin,2)=5,14/24,17.5/24))-8/24)*24),_xlpm.hrs,IF(SCTR_Brokers[[#This Row],[Estado]]="FINALIZADO",MAX(0,_xlpm.hfin-_xlpm.hini),IF(SCTR_Brokers[[#This Row],[Horas_Transcurridas]]="",MAX(0,_xlpm.hfin-_xlpm.hini),SCTR_Brokers[[#This Row],[Horas_Transcurridas]])),IF(_xlpm.hrs<=LISTAS!$E$3,LISTAS!$J$3,LISTAS!$J$4))) -> Dentro | T8: =IF(SCTR_Brokers[[#This Row],[FechaRecepcion]]="","",TEXT(SCTR_Brokers[[#This Row],[FechaRecepcion]],"mmmm")&" "&YEAR(SCTR_Brokers[[#This Row],[FechaRecepcion]])) -> agosto 2026 | U8: =IF(SCTR_Brokers[[#This Row],[Estado]]="FINALIZADO",1,0) -> 1 | V8: =IF(SCTR_Brokers[[#This Row],[FechaRecepcion]]="","",IF(SCTR_Brokers[[#This Row],[Estado]]="FINALIZADO",0,1)) -> 0 | W8: =IF(AND(SCTR_Brokers[[#This Row],[Estado]]="FINALIZADO",SCTR_Brokers[[#This Row],[Plazo]]=LISTAS!$J$3),1,0) -> 1 | X8: =IF(AND(SCTR_Brokers[[#This Row],[Estado]]="FINALIZADO",SCTR_Brokers[[#This Row],[Plazo]]=LISTAS!$J$4),1,0) -> 0 | Y8: =IF(AND(SCTR_Brokers[[#This Row],[Estado]]<>"FINALIZADO",SCTR_Brokers[[#This Row],[Plazo]]=LISTAS!$J$4),1,0) -> 0 | Z8: =IF(SCTR_Brokers[[#This Row],[Fecha_Solic_Informe]]="",0,1) -> 0 | AA8: =IF(SCTR_Brokers[[#This Row],[Fecha_Informe]]="",0,1) -> 0 | AB8: =IF(AND(SCTR_Brokers[[#This Row],[Fecha_Solic_Informe]]<>"",SCTR_Brokers[[#This Row],[Fecha_Informe]]=""),1,0) -> 0 | AC8: =IF(AND(SCTR_Brokers[[#This Row],[Fecha_Solic_Informe]]<>"",SCTR_Brokers[[#This Row],[Fecha_Informe]]<>""),ROUND((SCTR_Brokers[[#This Row],[Fecha_Informe]]-SCTR_Brokers[[#This Row],[Fecha_Solic_Informe]])*24,1),"")
A9: AAQkADdkNThjNzFkLWM0ZmMtNDJhYS04MDVlLTIwNzE4ZDI1Mzg4YgAQAEvkGJ0JTE4hpm6yW1eczK8= | C9: =IF(SCTR_Brokers[[#This Row],[FechaRecepcion]]="","",SCTR_Brokers[[#This Row],[ConversationId]]&"-"&TEXT(SCTR_Brokers[[#This Row],[FechaRecepcion]],"aaaammddhhmmss")) -> AAQkADdkNThjNzFkLWM0ZmMtNDJhYS04MDVlLTIwNzE4ZDI1Mzg4YgAQAEvkGJ0JTE4hpm6yW1eczK8=-20260813174900 | D9: RE: AMABLE RECORDATORIO RE: REVISION DEL CASO- CENTENO MOYOPAZ JAVIER DE NILSON- SCTR SALUD MAPFRE- PROVEFABRICA DEL PERU SOCIEDAD ANONIMA | E9: HOWDEN | F9: 46247.742 | G9: 46251.474 | H9: sctrsalud@mapfre.com.pe | I9: FINALIZADO | K9: SCTR SALUD | N9: =IF(SCTR_Brokers[[#This Row],[FechaRecepcion]]="","",IF(SCTR_Brokers[[#This Row],[Estado]]="FINALIZADO","",IF(SCTR_Brokers[[#This Row],[FechaUltimaRespuesta]]="","",_xlfn.LET(_xlpm.fer,LISTAS!$L$3:$L$100,_xlpm.ep,DATE(2000,1,1),_xlpm.ini,SCTR_Brokers[[#This Row],[FechaUltimaRespuesta]],_xlpm.fin,NOW(),_xlpm.dini,INT(_xlpm.ini),_xlpm.dfin,INT(_xlpm.fin),_xlpm.hini,9.5*NETWORKDAYS.INTL(_xlpm.ep,_xlpm.dini-1,"0000111",_xlpm.fer)+6*NETWORKDAYS.INTL(_xlpm.ep,_xlpm.dini-1,"1111011",_xlpm.fer)+IF(OR(WEEKDAY(_xlpm.dini,2)>5,COUNTIF(_xlpm.fer,_xlpm.dini)>0),0,MAX(0,MIN(_xlpm.ini-_xlpm.dini,IF(WEEKDAY(_xlpm.dini,2)=5,14/24,17.5/24))-8/24)*24),_xlpm.hfin,9.5*NETWORKDAYS.INTL(_xlpm.ep,_xlpm.dfin-1,"0000111",_xlpm.fer)+6*NETWORKDAYS.INTL(_xlpm.ep,_xlpm.dfin-1,"1111011",_xlpm.fer)+IF(OR(WEEKDAY(_xlpm.dfin,2)>5,COUNTIF(_xlpm.fer,_xlpm.dfin)>0),0,MAX(0,MIN(_xlpm.fin-_xlpm.dfin,IF(WEEKDAY(_xlpm.dfin,2)=5,14/24,17.5/24))-8/24)*24),ROUND(MAX(0,_xlpm.hfin-_xlpm.hini),1))))) | Q9: 46251.474 | R9: =IF(SCTR_Brokers[[#This Row],[FechaRecepcion]]="","",_xlfn.LET(_xlpm.fer,LISTAS!$L$3:$L$100,_xlpm.ep,DATE(2000,1,1),_xlpm.ini,SCTR_Brokers[[#This Row],[FechaRecepcion]],_xlpm.fin,IF(SCTR_Brokers[[#This Row],[Fecha_Cierre]]<>"",SCTR_Brokers[[#This Row],[Fecha_Cierre]],NOW()),_xlpm.dini,INT(_xlpm.ini),_xlpm.dfin,INT(_xlpm.fin),_xlpm.hini,9.5*NETWORKDAYS.INTL(_xlpm.ep,_xlpm.dini-1,"0000111",_xlpm.fer)+6*NETWORKDAYS.INTL(_xlpm.ep,_xlpm.dini-1,"1111011",_xlpm.fer)+IF(OR(WEEKDAY(_xlpm.dini,2)>5,COUNTIF(_xlpm.fer,_xlpm.dini)>0),0,MAX(0,MIN(_xlpm.ini-_xlpm.dini,IF(WEEKDAY(_xlpm.dini,2)=5,14/24,17.5/24))-8/24)*24),_xlpm.hfin,9.5*NETWORKDAYS.INTL(_xlpm.ep,_xlpm.dfin-1,"0000111",_xlpm.fer)+6*NETWORKDAYS.INTL(_xlpm.ep,_xlpm.dfin-1,"1111011",_xlpm.fer)+IF(OR(WEEKDAY(_xlpm.dfin,2)>5,COUNTIF(_xlpm.fer,_xlpm.dfin)>0),0,MAX(0,MIN(_xlpm.fin-_xlpm.dfin,IF(WEEKDAY(_xlpm.dfin,2)=5,14/24,17.5/24))-8/24)*24),_xlpm.hrs,IF(SCTR_Brokers[[#This Row],[Estado]]="FINALIZADO",MAX(0,_xlpm.hfin-_xlpm.hini),IF(SCTR_Brokers[[#This Row],[Horas_Transcurridas]]="",MAX(0,_xlpm.hfin-_xlpm.hini),SCTR_Brokers[[#This Row],[Horas_Transcurridas]])),IF(_xlpm.hrs<=LISTAS!$E$3,LISTAS!$J$3,LISTAS!$J$4))) -> Fuera | T9: =IF(SCTR_Brokers[[#This Row],[FechaRecepcion]]="","",TEXT(SCTR_Brokers[[#This Row],[FechaRecepcion]],"mmmm")&" "&YEAR(SCTR_Brokers[[#This Row],[FechaRecepcion]])) -> agosto 2026 | U9: =IF(SCTR_Brokers[[#This Row],[Estado]]="FINALIZADO",1,0) -> 1 | V9: =IF(SCTR_Brokers[[#This Row],[FechaRecepcion]]="","",IF(SCTR_Brokers[[#This Row],[Estado]]="FINALIZADO",0,1)) -> 0 | W9: =IF(AND(SCTR_Brokers[[#This Row],[Estado]]="FINALIZADO",SCTR_Brokers[[#This Row],[Plazo]]=LISTAS!$J$3),1,0) -> 0 | X9: =IF(AND(SCTR_Brokers[[#This Row],[Estado]]="FINALIZADO",SCTR_Brokers[[#This Row],[Plazo]]=LISTAS!$J$4),1,0) -> 1 | Y9: =IF(AND(SCTR_Brokers[[#This Row],[Estado]]<>"FINALIZADO",SCTR_Brokers[[#This Row],[Plazo]]=LISTAS!$J$4),1,0) -> 0 | Z9: =IF(SCTR_Brokers[[#This Row],[Fecha_Solic_Informe]]="",0,1) -> 0 | AA9: =IF(SCTR_Brokers[[#This Row],[Fecha_Informe]]="",0,1) -> 0 | AB9: =IF(AND(SCTR_Brokers[[#This Row],[Fecha_Solic_Informe]]<>"",SCTR_Brokers[[#This Row],[Fecha_Informe]]=""),1,0) -> 0 | AC9: =IF(AND(SCTR_Brokers[[#This Row],[Fecha_Solic_Informe]]<>"",SCTR_Brokers[[#This Row],[Fecha_Informe]]<>""),ROUND((SCTR_Brokers[[#This Row],[Fecha_Informe]]-SCTR_Brokers[[#This Row],[Fecha_Solic_Informe]])*24,1),"")
A10: AAQkADdkNThjNzFkLWM0ZmMtNDJhYS04MDVlLTIwNzE4ZDI1Mzg4YgAQAIcHvAvKE042nOSk-cjbPIc= | C10: =IF(SCTR_Brokers[[#This Row],[FechaRecepcion]]="","",SCTR_Brokers[[#This Row],[ConversationId]]&"-"&TEXT(SCTR_Brokers[[#This Row],[FechaRecepcion]],"aaaammddhhmmss")) -> AAQkADdkNThjNzFkLWM0ZmMtNDJhYS04MDVlLTIwNzE4ZDI1Mzg4YgAQAIcHvAvKE042nOSk-cjbPIc=-20260813220218 | D10: RE: LAP - MAPFRE SCTR SALUD - ASEG. RAUL PAY TAN - SOLICITUD DE ACTIVACION AT POR PICADURA DE INSECTO | E10: ARTHUR GALLAGHER | F10: 46247.918 | G10: 46248.547 | H10: sctrsalud@mapfre.com.pe | I10: FINALIZADO | K10: SCTR SALUD | N10: =IF(SCTR_Brokers[[#This Row],[FechaRecepcion]]="","",IF(SCTR_Brokers[[#This Row],[Estado]]="FINALIZADO","",IF(SCTR_Brokers[[#This Row],[FechaUltimaRespuesta]]="","",_xlfn.LET(_xlpm.fer,LISTAS!$L$3:$L$100,_xlpm.ep,DATE(2000,1,1),_xlpm.ini,SCTR_Brokers[[#This Row],[FechaUltimaRespuesta]],_xlpm.fin,NOW(),_xlpm.dini,INT(_xlpm.ini),_xlpm.dfin,INT(_xlpm.fin),_xlpm.hini,9.5*NETWORKDAYS.INTL(_xlpm.ep,_xlpm.dini-1,"0000111",_xlpm.fer)+6*NETWORKDAYS.INTL(_xlpm.ep,_xlpm.dini-1,"1111011",_xlpm.fer)+IF(OR(WEEKDAY(_xlpm.dini,2)>5,COUNTIF(_xlpm.fer,_xlpm.dini)>0),0,MAX(0,MIN(_xlpm.ini-_xlpm.dini,IF(WEEKDAY(_xlpm.dini,2)=5,14/24,17.5/24))-8/24)*24),_xlpm.hfin,9.5*NETWORKDAYS.INTL(_xlpm.ep,_xlpm.dfin-1,"0000111",_xlpm.fer)+6*NETWORKDAYS.INTL(_xlpm.ep,_xlpm.dfin-1,"1111011",_xlpm.fer)+IF(OR(WEEKDAY(_xlpm.dfin,2)>5,COUNTIF(_xlpm.fer,_xlpm.dfin)>0),0,MAX(0,MIN(_xlpm.fin-_xlpm.dfin,IF(WEEKDAY(_xlpm.dfin,2)=5,14/24,17.5/24))-8/24)*24),ROUND(MAX(0,_xlpm.hfin-_xlpm.hini),1))))) | Q10: 46248.547 | R10: =IF(SCTR_Brokers[[#This Row],[FechaRecepcion]]="","",_xlfn.LET(_xlpm.fer,LISTAS!$L$3:$L$100,_xlpm.ep,DATE(2000,1,1),_xlpm.ini,SCTR_Brokers[[#This Row],[FechaRecepcion]],_xlpm.fin,IF(SCTR_Brokers[[#This Row],[Fecha_Cierre]]<>"",SCTR_Brokers[[#This Row],[Fecha_Cierre]],NOW()),_xlpm.dini,INT(_xlpm.ini),_xlpm.dfin,INT(_xlpm.fin),_xlpm.hini,9.5*NETWORKDAYS.INTL(_xlpm.ep,_xlpm.dini-1,"0000111",_xlpm.fer)+6*NETWORKDAYS.INTL(_xlpm.ep,_xlpm.dini-1,"1111011",_xlpm.fer)+IF(OR(WEEKDAY(_xlpm.dini,2)>5,COUNTIF(_xlpm.fer,_xlpm.dini)>0),0,MAX(0,MIN(_xlpm.ini-_xlpm.dini,IF(WEEKDAY(_xlpm.dini,2)=5,14/24,17.5/24))-8/24)*24),_xlpm.hfin,9.5*NETWORKDAYS.INTL(_xlpm.ep,_xlpm.dfin-1,"0000111",_xlpm.fer)+6*NETWORKDAYS.INTL(_xlpm.ep,_xlpm.dfin-1,"1111011",_xlpm.fer)+IF(OR(WEEKDAY(_xlpm.dfin,2)>5,COUNTIF(_xlpm.fer,_xlpm.dfin)>0),0,MAX(0,MIN(_xlpm.fin-_xlpm.dfin,IF(WEEKDAY(_xlpm.dfin,2)=5,14/24,17.5/24))-8/24)*24),_xlpm.hrs,IF(SCTR_Brokers[[#This Row],[Estado]]="FINALIZADO",MAX(0,_xlpm.hfin-_xlpm.hini),IF(SCTR_Brokers[[#This Row],[Horas_Transcurridas]]="",MAX(0,_xlpm.hfin-_xlpm.hini),SCTR_Brokers[[#This Row],[Horas_Transcurridas]])),IF(_xlpm.hrs<=LISTAS!$E$3,LISTAS!$J$3,LISTAS!$J$4))) -> Dentro | T10: =IF(SCTR_Brokers[[#This Row],[FechaRecepcion]]="","",TEXT(SCTR_Brokers[[#This Row],[FechaRecepcion]],"mmmm")&" "&YEAR(SCTR_Brokers[[#This Row],[FechaRecepcion]])) -> agosto 2026 | U10: =IF(SCTR_Brokers[[#This Row],[Estado]]="FINALIZADO",1,0) -> 1 | V10: =IF(SCTR_Brokers[[#This Row],[FechaRecepcion]]="","",IF(SCTR_Brokers[[#This Row],[Estado]]="FINALIZADO",0,1)) -> 0 | W10: =IF(AND(SCTR_Brokers[[#This Row],[Estado]]="FINALIZADO",SCTR_Brokers[[#This Row],[Plazo]]=LISTAS!$J$3),1,0) -> 1 | X10: =IF(AND(SCTR_Brokers[[#This Row],[Estado]]="FINALIZADO",SCTR_Brokers[[#This Row],[Plazo]]=LISTAS!$J$4),1,0) -> 0 | Y10: =IF(AND(SCTR_Brokers[[#This Row],[Estado]]<>"FINALIZADO",SCTR_Brokers[[#This Row],[Plazo]]=LISTAS!$J$4),1,0) -> 0 | Z10: =IF(SCTR_Brokers[[#This Row],[Fecha_Solic_Informe]]="",0,1) -> 0 | AA10: =IF(SCTR_Brokers[[#This Row],[Fecha_Informe]]="",0,1) -> 0 | AB10: =IF(AND(SCTR_Brokers[[#This Row],[Fecha_Solic_Informe]]<>"",SCTR_Brokers[[#This Row],[Fecha_Informe]]=""),1,0) -> 0 | AC10: =IF(AND(SCTR_Brokers[[#This Row],[Fecha_Solic_Informe]]<>"",SCTR_Brokers[[#This Row],[Fecha_Informe]]<>""),ROUND((SCTR_Brokers[[#This Row],[Fecha_Informe]]-SCTR_Brokers[[#This Row],[Fecha_Solic_Informe]])*24,1),"")
A11: AAQkADdkNThjNzFkLWM0ZmMtNDJhYS04MDVlLTIwNzE4ZDI1Mzg4YgAQAE6KChvywltLjo3Y0Mnsb3U= | C11: =IF(SCTR_Brokers[[#This Row],[FechaRecepcion]]="","",SCTR_Brokers[[#This Row],[ConversationId]]&"-"&TEXT(SCTR_Brokers[[#This Row],[FechaRecepcion]],"aaaammddhhmmss")) -> AAQkADdkNThjNzFkLWM0ZmMtNDJhYS04MDVlLTIwNzE4ZDI1Mzg4YgAQAE6KChvywltLjo3Y0Mnsb3U=-20260813220517 | D11: RE: LIMA AIRPORT PARTNERS / SCTR / Chang Ramirez, Jorge Luis | E11: ARTHUR GALLAGHER | F11: 46247.92 | G11: 46248.538 | H11: sctrsalud@mapfre.com.pe | I11: FINALIZADO | K11: SCTR SALUD | N11: =IF(SCTR_Brokers[[#This Row],[FechaRecepcion]]="","",IF(SCTR_Brokers[[#This Row],[Estado]]="FINALIZADO","",IF(SCTR_Brokers[[#This Row],[FechaUltimaRespuesta]]="","",_xlfn.LET(_xlpm.fer,LISTAS!$L$3:$L$100,_xlpm.ep,DATE(2000,1,1),_xlpm.ini,SCTR_Brokers[[#This Row],[FechaUltimaRespuesta]],_xlpm.fin,NOW(),_xlpm.dini,INT(_xlpm.ini),_xlpm.dfin,INT(_xlpm.fin),_xlpm.hini,9.5*NETWORKDAYS.INTL(_xlpm.ep,_xlpm.dini-1,"0000111",_xlpm.fer)+6*NETWORKDAYS.INTL(_xlpm.ep,_xlpm.dini-1,"1111011",_xlpm.fer)+IF(OR(WEEKDAY(_xlpm.dini,2)>5,COUNTIF(_xlpm.fer,_xlpm.dini)>0),0,MAX(0,MIN(_xlpm.ini-_xlpm.dini,IF(WEEKDAY(_xlpm.dini,2)=5,14/24,17.5/24))-8/24)*24),_xlpm.hfin,9.5*NETWORKDAYS.INTL(_xlpm.ep,_xlpm.dfin-1,"0000111",_xlpm.fer)+6*NETWORKDAYS.INTL(_xlpm.ep,_xlpm.dfin-1,"1111011",_xlpm.fer)+IF(OR(WEEKDAY(_xlpm.dfin,2)>5,COUNTIF(_xlpm.fer,_xlpm.dfin)>0),0,MAX(0,MIN(_xlpm.fin-_xlpm.dfin,IF(WEEKDAY(_xlpm.dfin,2)=5,14/24,17.5/24))-8/24)*24),ROUND(MAX(0,_xlpm.hfin-_xlpm.hini),1))))) | Q11: 46248.538 | R11: =IF(SCTR_Brokers[[#This Row],[FechaRecepcion]]="","",_xlfn.LET(_xlpm.fer,LISTAS!$L$3:$L$100,_xlpm.ep,DATE(2000,1,1),_xlpm.ini,SCTR_Brokers[[#This Row],[FechaRecepcion]],_xlpm.fin,IF(SCTR_Brokers[[#This Row],[Fecha_Cierre]]<>"",SCTR_Brokers[[#This Row],[Fecha_Cierre]],NOW()),_xlpm.dini,INT(_xlpm.ini),_xlpm.dfin,INT(_xlpm.fin),_xlpm.hini,9.5*NETWORKDAYS.INTL(_xlpm.ep,_xlpm.dini-1,"0000111",_xlpm.fer)+6*NETWORKDAYS.INTL(_xlpm.ep,_xlpm.dini-1,"1111011",_xlpm.fer)+IF(OR(WEEKDAY(_xlpm.dini,2)>5,COUNTIF(_xlpm.fer,_xlpm.dini)>0),0,MAX(0,MIN(_xlpm.ini-_xlpm.dini,IF(WEEKDAY(_xlpm.dini,2)=5,14/24,17.5/24))-8/24)*24),_xlpm.hfin,9.5*NETWORKDAYS.INTL(_xlpm.ep,_xlpm.dfin-1,"0000111",_xlpm.fer)+6*NETWORKDAYS.INTL(_xlpm.ep,_xlpm.dfin-1,"1111011",_xlpm.fer)+IF(OR(WEEKDAY(_xlpm.dfin,2)>5,COUNTIF(_xlpm.fer,_xlpm.dfin)>0),0,MAX(0,MIN(_xlpm.fin-_xlpm.dfin,IF(WEEKDAY(_xlpm.dfin,2)=5,14/24,17.5/24))-8/24)*24),_xlpm.hrs,IF(SCTR_Brokers[[#This Row],[Estado]]="FINALIZADO",MAX(0,_xlpm.hfin-_xlpm.hini),IF(SCTR_Brokers[[#This Row],[Horas_Transcurridas]]="",MAX(0,_xlpm.hfin-_xlpm.hini),SCTR_Brokers[[#This Row],[Horas_Transcurridas]])),IF(_xlpm.hrs<=LISTAS!$E$3,LISTAS!$J$3,LISTAS!$J$4))) -> Dentro | T11: =IF(SCTR_Brokers[[#This Row],[FechaRecepcion]]="","",TEXT(SCTR_Brokers[[#This Row],[FechaRecepcion]],"mmmm")&" "&YEAR(SCTR_Brokers[[#This Row],[FechaRecepcion]])) -> agosto 2026 | U11: =IF(SCTR_Brokers[[#This Row],[Estado]]="FINALIZADO",1,0) -> 1 | V11: =IF(SCTR_Brokers[[#This Row],[FechaRecepcion]]="","",IF(SCTR_Brokers[[#This Row],[Estado]]="FINALIZADO",0,1)) -> 0 | W11: =IF(AND(SCTR_Brokers[[#This Row],[Estado]]="FINALIZADO",SCTR_Brokers[[#This Row],[Plazo]]=LISTAS!$J$3),1,0) -> 1 | X11: =IF(AND(SCTR_Brokers[[#This Row],[Estado]]="FINALIZADO",SCTR_Brokers[[#This Row],[Plazo]]=LISTAS!$J$4),1,0) -> 0 | Y11: =IF(AND(SCTR_Brokers[[#This Row],[Estado]]<>"FINALIZADO",SCTR_Brokers[[#This Row],[Plazo]]=LISTAS!$J$4),1,0) -> 0 | Z11: =IF(SCTR_Brokers[[#This Row],[Fecha_Solic_Informe]]="",0,1) -> 0 | AA11: =IF(SCTR_Brokers[[#This Row],[Fecha_Informe]]="",0,1) -> 0 | AB11: =IF(AND(SCTR_Brokers[[#This Row],[Fecha_Solic_Informe]]<>"",SCTR_Brokers[[#This Row],[Fecha_Informe]]=""),1,0) -> 0 | AC11: =IF(AND(SCTR_Brokers[[#This Row],[Fecha_Solic_Informe]]<>"",SCTR_Brokers[[#This Row],[Fecha_Informe]]<>""),ROUND((SCTR_Brokers[[#This Row],[Fecha_Informe]]-SCTR_Brokers[[#This Row],[Fecha_Solic_Informe]])*24,1),"")
A12: AAQkADdkNThjNzFkLWM0ZmMtNDJhYS04MDVlLTIwNzE4ZDI1Mzg4YgAQAGNYmKV8CwNGkjfWksK0qfg= | C12: =IF(SCTR_Brokers[[#This Row],[FechaRecepcion]]="","",SCTR_Brokers[[#This Row],[ConversationId]]&"-"&TEXT(SCTR_Brokers[[#This Row],[FechaRecepcion]],"aaaammddhhmmss")) -> AAQkADdkNThjNzFkLWM0ZmMtNDJhYS04MDVlLTIwNzE4ZDI1Mzg4YgAQAGNYmKV8CwNGkjfWksK0qfg=-20260814091313 | D12: HOMECENTERS PERUANOS // SINIESTRO SCTR // PACIENTE ELJAER FERNANDO CHICCHI HUAMAN | E12: MARSH | F12: 46248.384 | G12: 46248.384 | H12: Brenda.Salazar@mercermarshbeneficios.com | I12: FINALIZADO | K12: SCTR SALUD | N12: =IF(SCTR_Brokers[[#This Row],[FechaRecepcion]]="","",IF(SCTR_Brokers[[#This Row],[Estado]]="FINALIZADO","",IF(SCTR_Brokers[[#This Row],[FechaUltimaRespuesta]]="","",_xlfn.LET(_xlpm.fer,LISTAS!$L$3:$L$100,_xlpm.ep,DATE(2000,1,1),_xlpm.ini,SCTR_Brokers[[#This Row],[FechaUltimaRespuesta]],_xlpm.fin,NOW(),_xlpm.dini,INT(_xlpm.ini),_xlpm.dfin,INT(_xlpm.fin),_xlpm.hini,9.5*NETWORKDAYS.INTL(_xlpm.ep,_xlpm.dini-1,"0000111",_xlpm.fer)+6*NETWORKDAYS.INTL(_xlpm.ep,_xlpm.dini-1,"1111011",_xlpm.fer)+IF(OR(WEEKDAY(_xlpm.dini,2)>5,COUNTIF(_xlpm.fer,_xlpm.dini)>0),0,MAX(0,MIN(_xlpm.ini-_xlpm.dini,IF(WEEKDAY(_xlpm.dini,2)=5,14/24,17.5/24))-8/24)*24),_xlpm.hfin,9.5*NETWORKDAYS.INTL(_xlpm.ep,_xlpm.dfin-1,"0000111",_xlpm.fer)+6*NETWORKDAYS.INTL(_xlpm.ep,_xlpm.dfin-1,"1111011",_xlpm.fer)+IF(OR(WEEKDAY(_xlpm.dfin,2)>5,COUNTIF(_xlpm.fer,_xlpm.dfin)>0),0,MAX(0,MIN(_xlpm.fin-_xlpm.dfin,IF(WEEKDAY(_xlpm.dfin,2)=5,14/24,17.5/24))-8/24)*24),ROUND(MAX(0,_xlpm.hfin-_xlpm.hini),1))))) | Q12: 46248.594 | R12: =IF(SCTR_Brokers[[#This Row],[FechaRecepcion]]="","",_xlfn.LET(_xlpm.fer,LISTAS!$L$3:$L$100,_xlpm.ep,DATE(2000,1,1),_xlpm.ini,SCTR_Brokers[[#This Row],[FechaRecepcion]],_xlpm.fin,IF(SCTR_Brokers[[#This Row],[Fecha_Cierre]]<>"",SCTR_Brokers[[#This Row],[Fecha_Cierre]],NOW()),_xlpm.dini,INT(_xlpm.ini),_xlpm.dfin,INT(_xlpm.fin),_xlpm.hini,9.5*NETWORKDAYS.INTL(_xlpm.ep,_xlpm.dini-1,"0000111",_xlpm.fer)+6*NETWORKDAYS.INTL(_xlpm.ep,_xlpm.dini-1,"1111011",_xlpm.fer)+IF(OR(WEEKDAY(_xlpm.dini,2)>5,COUNTIF(_xlpm.fer,_xlpm.dini)>0),0,MAX(0,MIN(_xlpm.ini-_xlpm.dini,IF(WEEKDAY(_xlpm.dini,2)=5,14/24,17.5/24))-8/24)*24),_xlpm.hfin,9.5*NETWORKDAYS.INTL(_xlpm.ep,_xlpm.dfin-1,"0000111",_xlpm.fer)+6*NETWORKDAYS.INTL(_xlpm.ep,_xlpm.dfin-1,"1111011",_xlpm.fer)+IF(OR(WEEKDAY(_xlpm.dfin,2)>5,COUNTIF(_xlpm.fer,_xlpm.dfin)>0),0,MAX(0,MIN(_xlpm.fin-_xlpm.dfin,IF(WEEKDAY(_xlpm.dfin,2)=5,14/24,17.5/24))-8/24)*24),_xlpm.hrs,IF(SCTR_Brokers[[#This Row],[Estado]]="FINALIZADO",MAX(0,_xlpm.hfin-_xlpm.hini),IF(SCTR_Brokers[[#This Row],[Horas_Transcurridas]]="",MAX(0,_xlpm.hfin-_xlpm.hini),SCTR_Brokers[[#This Row],[Horas_Transcurridas]])),IF(_xlpm.hrs<=LISTAS!$E$3,LISTAS!$J$3,LISTAS!$J$4))) -> Dentro | T12: =IF(SCTR_Brokers[[#This Row],[FechaRecepcion]]="","",TEXT(SCTR_Brokers[[#This Row],[FechaRecepcion]],"mmmm")&" "&YEAR(SCTR_Brokers[[#This Row],[FechaRecepcion]])) -> agosto 2026 | U12: =IF(SCTR_Brokers[[#This Row],[Estado]]="FINALIZADO",1,0) -> 1 | V12: =IF(SCTR_Brokers[[#This Row],[FechaRecepcion]]="","",IF(SCTR_Brokers[[#This Row],[Estado]]="FINALIZADO",0,1)) -> 0 | W12: =IF(AND(SCTR_Brokers[[#This Row],[Estado]]="FINALIZADO",SCTR_Brokers[[#This Row],[Plazo]]=LISTAS!$J$3),1,0) -> 1 | X12: =IF(AND(SCTR_Brokers[[#This Row],[Estado]]="FINALIZADO",SCTR_Brokers[[#This Row],[Plazo]]=LISTAS!$J$4),1,0) -> 0 | Y12: =IF(AND(SCTR_Brokers[[#This Row],[Estado]]<>"FINALIZADO",SCTR_Brokers[[#This Row],[Plazo]]=LISTAS!$J$4),1,0) -> 0 | Z12: =IF(SCTR_Brokers[[#This Row],[Fecha_Solic_Informe]]="",0,1) -> 0 | AA12: =IF(SCTR_Brokers[[#This Row],[Fecha_Informe]]="",0,1) -> 0 | AB12: =IF(AND(SCTR_Brokers[[#This Row],[Fecha_Solic_Informe]]<>"",SCTR_Brokers[[#This Row],[Fecha_Informe]]=""),1,0) -> 0 | AC12: =IF(AND(SCTR_Brokers[[#This Row],[Fecha_Solic_Informe]]<>"",SCTR_Brokers[[#This Row],[Fecha_Informe]]<>""),ROUND((SCTR_Brokers[[#This Row],[Fecha_Informe]]-SCTR_Brokers[[#This Row],[Fecha_Solic_Informe]])*24,1),"")
A13: AAQkADdkNThjNzFkLWM0ZmMtNDJhYS04MDVlLTIwNzE4ZDI1Mzg4YgAQAL3ITZJk9d9Fkya9zVOFO74= | C13: =IF(SCTR_Brokers[[#This Row],[FechaRecepcion]]="","",SCTR_Brokers[[#This Row],[ConversationId]]&"-"&TEXT(SCTR_Brokers[[#This Row],[FechaRecepcion]],"aaaammddhhmmss")) -> AAQkADdkNThjNzFkLWM0ZmMtNDJhYS04MDVlLTIwNzE4ZDI1Mzg4YgAQAL3ITZJk9d9Fkya9zVOFO74=-20260814104959 | D13: CAMBIO DE PROVEEDOR / SCTR SALUD / ASG NAVARRO VILLANUEVA MIKELA / CRUZ DEL SUR / MAPFRE | E13: HOWDEN | F13: 46248.451 | G13: 46248.468 | H13: rrodas@contacto.com.pe | I13: FINALIZADO | K13: SCTR SALUD | N13: =IF(SCTR_Brokers[[#This Row],[FechaRecepcion]]="","",IF(SCTR_Brokers[[#This Row],[Estado]]="FINALIZADO","",IF(SCTR_Brokers[[#This Row],[FechaUltimaRespuesta]]="","",_xlfn.LET(_xlpm.fer,LISTAS!$L$3:$L$100,_xlpm.ep,DATE(2000,1,1),_xlpm.ini,SCTR_Brokers[[#This Row],[FechaUltimaRespuesta]],_xlpm.fin,NOW(),_xlpm.dini,INT(_xlpm.ini),_xlpm.dfin,INT(_xlpm.fin),_xlpm.hini,9.5*NETWORKDAYS.INTL(_xlpm.ep,_xlpm.dini-1,"0000111",_xlpm.fer)+6*NETWORKDAYS.INTL(_xlpm.ep,_xlpm.dini-1,"1111011",_xlpm.fer)+IF(OR(WEEKDAY(_xlpm.dini,2)>5,COUNTIF(_xlpm.fer,_xlpm.dini)>0),0,MAX(0,MIN(_xlpm.ini-_xlpm.dini,IF(WEEKDAY(_xlpm.dini,2)=5,14/24,17.5/24))-8/24)*24),_xlpm.hfin,9.5*NETWORKDAYS.INTL(_xlpm.ep,_xlpm.dfin-1,"0000111",_xlpm.fer)+6*NETWORKDAYS.INTL(_xlpm.ep,_xlpm.dfin-1,"1111011",_xlpm.fer)+IF(OR(WEEKDAY(_xlpm.dfin,2)>5,COUNTIF(_xlpm.fer,_xlpm.dfin)>0),0,MAX(0,MIN(_xlpm.fin-_xlpm.dfin,IF(WEEKDAY(_xlpm.dfin,2)=5,14/24,17.5/24))-8/24)*24),ROUND(MAX(0,_xlpm.hfin-_xlpm.hini),1))))) | Q13: 46248.499 | R13: =IF(SCTR_Brokers[[#This Row],[FechaRecepcion]]="","",_xlfn.LET(_xlpm.fer,LISTAS!$L$3:$L$100,_xlpm.ep,DATE(2000,1,1),_xlpm.ini,SCTR_Brokers[[#This Row],[FechaRecepcion]],_xlpm.fin,IF(SCTR_Brokers[[#This Row],[Fecha_Cierre]]<>"",SCTR_Brokers[[#This Row],[Fecha_Cierre]],NOW()),_xlpm.dini,INT(_xlpm.ini),_xlpm.dfin,INT(_xlpm.fin),_xlpm.hini,9.5*NETWORKDAYS.INTL(_xlpm.ep,_xlpm.dini-1,"0000111",_xlpm.fer)+6*NETWORKDAYS.INTL(_xlpm.ep,_xlpm.dini-1,"1111011",_xlpm.fer)+IF(OR(WEEKDAY(_xlpm.dini,2)>5,COUNTIF(_xlpm.fer,_xlpm.dini)>0),0,MAX(0,MIN(_xlpm.ini-_xlpm.dini,IF(WEEKDAY(_xlpm.dini,2)=5,14/24,17.5/24))-8/24)*24),_xlpm.hfin,9.5*NETWORKDAYS.INTL(_xlpm.ep,_xlpm.dfin-1,"0000111",_xlpm.fer)+6*NETWORKDAYS.INTL(_xlpm.ep,_xlpm.dfin-1,"1111011",_xlpm.fer)+IF(OR(WEEKDAY(_xlpm.dfin,2)>5,COUNTIF(_xlpm.fer,_xlpm.dfin)>0),0,MAX(0,MIN(_xlpm.fin-_xlpm.dfin,IF(WEEKDAY(_xlpm.dfin,2)=5,14/24,17.5/24))-8/24)*24),_xlpm.hrs,IF(SCTR_Brokers[[#This Row],[Estado]]="FINALIZADO",MAX(0,_xlpm.hfin-_xlpm.hini),IF(SCTR_Brokers[[#This Row],[Horas_Transcurridas]]="",MAX(0,_xlpm.hfin-_xlpm.hini),SCTR_Brokers[[#This Row],[Horas_Transcurridas]])),IF(_xlpm.hrs<=LISTAS!$E$3,LISTAS!$J$3,LISTAS!$J$4))) -> Dentro | T13: =IF(SCTR_Brokers[[#This Row],[FechaRecepcion]]="","",TEXT(SCTR_Brokers[[#This Row],[FechaRecepcion]],"mmmm")&" "&YEAR(SCTR_Brokers[[#This Row],[FechaRecepcion]])) -> agosto 2026 | U13: =IF(SCTR_Brokers[[#This Row],[Estado]]="FINALIZADO",1,0) -> 1 | V13: =IF(SCTR_Brokers[[#This Row],[FechaRecepcion]]="","",IF(SCTR_Brokers[[#This Row],[Estado]]="FINALIZADO",0,1)) -> 0 | W13: =IF(AND(SCTR_Brokers[[#This Row],[Estado]]="FINALIZADO",SCTR_Brokers[[#This Row],[Plazo]]=LISTAS!$J$3),1,0) -> 1 | X13: =IF(AND(SCTR_Brokers[[#This Row],[Estado]]="FINALIZADO",SCTR_Brokers[[#This Row],[Plazo]]=LISTAS!$J$4),1,0) -> 0 | Y13: =IF(AND(SCTR_Brokers[[#This Row],[Estado]]<>"FINALIZADO",SCTR_Brokers[[#This Row],[Plazo]]=LISTAS!$J$4),1,0) -> 0 | Z13: =IF(SCTR_Brokers[[#This Row],[Fecha_Solic_Informe]]="",0,1) -> 0 | AA13: =IF(SCTR_Brokers[[#This Row],[Fecha_Informe]]="",0,1) -> 0 | AB13: =IF(AND(SCTR_Brokers[[#This Row],[Fecha_Solic_Informe]]<>"",SCTR_Brokers[[#This Row],[Fecha_Informe]]=""),1,0) -> 0 | AC13: =IF(AND(SCTR_Brokers[[#This Row],[Fecha_Solic_Informe]]<>"",SCTR_Brokers[[#This Row],[Fecha_Informe]]<>""),ROUND((SCTR_Brokers[[#This Row],[Fecha_Informe]]-SCTR_Brokers[[#This Row],[Fecha_Solic_Informe]])*24,1),"")
... A16: AAQkADdkNThjNzFkLWM0ZmMtNDJhYS04MDVlLTIwNzE4ZDI1Mzg4YgAQAD_wnXEnjrNOuaL_qkr7GmE= | C16: =IF(SCTR_Brokers[[#This Row],[FechaRecepcion]]="","",SCTR_Brokers[[#This Row],[ConversationId]]&"-"&TEXT(SCTR_Brokers[[#This Row],[FechaRecepcion]],"aaaammddhhmmss")) -> AAQkADdkNThjNzFkLWM0ZmMtNDJhYS04MDVlLTIwNzE4ZDI1Mzg4YgAQAD_wnXEnjrNOuaL_qkr7GmE=-20260814120034 | D16: RE: EVALUACIÓN POR PROCEDIMIENTO NO CUBIERTO/ SCTR SALUD/ ASG HUAMANTICO LAURA ROBERTO / CEMENTOS INKA / MAPFRE | E16: HOWDEN | F16: 46248.5 | G16: 46248.507 | H16: sctrsalud@mapfre.com.pe | I16: FINALIZADO | K16: SCTR SALUD | N16: =IF(SCTR_Brokers[[#This Row],[FechaRecepcion]]="","",IF(SCTR_Brokers[[#This Row],[Estado]]="FINALIZADO","",IF(SCTR_Brokers[[#This Row],[FechaUltimaRespuesta]]="","",_xlfn.LET(_xlpm.fer,LISTAS!$L$3:$L$100,_xlpm.ep,DATE(2000,1,1),_xlpm.ini,SCTR_Brokers[[#This Row],[FechaUltimaRespuesta]],_xlpm.fin,NOW(),_xlpm.dini,INT(_xlpm.ini),_xlpm.dfin,INT(_xlpm.fin),_xlpm.hini,9.5*NETWORKDAYS.INTL(_xlpm.ep,_xlpm.dini-1,"0000111",_xlpm.fer)+6*NETWORKDAYS.INTL(_xlpm.ep,_xlpm.dini-1,"1111011",_xlpm.fer)+IF(OR(WEEKDAY(_xlpm.dini,2)>5,COUNTIF(_xlpm.fer,_xlpm.dini)>0),0,MAX(0,MIN(_xlpm.ini-_xlpm.dini,IF(WEEKDAY(_xlpm.dini,2)=5,14/24,17.5/24))-8/24)*24),_xlpm.hfin,9.5*NETWORKDAYS.INTL(_xlpm.ep,_xlpm.dfin-1,"0000111",_xlpm.fer)+6*NETWORKDAYS.INTL(_xlpm.ep,_xlpm.dfin-1,"1111011",_xlpm.fer)+IF(OR(WEEKDAY(_xlpm.dfin,2)>5,COUNTIF(_xlpm.fer,_xlpm.dfin)>0),0,MAX(0,MIN(_xlpm.fin-_xlpm.dfin,IF(WEEKDAY(_xlpm.dfin,2)=5,14/24,17.5/24))-8/24)*24),ROUND(MAX(0,_xlpm.hfin-_xlpm.hini),1))))) | Q16: 46248.55 | R16: =IF(SCTR_Brokers[[#This Row],[FechaRecepcion]]="","",_xlfn.LET(_xlpm.fer,LISTAS!$L$3:$L$100,_xlpm.ep,DATE(2000,1,1),_xlpm.ini,SCTR_Brokers[[#This Row],[FechaRecepcion]],_xlpm.fin,IF(SCTR_Brokers[[#This Row],[Fecha_Cierre]]<>"",SCTR_Brokers[[#This Row],[Fecha_Cierre]],NOW()),_xlpm.dini,INT(_xlpm.ini),_xlpm.dfin,INT(_xlpm.fin),_xlpm.hini,9.5*NETWORKDAYS.INTL(_xlpm.ep,_xlpm.dini-1,"0000111",_xlpm.fer)+6*NETWORKDAYS.INTL(_xlpm.ep,_xlpm.dini-1,"1111011",_xlpm.fer)+IF(OR(WEEKDAY(_xlpm.dini,2)>5,COUNTIF(_xlpm.fer,_xlpm.dini)>0),0,MAX(0,MIN(_xlpm.ini-_xlpm.dini,IF(WEEKDAY(_xlpm.dini,2)=5,14/24,17.5/24))-8/24)*24),_xlpm.hfin,9.5*NETWORKDAYS.INTL(_xlpm.ep,_xlpm.dfin-1,"0000111",_xlpm.fer)+6*NETWORKDAYS.INTL(_xlpm.ep,_xlpm.dfin-1,"1111011",_xlpm.fer)+IF(OR(WEEKDAY(_xlpm.dfin,2)>5,COUNTIF(_xlpm.fer,_xlpm.dfin)>0),0,MAX(0,MIN(_xlpm.fin-_xlpm.dfin,IF(WEEKDAY(_xlpm.dfin,2)=5,14/24,17.5/24))-8/24)*24),_xlpm.hrs,IF(SCTR_Brokers[[#This Row],[Estado]]="FINALIZADO",MAX(0,_xlpm.hfin-_xlpm.hini),IF(SCTR_Brokers[[#This Row],[Horas_Transcurridas]]="",MAX(0,_xlpm.hfin-_xlpm.hini),SCTR_Brokers[[#This Row],[Horas_Transcurridas]])),IF(_xlpm.hrs<=LISTAS!$E$3,LISTAS!$J$3,LISTAS!$J$4))) -> Dentro | T16: =IF(SCTR_Brokers[[#This Row],[FechaRecepcion]]="","",TEXT(SCTR_Brokers[[#This Row],[FechaRecepcion]],"mmmm")&" "&YEAR(SCTR_Brokers[[#This Row],[FechaRecepcion]])) -> agosto 2026 | U16: =IF(SCTR_Brokers[[#This Row],[Estado]]="FINALIZADO",1,0) -> 1 | V16: =IF(SCTR_Brokers[[#This Row],[FechaRecepcion]]="","",IF(SCTR_Brokers[[#This Row],[Estado]]="FINALIZADO",0,1)) -> 0 | W16: =IF(AND(SCTR_Brokers[[#This Row],[Estado]]="FINALIZADO",SCTR_Brokers[[#This Row],[Plazo]]=LISTAS!$J$3),1,0) -> 1 | X16: =IF(AND(SCTR_Brokers[[#This Row],[Estado]]="FINALIZADO",SCTR_Brokers[[#This Row],[Plazo]]=LISTAS!$J$4),1,0) -> 0 | Y16: =IF(AND(SCTR_Brokers[[#This Row],[Estado]]<>"FINALIZADO",SCTR_Brokers[[#This Row],[Plazo]]=LISTAS!$J$4),1,0) -> 0 | Z16: =IF(SCTR_Brokers[[#This Row],[Fecha_Solic_Informe]]="",0,1) -> 0 | AA16: =IF(SCTR_Brokers[[#This Row],[Fecha_Informe]]="",0,1) -> 0 | AB16: =IF(AND(SCTR_Brokers[[#This Row],[Fecha_Solic_Informe]]<>"",SCTR_Brokers[[#This Row],[Fecha_Informe]]=""),1,0) -> 0 | AC16: =IF(AND(SCTR_Brokers[[#This Row],[Fecha_Solic_Informe]]<>"",SCTR_Brokers[[#This Row],[Fecha_Informe]]<>""),ROUND((SCTR_Brokers[[#This Row],[Fecha_Informe]]-SCTR_Brokers[[#This Row],[Fecha_Solic_Informe]])*24,1),"")
A17: AAQkADdkNThjNzFkLWM0ZmMtNDJhYS04MDVlLTIwNzE4ZDI1Mzg4YgAQAN8nmHl1gsBAj4k02S1J6vc= | C17: =IF(SCTR_Brokers[[#This Row],[FechaRecepcion]]="","",SCTR_Brokers[[#This Row],[ConversationId]]&"-"&TEXT(SCTR_Brokers[[#This Row],[FechaRecepcion]],"aaaammddhhmmss")) -> AAQkADdkNThjNzFkLWM0ZmMtNDJhYS04MDVlLTIwNzE4ZDI1Mzg4YgAQAN8nmHl1gsBAj4k02S1J6vc=-20260814122801 | D17: PESQUERA DIAMANTE : Bloqueo Caudal: CAYLLAHUA FLORES MAYCOL | E17: ARTHUR GALLAGHER | F17: 46248.519 | G17: 46248.55 | H17: sctrsalud@mapfre.com.pe | I17: FINALIZADO | K17: SCTR SALUD | L17: Buenos días:_x000D_ _x000D_ Estimados, favor su apoyo con la evaluación de lo solicitado en el adjunto._x000D_ _x000D_ _x000D_ Saludos,_x000D_ _x000D_ _x000D_ _x000D_ Alicia Sancca Medina_x000D_ _x000D_ Área de SCTR Salud_x000D_ _x000D_ Siniestros y Prestaciones_x000D_ _x000D_ Mapfre Perú_x000D_ _x000D_ Av. Armendáriz 345, Miraflores._x000D_ _x000D_ _x000D_ _x000D_ #CuidamosLoQu | N17: =IF(SCTR_Brokers[[#This Row],[FechaRecepcion]]="","",IF(SCTR_Brokers[[#This Row],[Estado]]="FINALIZADO","",IF(SCTR_Brokers[[#This Row],[FechaUltimaRespuesta]]="","",_xlfn.LET(_xlpm.fer,LISTAS!$L$3:$L$100,_xlpm.ep,DATE(2000,1,1),_xlpm.ini,SCTR_Brokers[[#This Row],[FechaUltimaRespuesta]],_xlpm.fin,NOW(),_xlpm.dini,INT(_xlpm.ini),_xlpm.dfin,INT(_xlpm.fin),_xlpm.hini,9.5*NETWORKDAYS.INTL(_xlpm.ep,_xlpm.dini-1,"0000111",_xlpm.fer)+6*NETWORKDAYS.INTL(_xlpm.ep,_xlpm.dini-1,"1111011",_xlpm.fer)+IF(OR(WEEKDAY(_xlpm.dini,2)>5,COUNTIF(_xlpm.fer,_xlpm.dini)>0),0,MAX(0,MIN(_xlpm.ini-_xlpm.dini,IF(WEEKDAY(_xlpm.dini,2)=5,14/24,17.5/24))-8/24)*24),_xlpm.hfin,9.5*NETWORKDAYS.INTL(_xlpm.ep,_xlpm.dfin-1,"0000111",_xlpm.fer)+6*NETWORKDAYS.INTL(_xlpm.ep,_xlpm.dfin-1,"1111011",_xlpm.fer)+IF(OR(WEEKDAY(_xlpm.dfin,2)>5,COUNTIF(_xlpm.fer,_xlpm.dfin)>0),0,MAX(0,MIN(_xlpm.fin-_xlpm.dfin,IF(WEEKDAY(_xlpm.dfin,2)=5,14/24,17.5/24))-8/24)*24),ROUND(MAX(0,_xlpm.hfin-_xlpm.hini),1))))) | O17: 46248.534 | P17: 46248.546 | Q17: 46248.55 | R17: =IF(SCTR_Brokers[[#This Row],[FechaRecepcion]]="","",_xlfn.LET(_xlpm.fer,LISTAS!$L$3:$L$100,_xlpm.ep,DATE(2000,1,1),_xlpm.ini,SCTR_Brokers[[#This Row],[FechaRecepcion]],_xlpm.fin,IF(SCTR_Brokers[[#This Row],[Fecha_Cierre]]<>"",SCTR_Brokers[[#This Row],[Fecha_Cierre]],NOW()),_xlpm.dini,INT(_xlpm.ini),_xlpm.dfin,INT(_xlpm.fin),_xlpm.hini,9.5*NETWORKDAYS.INTL(_xlpm.ep,_xlpm.dini-1,"0000111",_xlpm.fer)+6*NETWORKDAYS.INTL(_xlpm.ep,_xlpm.dini-1,"1111011",_xlpm.fer)+IF(OR(WEEKDAY(_xlpm.dini,2)>5,COUNTIF(_xlpm.fer,_xlpm.dini)>0),0,MAX(0,MIN(_xlpm.ini-_xlpm.dini,IF(WEEKDAY(_xlpm.dini,2)=5,14/24,17.5/24))-8/24)*24),_xlpm.hfin,9.5*NETWORKDAYS.INTL(_xlpm.ep,_xlpm.dfin-1,"0000111",_xlpm.fer)+6*NETWORKDAYS.INTL(_xlpm.ep,_xlpm.dfin-1,"1111011",_xlpm.fer)+IF(OR(WEEKDAY(_xlpm.dfin,2)>5,COUNTIF(_xlpm.fer,_xlpm.dfin)>0),0,MAX(0,MIN(_xlpm.fin-_xlpm.dfin,IF(WEEKDAY(_xlpm.dfin,2)=5,14/24,17.5/24))-8/24)*24),_xlpm.hrs,IF(SCTR_Brokers[[#This Row],[Estado]]="FINALIZADO",MAX(0,_xlpm.hfin-_xlpm.hini),IF(SCTR_Brokers[[#This Row],[Horas_Transcurridas]]="",MAX(0,_xlpm.hfin-_xlpm.hini),SCTR_Brokers[[#This Row],[Horas_Transcurridas]])),IF(_xlpm.hrs<=LISTAS!$E$3,LISTAS!$J$3,LISTAS!$J$4))) -> Dentro | T17: =IF(SCTR_Brokers[[#This Row],[FechaRecepcion]]="","",TEXT(SCTR_Brokers[[#This Row],[FechaRecepcion]],"mmmm")&" "&YEAR(SCTR_Brokers[[#This Row],[FechaRecepcion]])) -> agosto 2026 | U17: =IF(SCTR_Brokers[[#This Row],[Estado]]="FINALIZADO",1,0) -> 1 | V17: =IF(SCTR_Brokers[[#This Row],[FechaRecepcion]]="","",IF(SCTR_Brokers[[#This Row],[Estado]]="FINALIZADO",0,1)) -> 0 | W17: =IF(AND(SCTR_Brokers[[#This Row],[Estado]]="FINALIZADO",SCTR_Brokers[[#This Row],[Plazo]]=LISTAS!$J$3),1,0) -> 1 | X17: =IF(AND(SCTR_Brokers[[#This Row],[Estado]]="FINALIZADO",SCTR_Brokers[[#This Row],[Plazo]]=LISTAS!$J$4),1,0) -> 0 | Y17: =IF(AND(SCTR_Brokers[[#This Row],[Estado]]<>"FINALIZADO",SCTR_Brokers[[#This Row],[Plazo]]=LISTAS!$J$4),1,0) -> 0 | Z17: =IF(SCTR_Brokers[[#This Row],[Fecha_Solic_Informe]]="",0,1) -> 1 | AA17: =IF(SCTR_Brokers[[#This Row],[Fecha_Informe]]="",0,1) -> 1 | AB17: =IF(AND(SCTR_Brokers[[#This Row],[Fecha_Solic_Informe]]<>"",SCTR_Brokers[[#This Row],[Fecha_Informe]]=""),1,0) -> 0 | AC17: =IF(AND(SCTR_Brokers[[#This Row],[Fecha_Solic_Informe]]<>"",SCTR_Brokers[[#This Row],[Fecha_Informe]]<>""),ROUND((SCTR_Brokers[[#This Row],[Fecha_Informe]]-SCTR_Brokers[[#This Row],[Fecha_Solic_Informe]])*24,1),"") -> 0.3
A18: AAQkADdkNThjNzFkLWM0ZmMtNDJhYS04MDVlLTIwNzE4ZDI1Mzg4YgAQAFvSRRnHhNhOqxGz6fyRmY0= | C18: =IF(SCTR_Brokers[[#This Row],[FechaRecepcion]]="","",SCTR_Brokers[[#This Row],[ConversationId]]&"-"&TEXT(SCTR_Brokers[[#This Row],[FechaRecepcion]],"aaaammddhhmmss")) -> AAQkADdkNThjNzFkLWM0ZmMtNDJhYS04MDVlLTIwNzE4ZDI1Mzg4YgAQAFvSRRnHhNhOqxGz6fyRmY0=-20260814124354 | D18: COBERTURA DE TERAPIA LASER TERAPEUTICO ASEG. MIGUEL GOMEZ MORENO - PRODUCTOS PARAISO DEL PERU | E18: GABEL | F18: 46248.53 | G18: 46248.53 | H18: wguevara@gabel.com.pe | I18: FINALIZADO | K18: SCTR SALUD | N18: =IF(SCTR_Brokers[[#This Row],[FechaRecepcion]]="","",IF(SCTR_Brokers[[#This Row],[Estado]]="FINALIZADO","",IF(SCTR_Brokers[[#This Row],[FechaUltimaRespuesta]]="","",_xlfn.LET(_xlpm.fer,LISTAS!$L$3:$L$100,_xlpm.ep,DATE(2000,1,1),_xlpm.ini,SCTR_Brokers[[#This Row],[FechaUltimaRespuesta]],_xlpm.fin,NOW(),_xlpm.dini,INT(_xlpm.ini),_xlpm.dfin,INT(_xlpm.fin),_xlpm.hini,9.5*NETWORKDAYS.INTL(_xlpm.ep,_xlpm.dini-1,"0000111",_xlpm.fer)+6*NETWORKDAYS.INTL(_xlpm.ep,_xlpm.dini-1,"1111011",_xlpm.fer)+IF(OR(WEEKDAY(_xlpm.dini,2)>5,COUNTIF(_xlpm.fer,_xlpm.dini)>0),0,MAX(0,MIN(_xlpm.ini-_xlpm.dini,IF(WEEKDAY(_xlpm.dini,2)=5,14/24,17.5/24))-8/24)*24),_xlpm.hfin,9.5*NETWORKDAYS.INTL(_xlpm.ep,_xlpm.dfin-1,"0000111",_xlpm.fer)+6*NETWORKDAYS.INTL(_xlpm.ep,_xlpm.dfin-1,"1111011",_xlpm.fer)+IF(OR(WEEKDAY(_xlpm.dfin,2)>5,COUNTIF(_xlpm.fer,_xlpm.dfin)>0),0,MAX(0,MIN(_xlpm.fin-_xlpm.dfin,IF(WEEKDAY(_xlpm.dfin,2)=5,14/24,17.5/24))-8/24)*24),ROUND(MAX(0,_xlpm.hfin-_xlpm.hini),1))))) | Q18: 46248.732 | R18: =IF(SCTR_Brokers[[#This Row],[FechaRecepcion]]="","",_xlfn.LET(_xlpm.fer,LISTAS!$L$3:$L$100,_xlpm.ep,DATE(2000,1,1),_xlpm.ini,SCTR_Brokers[[#This Row],[FechaRecepcion]],_xlpm.fin,IF(SCTR_Brokers[[#This Row],[Fecha_Cierre]]<>"",SCTR_Brokers[[#This Row],[Fecha_Cierre]],NOW()),_xlpm.dini,INT(_xlpm.ini),_xlpm.dfin,INT(_xlpm.fin),_xlpm.hini,9.5*NETWORKDAYS.INTL(_xlpm.ep,_xlpm.dini-1,"0000111",_xlpm.fer)+6*NETWORKDAYS.INTL(_xlpm.ep,_xlpm.dini-1,"1111011",_xlpm.fer)+IF(OR(WEEKDAY(_xlpm.dini,2)>5,COUNTIF(_xlpm.fer,_xlpm.dini)>0),0,MAX(0,MIN(_xlpm.ini-_xlpm.dini,IF(WEEKDAY(_xlpm.dini,2)=5,14/24,17.5/24))-8/24)*24),_xlpm.hfin,9.5*NETWORKDAYS.INTL(_xlpm.ep,_xlpm.dfin-1,"0000111",_xlpm.fer)+6*NETWORKDAYS.INTL(_xlpm.ep,_xlpm.dfin-1,"1111011",_xlpm.fer)+IF(OR(WEEKDAY(_xlpm.dfin,2)>5,COUNTIF(_xlpm.fer,_xlpm.dfin)>0),0,MAX(0,MIN(_xlpm.fin-_xlpm.dfin,IF(WEEKDAY(_xlpm.dfin,2)=5,14/24,17.5/24))-8/24)*24),_xlpm.hrs,IF(SCTR_Brokers[[#This Row],[Estado]]="FINALIZADO",MAX(0,_xlpm.hfin-_xlpm.hini),IF(SCTR_Brokers[[#This Row],[Horas_Transcurridas]]="",MAX(0,_xlpm.hfin-_xlpm.hini),SCTR_Brokers[[#This Row],[Horas_Transcurridas]])),IF(_xlpm.hrs<=LISTAS!$E$3,LISTAS!$J$3,LISTAS!$J$4))) -> Dentro | T18: =IF(SCTR_Brokers[[#This Row],[FechaRecepcion]]="","",TEXT(SCTR_Brokers[[#This Row],[FechaRecepcion]],"mmmm")&" "&YEAR(SCTR_Brokers[[#This Row],[FechaRecepcion]])) -> agosto 2026 | U18: =IF(SCTR_Brokers[[#This Row],[Estado]]="FINALIZADO",1,0) -> 1 | V18: =IF(SCTR_Brokers[[#This Row],[FechaRecepcion]]="","",IF(SCTR_Brokers[[#This Row],[Estado]]="FINALIZADO",0,1)) -> 0 | W18: =IF(AND(SCTR_Brokers[[#This Row],[Estado]]="FINALIZADO",SCTR_Brokers[[#This Row],[Plazo]]=LISTAS!$J$3),1,0) -> 1 | X18: =IF(AND(SCTR_Brokers[[#This Row],[Estado]]="FINALIZADO",SCTR_Brokers[[#This Row],[Plazo]]=LISTAS!$J$4),1,0) -> 0 | Y18: =IF(AND(SCTR_Brokers[[#This Row],[Estado]]<>"FINALIZADO",SCTR_Brokers[[#This Row],[Plazo]]=LISTAS!$J$4),1,0) -> 0 | Z18: =IF(SCTR_Brokers[[#This Row],[Fecha_Solic_Informe]]="",0,1) -> 0 | AA18: =IF(SCTR_Brokers[[#This Row],[Fecha_Informe]]="",0,1) -> 0 | AB18: =IF(AND(SCTR_Brokers[[#This Row],[Fecha_Solic_Informe]]<>"",SCTR_Brokers[[#This Row],[Fecha_Informe]]=""),1,0) -> 0 | AC18: =IF(AND(SCTR_Brokers[[#This Row],[Fecha_Solic_Informe]]<>"",SCTR_Brokers[[#This Row],[Fecha_Informe]]<>""),ROUND((SCTR_Brokers[[#This Row],[Fecha_Informe]]-SCTR_Brokers[[#This Row],[Fecha_Solic_Informe]])*24,1),"")
A19: AAQkADdkNThjNzFkLWM0ZmMtNDJhYS04MDVlLTIwNzE4ZDI1Mzg4YgAQAD0KJzq8UO5HuSV08G9KmYE= | C19: =IF(SCTR_Brokers[[#This Row],[FechaRecepcion]]="","",SCTR_Brokers[[#This Row],[ConversationId]]&"-"&TEXT(SCTR_Brokers[[#This Row],[FechaRecepcion]],"aaaammddhhmmss")) -> AAQkADdkNThjNzFkLWM0ZmMtNDJhYS04MDVlLTIwNzE4ZDI1Mzg4YgAQAD0KJzq8UO5HuSV08G9KmYE=-20260814131146 | D19: RV: MEDICAMENTOS-GIL JIMENEZ EMANUEL | E19: MARSH | F19: 46248.55 | G19: 46248.578 | H19: sctrsalud@mapfre.com.pe | I19: FINALIZADO | K19: SCTR SALUD | N19: =IF(SCTR_Brokers[[#This Row],[FechaRecepcion]]="","",IF(SCTR_Brokers[[#This Row],[Estado]]="FINALIZADO","",IF(SCTR_Brokers[[#This Row],[FechaUltimaRespuesta]]="","",_xlfn.LET(_xlpm.fer,LISTAS!$L$3:$L$100,_xlpm.ep,DATE(2000,1,1),_xlpm.ini,SCTR_Brokers[[#This Row],[FechaUltimaRespuesta]],_xlpm.fin,NOW(),_xlpm.dini,INT(_xlpm.ini),_xlpm.dfin,INT(_xlpm.fin),_xlpm.hini,9.5*NETWORKDAYS.INTL(_xlpm.ep,_xlpm.dini-1,"0000111",_xlpm.fer)+6*NETWORKDAYS.INTL(_xlpm.ep,_xlpm.dini-1,"1111011",_xlpm.fer)+IF(OR(WEEKDAY(_xlpm.dini,2)>5,COUNTIF(_xlpm.fer,_xlpm.dini)>0),0,MAX(0,MIN(_xlpm.ini-_xlpm.dini,IF(WEEKDAY(_xlpm.dini,2)=5,14/24,17.5/24))-8/24)*24),_xlpm.hfin,9.5*NETWORKDAYS.INTL(_xlpm.ep,_xlpm.dfin-1,"0000111",_xlpm.fer)+6*NETWORKDAYS.INTL(_xlpm.ep,_xlpm.dfin-1,"1111011",_xlpm.fer)+IF(OR(WEEKDAY(_xlpm.dfin,2)>5,COUNTIF(_xlpm.fer,_xlpm.dfin)>0),0,MAX(0,MIN(_xlpm.fin-_xlpm.dfin,IF(WEEKDAY(_xlpm.dfin,2)=5,14/24,17.5/24))-8/24)*24),ROUND(MAX(0,_xlpm.hfin-_xlpm.hini),1))))) | Q19: 46248.578 | R19: =IF(SCTR_Brokers[[#This Row],[FechaRecepcion]]="","",_xlfn.LET(_xlpm.fer,LISTAS!$L$3:$L$100,_xlpm.ep,DATE(2000,1,1),_xlpm.ini,SCTR_Brokers[[#This Row],[FechaRecepcion]],_xlpm.fin,IF(SCTR_Brokers[[#This Row],[Fecha_Cierre]]<>"",SCTR_Brokers[[#This Row],[Fecha_Cierre]],NOW()),_xlpm.dini,INT(_xlpm.ini),_xlpm.dfin,INT(_xlpm.fin),_xlpm.hini,9.5*NETWORKDAYS.INTL(_xlpm.ep,_xlpm.dini-1,"0000111",_xlpm.fer)+6*NETWORKDAYS.INTL(_xlpm.ep,_xlpm.dini-1,"1111011",_xlpm.fer)+IF(OR(WEEKDAY(_xlpm.dini,2)>5,COUNTIF(_xlpm.fer,_xlpm.dini)>0),0,MAX(0,MIN(_xlpm.ini-_xlpm.dini,IF(WEEKDAY(_xlpm.dini,2)=5,14/24,17.5/24))-8/24)*24),_xlpm.hfin,9.5*NETWORKDAYS.INTL(_xlpm.ep,_xlpm.dfin-1,"0000111",_xlpm.fer)+6*NETWORKDAYS.INTL(_xlpm.ep,_xlpm.dfin-1,"1111011",_xlpm.fer)+IF(OR(WEEKDAY(_xlpm.dfin,2)>5,COUNTIF(_xlpm.fer,_xlpm.dfin)>0),0,MAX(0,MIN(_xlpm.fin-_xlpm.dfin,IF(WEEKDAY(_xlpm.dfin,2)=5,14/24,17.5/24))-8/24)*24),_xlpm.hrs,IF(SCTR_Brokers[[#This Row],[Estado]]="FINALIZADO",MAX(0,_xlpm.hfin-_xlpm.hini),IF(SCTR_Brokers[[#This Row],[Horas_Transcurridas]]="",MAX(0,_xlpm.hfin-_xlpm.hini),SCTR_Brokers[[#This Row],[Horas_Transcurridas]])),IF(_xlpm.hrs<=LISTAS!$E$3,LISTAS!$J$3,LISTAS!$J$4))) -> Dentro | T19: =IF(SCTR_Brokers[[#This Row],[FechaRecepcion]]="","",TEXT(SCTR_Brokers[[#This Row],[FechaRecepcion]],"mmmm")&" "&YEAR(SCTR_Brokers[[#This Row],[FechaRecepcion]])) -> agosto 2026 | U19: =IF(SCTR_Brokers[[#This Row],[Estado]]="FINALIZADO",1,0) -> 1 | V19: =IF(SCTR_Brokers[[#This Row],[FechaRecepcion]]="","",IF(SCTR_Brokers[[#This Row],[Estado]]="FINALIZADO",0,1)) -> 0 | W19: =IF(AND(SCTR_Brokers[[#This Row],[Estado]]="FINALIZADO",SCTR_Brokers[[#This Row],[Plazo]]=LISTAS!$J$3),1,0) -> 1 | X19: =IF(AND(SCTR_Brokers[[#This Row],[Estado]]="FINALIZADO",SCTR_Brokers[[#This Row],[Plazo]]=LISTAS!$J$4),1,0) -> 0 | Y19: =IF(AND(SCTR_Brokers[[#This Row],[Estado]]<>"FINALIZADO",SCTR_Brokers[[#This Row],[Plazo]]=LISTAS!$J$4),1,0) -> 0 | Z19: =IF(SCTR_Brokers[[#This Row],[Fecha_Solic_Informe]]="",0,1) -> 0 | AA19: =IF(SCTR_Brokers[[#This Row],[Fecha_Informe]]="",0,1) -> 0 | AB19: =IF(AND(SCTR_Brokers[[#This Row],[Fecha_Solic_Informe]]<>"",SCTR_Brokers[[#This Row],[Fecha_Informe]]=""),1,0) -> 0 | AC19: =IF(AND(SCTR_Brokers[[#This Row],[Fecha_Solic_Informe]]<>"",SCTR_Brokers[[#This Row],[Fecha_Informe]]<>""),ROUND((SCTR_Brokers[[#This Row],[Fecha_Informe]]-SCTR_Brokers[[#This Row],[Fecha_Solic_Informe]])*24,1),"")
A20: AAQkADdkNThjNzFkLWM0ZmMtNDJhYS04MDVlLTIwNzE4ZDI1Mzg4YgAQALdAcFsH1PJArDbyP_CirxI= | C20: =IF(SCTR_Brokers[[#This Row],[FechaRecepcion]]="","",SCTR_Brokers[[#This Row],[ConversationId]]&"-"&TEXT(SCTR_Brokers[[#This Row],[FechaRecepcion]],"aaaammddhhmmss")) -> AAQkADdkNThjNzFkLWM0ZmMtNDJhYS04MDVlLTIwNzE4ZDI1Mzg4YgAQALdAcFsH1PJArDbyP_CirxI=-20260814145615 | D20: PRIORIDAD *** SOLICITUD DE RODILLERA - SCTR SALUD / DON POLLO TROPICAL / Asegurado: YARICAHUA TAPULLIMA, ROYER | E20: MARSH | F20: 46248.622 | G20: 46252.379 | H20: sctrsalud@mapfre.com.pe | I20: FINALIZADO | K20: SCTR SALUD | N20: =IF(SCTR_Brokers[[#This Row],[FechaRecepcion]]="","",IF(SCTR_Brokers[[#This Row],[Estado]]="FINALIZADO","",IF(SCTR_Brokers[[#This Row],[FechaUltimaRespuesta]]="","",_xlfn.LET(_xlpm.fer,LISTAS!$L$3:$L$100,_xlpm.ep,DATE(2000,1,1),_xlpm.ini,SCTR_Brokers[[#This Row],[FechaUltimaRespuesta]],_xlpm.fin,NOW(),_xlpm.dini,INT(_xlpm.ini),_xlpm.dfin,INT(_xlpm.fin),_xlpm.hini,9.5*NETWORKDAYS.INTL(_xlpm.ep,_xlpm.dini-1,"0000111",_xlpm.fer)+6*NETWORKDAYS.INTL(_xlpm.ep,_xlpm.dini-1,"1111011",_xlpm.fer)+IF(OR(WEEKDAY(_xlpm.dini,2)>5,COUNTIF(_xlpm.fer,_xlpm.dini)>0),0,MAX(0,MIN(_xlpm.ini-_xlpm.dini,IF(WEEKDAY(_xlpm.dini,2)=5,14/24,17.5/24))-8/24)*24),_xlpm.hfin,9.5*NETWORKDAYS.INTL(_xlpm.ep,_xlpm.dfin-1,"0000111",_xlpm.fer)+6*NETWORKDAYS.INTL(_xlpm.ep,_xlpm.dfin-1,"1111011",_xlpm.fer)+IF(OR(WEEKDAY(_xlpm.dfin,2)>5,COUNTIF(_xlpm.fer,_xlpm.dfin)>0),0,MAX(0,MIN(_xlpm.fin-_xlpm.dfin,IF(WEEKDAY(_xlpm.dfin,2)=5,14/24,17.5/24))-8/24)*24),ROUND(MAX(0,_xlpm.hfin-_xlpm.hini),1))))) | Q20: 46252.379 | R20: =IF(SCTR_Brokers[[#This Row],[FechaRecepcion]]="","",_xlfn.LET(_xlpm.fer,LISTAS!$L$3:$L$100,_xlpm.ep,DATE(2000,1,1),_xlpm.ini,SCTR_Brokers[[#This Row],[FechaRecepcion]],_xlpm.fin,IF(SCTR_Brokers[[#This Row],[Fecha_Cierre]]<>"",SCTR_Brokers[[#This Row],[Fecha_Cierre]],NOW()),_xlpm.dini,INT(_xlpm.ini),_xlpm.dfin,INT(_xlpm.fin),_xlpm.hini,9.5*NETWORKDAYS.INTL(_xlpm.ep,_xlpm.dini-1,"0000111",_xlpm.fer)+6*NETWORKDAYS.INTL(_xlpm.ep,_xlpm.dini-1,"1111011",_xlpm.fer)+IF(OR(WEEKDAY(_xlpm.dini,2)>5,COUNTIF(_xlpm.fer,_xlpm.dini)>0),0,MAX(0,MIN(_xlpm.ini-_xlpm.dini,IF(WEEKDAY(_xlpm.dini,2)=5,14/24,17.5/24))-8/24)*24),_xlpm.hfin,9.5*NETWORKDAYS.INTL(_xlpm.ep,_xlpm.dfin-1,"0000111",_xlpm.fer)+6*NETWORKDAYS.INTL(_xlpm.ep,_xlpm.dfin-1,"1111011",_xlpm.fer)+IF(OR(WEEKDAY(_xlpm.dfin,2)>5,COUNTIF(_xlpm.fer,_xlpm.dfin)>0),0,MAX(0,MIN(_xlpm.fin-_xlpm.dfin,IF(WEEKDAY(_xlpm.dfin,2)=5,14/24,17.5/24))-8/24)*24),_xlpm.hrs,IF(SCTR_Brokers[[#This Row],[Estado]]="FINALIZADO",MAX(0,_xlpm.hfin-_xlpm.hini),IF(SCTR_Brokers[[#This Row],[Horas_Transcurridas]]="",MAX(0,_xlpm.hfin-_xlpm.hini),SCTR_Brokers[[#This Row],[Horas_Transcurridas]])),IF(_xlpm.hrs<=LISTAS!$E$3,LISTAS!$J$3,LISTAS!$J$4))) -> Fuera | T20: =IF(SCTR_Brokers[[#This Row],[FechaRecepcion]]="","",TEXT(SCTR_Brokers[[#This Row],[FechaRecepcion]],"mmmm")&" "&YEAR(SCTR_Brokers[[#This Row],[FechaRecepcion]])) -> agosto 2026 | U20: =IF(SCTR_Brokers[[#This Row],[Estado]]="FINALIZADO",1,0) -> 1 | V20: =IF(SCTR_Brokers[[#This Row],[FechaRecepcion]]="","",IF(SCTR_Brokers[[#This Row],[Estado]]="FINALIZADO",0,1)) -> 0 | W20: =IF(AND(SCTR_Brokers[[#This Row],[Estado]]="FINALIZADO",SCTR_Brokers[[#This Row],[Plazo]]=LISTAS!$J$3),1,0) -> 0 | X20: =IF(AND(SCTR_Brokers[[#This Row],[Estado]]="FINALIZADO",SCTR_Brokers[[#This Row],[Plazo]]=LISTAS!$J$4),1,0) -> 1 | Y20: =IF(AND(SCTR_Brokers[[#This Row],[Estado]]<>"FINALIZADO",SCTR_Brokers[[#This Row],[Plazo]]=LISTAS!$J$4),1,0) -> 0 | Z20: =IF(SCTR_Brokers[[#This Row],[Fecha_Solic_Informe]]="",0,1) -> 0 | AA20: =IF(SCTR_Brokers[[#This Row],[Fecha_Informe]]="",0,1) -> 0 | AB20: =IF(AND(SCTR_Brokers[[#This Row],[Fecha_Solic_Informe]]<>"",SCTR_Brokers[[#This Row],[Fecha_Informe]]=""),1,0) -> 0 | AC20: =IF(AND(SCTR_Brokers[[#This Row],[Fecha_Solic_Informe]]<>"",SCTR_Brokers[[#This Row],[Fecha_Informe]]<>""),ROUND((SCTR_Brokers[[#This Row],[Fecha_Informe]]-SCTR_Brokers[[#This Row],[Fecha_Solic_Informe]])*24,1),"")
A21: AAQkADdkNThjNzFkLWM0ZmMtNDJhYS04MDVlLTIwNzE4ZDI1Mzg4YgAQAO1Ks_-a0Es1sJ99uZJRKRc= | C21: =IF(SCTR_Brokers[[#This Row],[FechaRecepcion]]="","",SCTR_Brokers[[#This Row],[ConversationId]]&"-"&TEXT(SCTR_Brokers[[#This Row],[FechaRecepcion]],"aaaammddhhmmss")) -> AAQkADdkNThjNzFkLWM0ZmMtNDJhYS04MDVlLTIwNzE4ZDI1Mzg4YgAQAO1Ks_-a0Es1sJ99uZJRKRc=-20260814154225 | D21: DON POLLO LA LIBERTAD // SCTR SALUD - ACCIDENTE DE TRABAJO: CABANILLAS SALDAÑA JOSE BARTOLO | E21: MARSH | F21: 46248.654 | G21: 46248.654 | H21: Marsh.SiniestrosRRLL@marsh.com | I21: FINALIZADO | K21: SCTR SALUD | N21: =IF(SCTR_Brokers[[#This Row],[FechaRecepcion]]="","",IF(SCTR_Brokers[[#This Row],[Estado]]="FINALIZADO","",IF(SCTR_Brokers[[#This Row],[FechaUltimaRespuesta]]="","",_xlfn.LET(_xlpm.fer,LISTAS!$L$3:$L$100,_xlpm.ep,DATE(2000,1,1),_xlpm.ini,SCTR_Brokers[[#This Row],[FechaUltimaRespuesta]],_xlpm.fin,NOW(),_xlpm.dini,INT(_xlpm.ini),_xlpm.dfin,INT(_xlpm.fin),_xlpm.hini,9.5*NETWORKDAYS.INTL(_xlpm.ep,_xlpm.dini-1,"0000111",_xlpm.fer)+6*NETWORKDAYS.INTL(_xlpm.ep,_xlpm.dini-1,"1111011",_xlpm.fer)+IF(OR(WEEKDAY(_xlpm.dini,2)>5,COUNTIF(_xlpm.fer,_xlpm.dini)>0),0,MAX(0,MIN(_xlpm.ini-_xlpm.dini,IF(WEEKDAY(_xlpm.dini,2)=5,14/24,17.5/24))-8/24)*24),_xlpm.hfin,9.5*NETWORKDAYS.INTL(_xlpm.ep,_xlpm.dfin-1,"0000111",_xlpm.fer)+6*NETWORKDAYS.INTL(_xlpm.ep,_xlpm.dfin-1,"1111011",_xlpm.fer)+IF(OR(WEEKDAY(_xlpm.dfin,2)>5,COUNTIF(_xlpm.fer,_xlpm.dfin)>0),0,MAX(0,MIN(_xlpm.fin-_xlpm.dfin,IF(WEEKDAY(_xlpm.dfin,2)=5,14/24,17.5/24))-8/24)*24),ROUND(MAX(0,_xlpm.hfin-_xlpm.hini),1))))) | Q21: 46248.654 | R21: =IF(SCTR_Brokers[[#This Row],[FechaRecepcion]]="","",_xlfn.LET(_xlpm.fer,LISTAS!$L$3:$L$100,_xlpm.ep,DATE(2000,1,1),_xlpm.ini,SCTR_Brokers[[#This Row],[FechaRecepcion]],_xlpm.fin,IF(SCTR_Brokers[[#This Row],[Fecha_Cierre]]<>"",SCTR_Brokers[[#This Row],[Fecha_Cierre]],NOW()),_xlpm.dini,INT(_xlpm.ini),_xlpm.dfin,INT(_xlpm.fin),_xlpm.hini,9.5*NETWORKDAYS.INTL(_xlpm.ep,_xlpm.dini-1,"0000111",_xlpm.fer)+6*NETWORKDAYS.INTL(_xlpm.ep,_xlpm.dini-1,"1111011",_xlpm.fer)+IF(OR(WEEKDAY(_xlpm.dini,2)>5,COUNTIF(_xlpm.fer,_xlpm.dini)>0),0,MAX(0,MIN(_xlpm.ini-_xlpm.dini,IF(WEEKDAY(_xlpm.dini,2)=5,14/24,17.5/24))-8/24)*24),_xlpm.hfin,9.5*NETWORKDAYS.INTL(_xlpm.ep,_xlpm.dfin-1,"0000111",_xlpm.fer)+6*NETWORKDAYS.INTL(_xlpm.ep,_xlpm.dfin-1,"1111011",_xlpm.fer)+IF(OR(WEEKDAY(_xlpm.dfin,2)>5,COUNTIF(_xlpm.fer,_xlpm.dfin)>0),0,MAX(0,MIN(_xlpm.fin-_xlpm.dfin,IF(WEEKDAY(_xlpm.dfin,2)=5,14/24,17.5/24))-8/24)*24),_xlpm.hrs,IF(SCTR_Brokers[[#This Row],[Estado]]="FINALIZADO",MAX(0,_xlpm.hfin-_xlpm.hini),IF(SCTR_Brokers[[#This Row],[Horas_Transcurridas]]="",MAX(0,_xlpm.hfin-_xlpm.hini),SCTR_Brokers[[#This Row],[Horas_Transcurridas]])),IF(_xlpm.hrs<=LISTAS!$E$3,LISTAS!$J$3,LISTAS!$J$4))) -> Dentro | T21: =IF(SCTR_Brokers[[#This Row],[FechaRecepcion]]="","",TEXT(SCTR_Brokers[[#This Row],[FechaRecepcion]],"mmmm")&" "&YEAR(SCTR_Brokers[[#This Row],[FechaRecepcion]])) -> agosto 2026 | U21: =IF(SCTR_Brokers[[#This Row],[Estado]]="FINALIZADO",1,0) -> 1 | V21: =IF(SCTR_Brokers[[#This Row],[FechaRecepcion]]="","",IF(SCTR_Brokers[[#This Row],[Estado]]="FINALIZADO",0,1)) -> 0 | W21: =IF(AND(SCTR_Brokers[[#This Row],[Estado]]="FINALIZADO",SCTR_Brokers[[#This Row],[Plazo]]=LISTAS!$J$3),1,0) -> 1 | X21: =IF(AND(SCTR_Brokers[[#This Row],[Estado]]="FINALIZADO",SCTR_Brokers[[#This Row],[Plazo]]=LISTAS!$J$4),1,0) -> 0 | Y21: =IF(AND(SCTR_Brokers[[#This Row],[Estado]]<>"FINALIZADO",SCTR_Brokers[[#This Row],[Plazo]]=LISTAS!$J$4),1,0) -> 0 | Z21: =IF(SCTR_Brokers[[#This Row],[Fecha_Solic_Informe]]="",0,1) -> 0 | AA21: =IF(SCTR_Brokers[[#This Row],[Fecha_Informe]]="",0,1) -> 0 | AB21: =IF(AND(SCTR_Brokers[[#This Row],[Fecha_Solic_Informe]]<>"",SCTR_Brokers[[#This Row],[Fecha_Informe]]=""),1,0) -> 0 | AC21: =IF(AND(SCTR_Brokers[[#This Row],[Fecha_Solic_Informe]]<>"",SCTR_Brokers[[#This Row],[Fecha_Informe]]<>""),ROUND((SCTR_Brokers[[#This Row],[Fecha_Informe]]-SCTR_Brokers[[#This Row],[Fecha_Solic_Informe]])*24,1),"")
A22: AAQkADdkNThjNzFkLWM0ZmMtNDJhYS04MDVlLTIwNzE4ZDI1Mzg4YgAQAFGmjH3HIEZQpdi_IN7Cyw8= | C22: =IF(SCTR_Brokers[[#This Row],[FechaRecepcion]]="","",SCTR_Brokers[[#This Row],[ConversationId]]&"-"&TEXT(SCTR_Brokers[[#This Row],[FechaRecepcion]],"aaaammddhhmmss")) -> AAQkADdkNThjNzFkLWM0ZmMtNDJhYS04MDVlLTIwNzE4ZDI1Mzg4YgAQAFGmjH3HIEZQpdi_IN7Cyw8=-20260814154819 | D22: CAMBIO DE CLINICA MEDICINA FISICA Y REHABILITACIÓN _ CALLA URIARTE ALEXIS _ DNI 71183334 _ CONSORCIO SAN MIGUEL _ RUC 20605151958 _ SCTR | E22: GABEL | F22: 46248.659 | G22: 46248.659 | H22: jyzquierdo@gabel.com.pe | I22: FINALIZADO | K22: SCTR SALUD | N22: =IF(SCTR_Brokers[[#This Row],[FechaRecepcion]]="","",IF(SCTR_Brokers[[#This Row],[Estado]]="FINALIZADO","",IF(SCTR_Brokers[[#This Row],[FechaUltimaRespuesta]]="","",_xlfn.LET(_xlpm.fer,LISTAS!$L$3:$L$100,_xlpm.ep,DATE(2000,1,1),_xlpm.ini,SCTR_Brokers[[#This Row],[FechaUltimaRespuesta]],_xlpm.fin,NOW(),_xlpm.dini,INT(_xlpm.ini),_xlpm.dfin,INT(_xlpm.fin),_xlpm.hini,9.5*NETWORKDAYS.INTL(_xlpm.ep,_xlpm.dini-1,"0000111",_xlpm.fer)+6*NETWORKDAYS.INTL(_xlpm.ep,_xlpm.dini-1,"1111011",_xlpm.fer)+IF(OR(WEEKDAY(_xlpm.dini,2)>5,COUNTIF(_xlpm.fer,_xlpm.dini)>0),0,MAX(0,MIN(_xlpm.ini-_xlpm.dini,IF(WEEKDAY(_xlpm.dini,2)=5,14/24,17.5/24))-8/24)*24),_xlpm.hfin,9.5*NETWORKDAYS.INTL(_xlpm.ep,_xlpm.dfin-1,"0000111",_xlpm.fer)+6*NETWORKDAYS.INTL(_xlpm.ep,_xlpm.dfin-1,"1111011",_xlpm.fer)+IF(OR(WEEKDAY(_xlpm.dfin,2)>5,COUNTIF(_xlpm.fer,_xlpm.dfin)>0),0,MAX(0,MIN(_xlpm.fin-_xlpm.dfin,IF(WEEKDAY(_xlpm.dfin,2)=5,14/24,17.5/24))-8/24)*24),ROUND(MAX(0,_xlpm.hfin-_xlpm.hini),1))))) | Q22: 46251.502 | R22: =IF(SCTR_Brokers[[#This Row],[FechaRecepcion]]="","",_xlfn.LET(_xlpm.fer,LISTAS!$L$3:$L$100,_xlpm.ep,DATE(2000,1,1),_xlpm.ini,SCTR_Brokers[[#This Row],[FechaRecepcion]],_xlpm.fin,IF(SCTR_Brokers[[#This Row],[Fecha_Cierre]]<>"",SCTR_Brokers[[#This Row],[Fecha_Cierre]],NOW()),_xlpm.dini,INT(_xlpm.ini),_xlpm.dfin,INT(_xlpm.fin),_xlpm.hini,9.5*NETWORKDAYS.INTL(_xlpm.ep,_xlpm.dini-1,"0000111",_xlpm.fer)+6*NETWORKDAYS.INTL(_xlpm.ep,_xlpm.dini-1,"1111011",_xlpm.fer)+IF(OR(WEEKDAY(_xlpm.dini,2)>5,COUNTIF(_xlpm.fer,_xlpm.dini)>0),0,MAX(0,MIN(_xlpm.ini-_xlpm.dini,IF(WEEKDAY(_xlpm.dini,2)=5,14/24,17.5/24))-8/24)*24),_xlpm.hfin,9.5*NETWORKDAYS.INTL(_xlpm.ep,_xlpm.dfin-1,"0000111",_xlpm.fer)+6*NETWORKDAYS.INTL(_xlpm.ep,_xlpm.dfin-1,"1111011",_xlpm.fer)+IF(OR(WEEKDAY(_xlpm.dfin,2)>5,COUNTIF(_xlpm.fer,_xlpm.dfin)>0),0,MAX(0,MIN(_xlpm.fin-_xlpm.dfin,IF(WEEKDAY(_xlpm.dfin,2)=5,14/24,17.5/24))-8/24)*24),_xlpm.hrs,IF(SCTR_Brokers[[#This Row],[Estado]]="FINALIZADO",MAX(0,_xlpm.hfin-_xlpm.hini),IF(SCTR_Brokers[[#This Row],[Horas_Transcurridas]]="",MAX(0,_xlpm.hfin-_xlpm.hini),SCTR_Brokers[[#This Row],[Horas_Transcurridas]])),IF(_xlpm.hrs<=LISTAS!$E$3,LISTAS!$J$3,LISTAS!$J$4))) -> Dentro | T22: =IF(SCTR_Brokers[[#This Row],[FechaRecepcion]]="","",TEXT(SCTR_Brokers[[#This Row],[FechaRecepcion]],"mmmm")&" "&YEAR(SCTR_Brokers[[#This Row],[FechaRecepcion]])) -> agosto 2026 | U22: =IF(SCTR_Brokers[[#This Row],[Estado]]="FINALIZADO",1,0) -> 1 | V22: =IF(SCTR_Brokers[[#This Row],[FechaRecepcion]]="","",IF(SCTR_Brokers[[#This Row],[Estado]]="FINALIZADO",0,1)) -> 0 | W22: =IF(AND(SCTR_Brokers[[#This Row],[Estado]]="FINALIZADO",SCTR_Brokers[[#This Row],[Plazo]]=LISTAS!$J$3),1,0) -> 1 | X22: =IF(AND(SCTR_Brokers[[#This Row],[Estado]]="FINALIZADO",SCTR_Brokers[[#This Row],[Plazo]]=LISTAS!$J$4),1,0) -> 0 | Y22: =IF(AND(SCTR_Brokers[[#This Row],[Estado]]<>"FINALIZADO",SCTR_Brokers[[#This Row],[Plazo]]=LISTAS!$J$4),1,0) -> 0 | Z22: =IF(SCTR_Brokers[[#This Row],[Fecha_Solic_Informe]]="",0,1) -> 0 | AA22: =IF(SCTR_Brokers[[#This Row],[Fecha_Informe]]="",0,1) -> 0 | AB22: =IF(AND(SCTR_Brokers[[#This Row],[Fecha_Solic_Informe]]<>"",SCTR_Brokers[[#This Row],[Fecha_Informe]]=""),1,0) -> 0 | AC22: =IF(AND(SCTR_Brokers[[#This Row],[Fecha_Solic_Informe]]<>"",SCTR_Brokers[[#This Row],[Fecha_Informe]]<>""),ROUND((SCTR_Brokers[[#This Row],[Fecha_Informe]]-SCTR_Brokers[[#This Row],[Fecha_Solic_Informe]])*24,1),"")
A23: AAQkADdkNThjNzFkLWM0ZmMtNDJhYS04MDVlLTIwNzE4ZDI1Mzg4YgAQAKqb5xWndDpBvqEi82SUhBo= | C23: =IF(SCTR_Brokers[[#This Row],[FechaRecepcion]]="","",SCTR_Brokers[[#This Row],[ConversationId]]&"-"&TEXT(SCTR_Brokers[[#This Row],[FechaRecepcion]],"aaaammddhhmmss")) -> AAQkADdkNThjNzFkLWM0ZmMtNDJhYS04MDVlLTIwNzE4ZDI1Mzg4YgAQAKqb5xWndDpBvqEi82SUhBo=-20260814155245 | D23: AUTORIZACION ATENCION SCTR - ASEG. RAYMUNDO CHAVEZ ROSA | E23: MARSH | F23: 46248.662 | G23: 46251.67 | H23: guisella.aponte@mercermarshbeneficios.com | I23: FINALIZADO | K23: SCTR SALUD | N23: =IF(SCTR_Brokers[[#This Row],[FechaRecepcion]]="","",IF(SCTR_Brokers[[#This Row],[Estado]]="FINALIZADO","",IF(SCTR_Brokers[[#This Row],[FechaUltimaRespuesta]]="","",_xlfn.LET(_xlpm.fer,LISTAS!$L$3:$L$100,_xlpm.ep,DATE(2000,1,1),_xlpm.ini,SCTR_Brokers[[#This Row],[FechaUltimaRespuesta]],_xlpm.fin,NOW(),_xlpm.dini,INT(_xlpm.ini),_xlpm.dfin,INT(_xlpm.fin),_xlpm.hini,9.5*NETWORKDAYS.INTL(_xlpm.ep,_xlpm.dini-1,"0000111",_xlpm.fer)+6*NETWORKDAYS.INTL(_xlpm.ep,_xlpm.dini-1,"1111011",_xlpm.fer)+IF(OR(WEEKDAY(_xlpm.dini,2)>5,COUNTIF(_xlpm.fer,_xlpm.dini)>0),0,MAX(0,MIN(_xlpm.ini-_xlpm.dini,IF(WEEKDAY(_xlpm.dini,2)=5,14/24,17.5/24))-8/24)*24),_xlpm.hfin,9.5*NETWORKDAYS.INTL(_xlpm.ep,_xlpm.dfin-1,"0000111",_xlpm.fer)+6*NETWORKDAYS.INTL(_xlpm.ep,_xlpm.dfin-1,"1111011",_xlpm.fer)+IF(OR(WEEKDAY(_xlpm.dfin,2)>5,COUNTIF(_xlpm.fer,_xlpm.dfin)>0),0,MAX(0,MIN(_xlpm.fin-_xlpm.dfin,IF(WEEKDAY(_xlpm.dfin,2)=5,14/24,17.5/24))-8/24)*24),ROUND(MAX(0,_xlpm.hfin-_xlpm.hini),1))))) | Q23: 46251.67 | R23: =IF(SCTR_Brokers[[#This Row],[FechaRecepcion]]="","",_xlfn.LET(_xlpm.fer,LISTAS!$L$3:$L$100,_xlpm.ep,DATE(2000,1,1),_xlpm.ini,SCTR_Brokers[[#This Row],[FechaRecepcion]],_xlpm.fin,IF(SCTR_Brokers[[#This Row],[Fecha_Cierre]]<>"",SCTR_Brokers[[#This Row],[Fecha_Cierre]],NOW()),_xlpm.dini,INT(_xlpm.ini),_xlpm.dfin,INT(_xlpm.fin),_xlpm.hini,9.5*NETWORKDAYS.INTL(_xlpm.ep,_xlpm.dini-1,"0000111",_xlpm.fer)+6*NETWORKDAYS.INTL(_xlpm.ep,_xlpm.dini-1,"1111011",_xlpm.fer)+IF(OR(WEEKDAY(_xlpm.dini,2)>5,COUNTIF(_xlpm.fer,_xlpm.dini)>0),0,MAX(0,MIN(_xlpm.ini-_xlpm.dini,IF(WEEKDAY(_xlpm.dini,2)=5,14/24,17.5/24))-8/24)*24),_xlpm.hfin,9.5*NETWORKDAYS.INTL(_xlpm.ep,_xlpm.dfin-1,"0000111",_xlpm.fer)+6*NETWORKDAYS.INTL(_xlpm.ep,_xlpm.dfin-1,"1111011",_xlpm.fer)+IF(OR(WEEKDAY(_xlpm.dfin,2)>5,COUNTIF(_xlpm.fer,_xlpm.dfin)>0),0,MAX(0,MIN(_xlpm.fin-_xlpm.dfin,IF(WEEKDAY(_xlpm.dfin,2)=5,14/24,17.5/24))-8/24)*24),_xlpm.hrs,IF(SCTR_Brokers[[#This Row],[Estado]]="FINALIZADO",MAX(0,_xlpm.hfin-_xlpm.hini),IF(SCTR_Brokers[[#This Row],[Horas_Transcurridas]]="",MAX(0,_xlpm.hfin-_xlpm.hini),SCTR_Brokers[[#This Row],[Horas_Transcurridas]])),IF(_xlpm.hrs<=LISTAS!$E$3,LISTAS!$J$3,LISTAS!$J$4))) -> Fuera | T23: =IF(SCTR_Brokers[[#This Row],[FechaRecepcion]]="","",TEXT(SCTR_Brokers[[#This Row],[FechaRecepcion]],"mmmm")&" "&YEAR(SCTR_Brokers[[#This Row],[FechaRecepcion]])) -> agosto 2026 | U23: =IF(SCTR_Brokers[[#This Row],[Estado]]="FINALIZADO",1,0) -> 1 | V23: =IF(SCTR_Brokers[[#This Row],[FechaRecepcion]]="","",IF(SCTR_Brokers[[#This Row],[Estado]]="FINALIZADO",0,1)) -> 0 | W23: =IF(AND(SCTR_Brokers[[#This Row],[Estado]]="FINALIZADO",SCTR_Brokers[[#This Row],[Plazo]]=LISTAS!$J$3),1,0) -> 0 | X23: =IF(AND(SCTR_Brokers[[#This Row],[Estado]]="FINALIZADO",SCTR_Brokers[[#This Row],[Plazo]]=LISTAS!$J$4),1,0) -> 1 | Y23: =IF(AND(SCTR_Brokers[[#This Row],[Estado]]<>"FINALIZADO",SCTR_Brokers[[#This Row],[Plazo]]=LISTAS!$J$4),1,0) -> 0 | Z23: =IF(SCTR_Brokers[[#This Row],[Fecha_Solic_Informe]]="",0,1) -> 0 | AA23: =IF(SCTR_Brokers[[#This Row],[Fecha_Informe]]="",0,1) -> 0 | AB23: =IF(AND(SCTR_Brokers[[#This Row],[Fecha_Solic_Informe]]<>"",SCTR_Brokers[[#This Row],[Fecha_Informe]]=""),1,0) -> 0 | AC23: =IF(AND(SCTR_Brokers[[#This Row],[Fecha_Solic_Informe]]<>"",SCTR_Brokers[[#This Row],[Fecha_Informe]]<>""),ROUND((SCTR_Brokers[[#This Row],[Fecha_Informe]]-SCTR_Brokers[[#This Row],[Fecha_Solic_Informe]])*24,1),"")
A24: AAQkADdkNThjNzFkLWM0ZmMtNDJhYS04MDVlLTIwNzE4ZDI1Mzg4YgAQAHxs9sqdkTpGvBXLONcmbdw= | C24: =IF(SCTR_Brokers[[#This Row],[FechaRecepcion]]="","",SCTR_Brokers[[#This Row],[ConversationId]]&"-"&TEXT(SCTR_Brokers[[#This Row],[FechaRecepcion]],"aaaammddhhmmss")) -> AAQkADdkNThjNzFkLWM0ZmMtNDJhYS04MDVlLTIwNzE4ZDI1Mzg4YgAQAHxs9sqdkTpGvBXLONcmbdw=-20260814171411 | D24: SOLICITUD DE PROTESIS / SCTR SALUD / ASG PEREZ GONZALES ISBER / GALILEA / MAPFRE | E24: HOWDEN | F24: 46248.718 | G24: 46251.416 | H24: sctrsalud@mapfre.com.pe | I24: FINALIZADO | K24: SCTR SALUD | N24: =IF(SCTR_Brokers[[#This Row],[FechaRecepcion]]="","",IF(SCTR_Brokers[[#This Row],[Estado]]="FINALIZADO","",IF(SCTR_Brokers[[#This Row],[FechaUltimaRespuesta]]="","",_xlfn.LET(_xlpm.fer,LISTAS!$L$3:$L$100,_xlpm.ep,DATE(2000,1,1),_xlpm.ini,SCTR_Brokers[[#This Row],[FechaUltimaRespuesta]],_xlpm.fin,NOW(),_xlpm.dini,INT(_xlpm.ini),_xlpm.dfin,INT(_xlpm.fin),_xlpm.hini,9.5*NETWORKDAYS.INTL(_xlpm.ep,_xlpm.dini-1,"0000111",_xlpm.fer)+6*NETWORKDAYS.INTL(_xlpm.ep,_xlpm.dini-1,"1111011",_xlpm.fer)+IF(OR(WEEKDAY(_xlpm.dini,2)>5,COUNTIF(_xlpm.fer,_xlpm.dini)>0),0,MAX(0,MIN(_xlpm.ini-_xlpm.dini,IF(WEEKDAY(_xlpm.dini,2)=5,14/24,17.5/24))-8/24)*24),_xlpm.hfin,9.5*NETWORKDAYS.INTL(_xlpm.ep,_xlpm.dfin-1,"0000111",_xlpm.fer)+6*NETWORKDAYS.INTL(_xlpm.ep,_xlpm.dfin-1,"1111011",_xlpm.fer)+IF(OR(WEEKDAY(_xlpm.dfin,2)>5,COUNTIF(_xlpm.fer,_xlpm.dfin)>0),0,MAX(0,MIN(_xlpm.fin-_xlpm.dfin,IF(WEEKDAY(_xlpm.dfin,2)=5,14/24,17.5/24))-8/24)*24),ROUND(MAX(0,_xlpm.hfin-_xlpm.hini),1))))) | Q24: 46251.416 | R24: =IF(SCTR_Brokers[[#This Row],[FechaRecepcion]]="","",_xlfn.LET(_xlpm.fer,LISTAS!$L$3:$L$100,_xlpm.ep,DATE(2000,1,1),_xlpm.ini,SCTR_Brokers[[#This Row],[FechaRecepcion]],_xlpm.fin,IF(SCTR_Brokers[[#This Row],[Fecha_Cierre]]<>"",SCTR_Brokers[[#This Row],[Fecha_Cierre]],NOW()),_xlpm.dini,INT(_xlpm.ini),_xlpm.dfin,INT(_xlpm.fin),_xlpm.hini,9.5*NETWORKDAYS.INTL(_xlpm.ep,_xlpm.dini-1,"0000111",_xlpm.fer)+6*NETWORKDAYS.INTL(_xlpm.ep,_xlpm.dini-1,"1111011",_xlpm.fer)+IF(OR(WEEKDAY(_xlpm.dini,2)>5,COUNTIF(_xlpm.fer,_xlpm.dini)>0),0,MAX(0,MIN(_xlpm.ini-_xlpm.dini,IF(WEEKDAY(_xlpm.dini,2)=5,14/24,17.5/24))-8/24)*24),_xlpm.hfin,9.5*NETWORKDAYS.INTL(_xlpm.ep,_xlpm.dfin-1,"0000111",_xlpm.fer)+6*NETWORKDAYS.INTL(_xlpm.ep,_xlpm.dfin-1,"1111011",_xlpm.fer)+IF(OR(WEEKDAY(_xlpm.dfin,2)>5,COUNTIF(_xlpm.fer,_xlpm.dfin)>0),0,MAX(0,MIN(_xlpm.fin-_xlpm.dfin,IF(WEEKDAY(_xlpm.dfin,2)=5,14/24,17.5/24))-8/24)*24),_xlpm.hrs,IF(SCTR_Brokers[[#This Row],[Estado]]="FINALIZADO",MAX(0,_xlpm.hfin-_xlpm.hini),IF(SCTR_Brokers[[#This Row],[Horas_Transcurridas]]="",MAX(0,_xlpm.hfin-_xlpm.hini),SCTR_Brokers[[#This Row],[Horas_Transcurridas]])),IF(_xlpm.hrs<=LISTAS!$E$3,LISTAS!$J$3,LISTAS!$J$4))) -> Dentro | T24: =IF(SCTR_Brokers[[#This Row],[FechaRecepcion]]="","",TEXT(SCTR_Brokers[[#This Row],[FechaRecepcion]],"mmmm")&" "&YEAR(SCTR_Brokers[[#This Row],[FechaRecepcion]])) -> agosto 2026 | U24: =IF(SCTR_Brokers[[#This Row],[Estado]]="FINALIZADO",1,0) -> 1 | V24: =IF(SCTR_Brokers[[#This Row],[FechaRecepcion]]="","",IF(SCTR_Brokers[[#This Row],[Estado]]="FINALIZADO",0,1)) -> 0 | W24: =IF(AND(SCTR_Brokers[[#This Row],[Estado]]="FINALIZADO",SCTR_Brokers[[#This Row],[Plazo]]=LISTAS!$J$3),1,0) -> 1 | X24: =IF(AND(SCTR_Brokers[[#This Row],[Estado]]="FINALIZADO",SCTR_Brokers[[#This Row],[Plazo]]=LISTAS!$J$4),1,0) -> 0 | Y24: =IF(AND(SCTR_Brokers[[#This Row],[Estado]]<>"FINALIZADO",SCTR_Brokers[[#This Row],[Plazo]]=LISTAS!$J$4),1,0) -> 0 | Z24: =IF(SCTR_Brokers[[#This Row],[Fecha_Solic_Informe]]="",0,1) -> 0 | AA24: =IF(SCTR_Brokers[[#This Row],[Fecha_Informe]]="",0,1) -> 0 | AB24: =IF(AND(SCTR_Brokers[[#This Row],[Fecha_Solic_Informe]]<>"",SCTR_Brokers[[#This Row],[Fecha_Informe]]=""),1,0) -> 0 | AC24: =IF(AND(SCTR_Brokers[[#This Row],[Fecha_Solic_Informe]]<>"",SCTR_Brokers[[#This Row],[Fecha_Informe]]<>""),ROUND((SCTR_Brokers[[#This Row],[Fecha_Informe]]-SCTR_Brokers[[#This Row],[Fecha_Solic_Informe]])*24,1),"")
A25: AAQkADdkNThjNzFkLWM0ZmMtNDJhYS04MDVlLTIwNzE4ZDI1Mzg4YgAQAEgjq3kKTEBgskkgYt1qMZI= | C25: =IF(SCTR_Brokers[[#This Row],[FechaRecepcion]]="","",SCTR_Brokers[[#This Row],[ConversationId]]&"-"&TEXT(SCTR_Brokers[[#This Row],[FechaRecepcion]],"aaaammddhhmmss")) -> AAQkADdkNThjNzFkLWM0ZmMtNDJhYS04MDVlLTIwNzE4ZDI1Mzg4YgAQAEgjq3kKTEBgskkgYt1qMZI=-20260814184751 | D25: RV: URGENTE: SOLCITUD NUMERO DE EXPEDIENTE - CASO ALANIS MUNARRIZ - EMERGENT COLD SOLUCIONES INTEGRALES | E25: MARSH | F25: 46248.783 | G25: 46248.783 | H25: Katherine.Andrade@marsh.com | I25: FINALIZADO | K25: SCTR SALUD | N25: =IF(SCTR_Brokers[[#This Row],[FechaRecepcion]]="","",IF(SCTR_Brokers[[#This Row],[Estado]]="FINALIZADO","",IF(SCTR_Brokers[[#This Row],[FechaUltimaRespuesta]]="","",_xlfn.LET(_xlpm.fer,LISTAS!$L$3:$L$100,_xlpm.ep,DATE(2000,1,1),_xlpm.ini,SCTR_Brokers[[#This Row],[FechaUltimaRespuesta]],_xlpm.fin,NOW(),_xlpm.dini,INT(_xlpm.ini),_xlpm.dfin,INT(_xlpm.fin),_xlpm.hini,9.5*NETWORKDAYS.INTL(_xlpm.ep,_xlpm.dini-1,"0000111",_xlpm.fer)+6*NETWORKDAYS.INTL(_xlpm.ep,_xlpm.dini-1,"1111011",_xlpm.fer)+IF(OR(WEEKDAY(_xlpm.dini,2)>5,COUNTIF(_xlpm.fer,_xlpm.dini)>0),0,MAX(0,MIN(_xlpm.ini-_xlpm.dini,IF(WEEKDAY(_xlpm.dini,2)=5,14/24,17.5/24))-8/24)*24),_xlpm.hfin,9.5*NETWORKDAYS.INTL(_xlpm.ep,_xlpm.dfin-1,"0000111",_xlpm.fer)+6*NETWORKDAYS.INTL(_xlpm.ep,_xlpm.dfin-1,"1111011",_xlpm.fer)+IF(OR(WEEKDAY(_xlpm.dfin,2)>5,COUNTIF(_xlpm.fer,_xlpm.dfin)>0),0,MAX(0,MIN(_xlpm.fin-_xlpm.dfin,IF(WEEKDAY(_xlpm.dfin,2)=5,14/24,17.5/24))-8/24)*24),ROUND(MAX(0,_xlpm.hfin-_xlpm.hini),1))))) | Q25: 46251.445 | R25: =IF(SCTR_Brokers[[#This Row],[FechaRecepcion]]="","",_xlfn.LET(_xlpm.fer,LISTAS!$L$3:$L$100,_xlpm.ep,DATE(2000,1,1),_xlpm.ini,SCTR_Brokers[[#This Row],[FechaRecepcion]],_xlpm.fin,IF(SCTR_Brokers[[#This Row],[Fecha_Cierre]]<>"",SCTR_Brokers[[#This Row],[Fecha_Cierre]],NOW()),_xlpm.dini,INT(_xlpm.ini),_xlpm.dfin,INT(_xlpm.fin),_xlpm.hini,9.5*NETWORKDAYS.INTL(_xlpm.ep,_xlpm.dini-1,"0000111",_xlpm.fer)+6*NETWORKDAYS.INTL(_xlpm.ep,_xlpm.dini-1,"1111011",_xlpm.fer)+IF(OR(WEEKDAY(_xlpm.dini,2)>5,COUNTIF(_xlpm.fer,_xlpm.dini)>0),0,MAX(0,MIN(_xlpm.ini-_xlpm.dini,IF(WEEKDAY(_xlpm.dini,2)=5,14/24,17.5/24))-8/24)*24),_xlpm.hfin,9.5*NETWORKDAYS.INTL(_xlpm.ep,_xlpm.dfin-1,"0000111",_xlpm.fer)+6*NETWORKDAYS.INTL(_xlpm.ep,_xlpm.dfin-1,"1111011",_xlpm.fer)+IF(OR(WEEKDAY(_xlpm.dfin,2)>5,COUNTIF(_xlpm.fer,_xlpm.dfin)>0),0,MAX(0,MIN(_xlpm.fin-_xlpm.dfin,IF(WEEKDAY(_xlpm.dfin,2)=5,14/24,17.5/24))-8/24)*24),_xlpm.hrs,IF(SCTR_Brokers[[#This Row],[Estado]]="FINALIZADO",MAX(0,_xlpm.hfin-_xlpm.hini),IF(SCTR_Brokers[[#This Row],[Horas_Transcurridas]]="",MAX(0,_xlpm.hfin-_xlpm.hini),SCTR_Brokers[[#This Row],[Horas_Transcurridas]])),IF(_xlpm.hrs<=LISTAS!$E$3,LISTAS!$J$3,LISTAS!$J$4))) -> Dentro | T25: =IF(SCTR_Brokers[[#This Row],[FechaRecepcion]]="","",TEXT(SCTR_Brokers[[#This Row],[FechaRecepcion]],"mmmm")&" "&YEAR(SCTR_Brokers[[#This Row],[FechaRecepcion]])) -> agosto 2026 | U25: =IF(SCTR_Brokers[[#This Row],[Estado]]="FINALIZADO",1,0) -> 1 | V25: =IF(SCTR_Brokers[[#This Row],[FechaRecepcion]]="","",IF(SCTR_Brokers[[#This Row],[Estado]]="FINALIZADO",0,1)) -> 0 | W25: =IF(AND(SCTR_Brokers[[#This Row],[Estado]]="FINALIZADO",SCTR_Brokers[[#This Row],[Plazo]]=LISTAS!$J$3),1,0) -> 1 | X25: =IF(AND(SCTR_Brokers[[#This Row],[Estado]]="FINALIZADO",SCTR_Brokers[[#This Row],[Plazo]]=LISTAS!$J$4),1,0) -> 0 | Y25: =IF(AND(SCTR_Brokers[[#This Row],[Estado]]<>"FINALIZADO",SCTR_Brokers[[#This Row],[Plazo]]=LISTAS!$J$4),1,0) -> 0 | Z25: =IF(SCTR_Brokers[[#This Row],[Fecha_Solic_Informe]]="",0,1) -> 0 | AA25: =IF(SCTR_Brokers[[#This Row],[Fecha_Informe]]="",0,1) -> 0 | AB25: =IF(AND(SCTR_Brokers[[#This Row],[Fecha_Solic_Informe]]<>"",SCTR_Brokers[[#This Row],[Fecha_Informe]]=""),1,0) -> 0 | AC25: =IF(AND(SCTR_Brokers[[#This Row],[Fecha_Solic_Informe]]<>"",SCTR_Brokers[[#This Row],[Fecha_Informe]]<>""),ROUND((SCTR_Brokers[[#This Row],[Fecha_Informe]]-SCTR_Brokers[[#This Row],[Fecha_Solic_Informe]])*24,1),"")
A26: AAQkADdkNThjNzFkLWM0ZmMtNDJhYS04MDVlLTIwNzE4ZDI1Mzg4YgAQAJUvwckyVvNFuzFeVSuR08E= | C26: =IF(SCTR_Brokers[[#This Row],[FechaRecepcion]]="","",SCTR_Brokers[[#This Row],[ConversationId]]&"-"&TEXT(SCTR_Brokers[[#This Row],[FechaRecepcion]],"aaaammddhhmmss")) -> AAQkADdkNThjNzFkLWM0ZmMtNDJhYS04MDVlLTIwNzE4ZDI1Mzg4YgAQAJUvwckyVvNFuzFeVSuR08E=-20260816195354 | D26: RE: **3er recordatorio** CORPORACION INVERSIONES LYS S.A. / SCTR SALUD MAPFRE / ALFONSO FAUSTINO CORBERA JAQUI / ATENCION DE MEDICAMENTO - PODOLOGÍA | E26: ARTHUR GALLAGHER | F26: 46250.829 | G26: 46251.459 | H26: sctrsalud@mapfre.com.pe | I26: FINALIZADO | K26: SCTR SALUD | N26: =IF(SCTR_Brokers[[#This Row],[FechaRecepcion]]="","",IF(SCTR_Brokers[[#This Row],[Estado]]="FINALIZADO","",IF(SCTR_Brokers[[#This Row],[FechaUltimaRespuesta]]="","",_xlfn.LET(_xlpm.fer,LISTAS!$L$3:$L$100,_xlpm.ep,DATE(2000,1,1),_xlpm.ini,SCTR_Brokers[[#This Row],[FechaUltimaRespuesta]],_xlpm.fin,NOW(),_xlpm.dini,INT(_xlpm.ini),_xlpm.dfin,INT(_xlpm.fin),_xlpm.hini,9.5*NETWORKDAYS.INTL(_xlpm.ep,_xlpm.dini-1,"0000111",_xlpm.fer)+6*NETWORKDAYS.INTL(_xlpm.ep,_xlpm.dini-1,"1111011",_xlpm.fer)+IF(OR(WEEKDAY(_xlpm.dini,2)>5,COUNTIF(_xlpm.fer,_xlpm.dini)>0),0,MAX(0,MIN(_xlpm.ini-_xlpm.dini,IF(WEEKDAY(_xlpm.dini,2)=5,14/24,17.5/24))-8/24)*24),_xlpm.hfin,9.5*NETWORKDAYS.INTL(_xlpm.ep,_xlpm.dfin-1,"0000111",_xlpm.fer)+6*NETWORKDAYS.INTL(_xlpm.ep,_xlpm.dfin-1,"1111011",_xlpm.fer)+IF(OR(WEEKDAY(_xlpm.dfin,2)>5,COUNTIF(_xlpm.fer,_xlpm.dfin)>0),0,MAX(0,MIN(_xlpm.fin-_xlpm.dfin,IF(WEEKDAY(_xlpm.dfin,2)=5,14/24,17.5/24))-8/24)*24),ROUND(MAX(0,_xlpm.hfin-_xlpm.hini),1))))) | Q26: 46251.459 | R26: =IF(SCTR_Brokers[[#This Row],[FechaRecepcion]]="","",_xlfn.LET(_xlpm.fer,LISTAS!$L$3:$L$100,_xlpm.ep,DATE(2000,1,1),_xlpm.ini,SCTR_Brokers[[#This Row],[FechaRecepcion]],_xlpm.fin,IF(SCTR_Brokers[[#This Row],[Fecha_Cierre]]<>"",SCTR_Brokers[[#This Row],[Fecha_Cierre]],NOW()),_xlpm.dini,INT(_xlpm.ini),_xlpm.dfin,INT(_xlpm.fin),_xlpm.hini,9.5*NETWORKDAYS.INTL(_xlpm.ep,_xlpm.dini-1,"0000111",_xlpm.fer)+6*NETWORKDAYS.INTL(_xlpm.ep,_xlpm.dini-1,"1111011",_xlpm.fer)+IF(OR(WEEKDAY(_xlpm.dini,2)>5,COUNTIF(_xlpm.fer,_xlpm.dini)>0),0,MAX(0,MIN(_xlpm.ini-_xlpm.dini,IF(WEEKDAY(_xlpm.dini,2)=5,14/24,17.5/24))-8/24)*24),_xlpm.hfin,9.5*NETWORKDAYS.INTL(_xlpm.ep,_xlpm.dfin-1,"0000111",_xlpm.fer)+6*NETWORKDAYS.INTL(_xlpm.ep,_xlpm.dfin-1,"1111011",_xlpm.fer)+IF(OR(WEEKDAY(_xlpm.dfin,2)>5,COUNTIF(_xlpm.fer,_xlpm.dfin)>0),0,MAX(0,MIN(_xlpm.fin-_xlpm.dfin,IF(WEEKDAY(_xlpm.dfin,2)=5,14/24,17.5/24))-8/24)*24),_xlpm.hrs,IF(SCTR_Brokers[[#This Row],[Estado]]="FINALIZADO",MAX(0,_xlpm.hfin-_xlpm.hini),IF(SCTR_Brokers[[#This Row],[Horas_Transcurridas]]="",MAX(0,_xlpm.hfin-_xlpm.hini),SCTR_Brokers[[#This Row],[Horas_Transcurridas]])),IF(_xlpm.hrs<=LISTAS!$E$3,LISTAS!$J$3,LISTAS!$J$4))) -> Dentro | T26: =IF(SCTR_Brokers[[#This Row],[FechaRecepcion]]="","",TEXT(SCTR_Brokers[[#This Row],[FechaRecepcion]],"mmmm")&" "&YEAR(SCTR_Brokers[[#This Row],[FechaRecepcion]])) -> agosto 2026 | U26: =IF(SCTR_Brokers[[#This Row],[Estado]]="FINALIZADO",1,0) -> 1 | V26: =IF(SCTR_Brokers[[#This Row],[FechaRecepcion]]="","",IF(SCTR_Brokers[[#This Row],[Estado]]="FINALIZADO",0,1)) -> 0 | W26: =IF(AND(SCTR_Brokers[[#This Row],[Estado]]="FINALIZADO",SCTR_Brokers[[#This Row],[Plazo]]=LISTAS!$J$3),1,0) -> 1 | X26: =IF(AND(SCTR_Brokers[[#This Row],[Estado]]="FINALIZADO",SCTR_Brokers[[#This Row],[Plazo]]=LISTAS!$J$4),1,0) -> 0 | Y26: =IF(AND(SCTR_Brokers[[#This Row],[Estado]]<>"FINALIZADO",SCTR_Brokers[[#This Row],[Plazo]]=LISTAS!$J$4),1,0) -> 0 | Z26: =IF(SCTR_Brokers[[#This Row],[Fecha_Solic_Informe]]="",0,1) -> 0 | AA26: =IF(SCTR_Brokers[[#This Row],[Fecha_Informe]]="",0,1) -> 0 | AB26: =IF(AND(SCTR_Brokers[[#This Row],[Fecha_Solic_Informe]]<>"",SCTR_Brokers[[#This Row],[Fecha_Informe]]=""),1,0) -> 0 | AC26: =IF(AND(SCTR_Brokers[[#This Row],[Fecha_Solic_Informe]]<>"",SCTR_Brokers[[#This Row],[Fecha_Informe]]<>""),ROUND((SCTR_Brokers[[#This Row],[Fecha_Informe]]-SCTR_Brokers[[#This Row],[Fecha_Solic_Informe]])*24,1),"")
A27: AAQkADdkNThjNzFkLWM0ZmMtNDJhYS04MDVlLTIwNzE4ZDI1Mzg4YgAQAKx3ApF14n5Am1OvD8XqgLs= | C27: =IF(SCTR_Brokers[[#This Row],[FechaRecepcion]]="","",SCTR_Brokers[[#This Row],[ConversationId]]&"-"&TEXT(SCTR_Brokers[[#This Row],[FechaRecepcion]],"aaaammddhhmmss")) -> AAQkADdkNThjNzFkLWM0ZmMtNDJhYS04MDVlLTIwNzE4ZDI1Mzg4YgAQAKx3ApF14n5Am1OvD8XqgLs=-20260817094727 | D27: PRIORIDAD // GRUPO INTERCORP // Incidente laboratorio de carnes MK Cercado // Leguia Vilchez Mayra | E27: MARSH | F27: 46251.408 | G27: 46251.408 | H27: Brenda.Salazar@mercermarshbeneficios.com | I27: FINALIZADO | K27: SCTR SALUD | N27: =IF(SCTR_Brokers[[#This Row],[FechaRecepcion]]="","",IF(SCTR_Brokers[[#This Row],[Estado]]="FINALIZADO","",IF(SCTR_Brokers[[#This Row],[FechaUltimaRespuesta]]="","",_xlfn.LET(_xlpm.fer,LISTAS!$L$3:$L$100,_xlpm.ep,DATE(2000,1,1),_xlpm.ini,SCTR_Brokers[[#This Row],[FechaUltimaRespuesta]],_xlpm.fin,NOW(),_xlpm.dini,INT(_xlpm.ini),_xlpm.dfin,INT(_xlpm.fin),_xlpm.hini,9.5*NETWORKDAYS.INTL(_xlpm.ep,_xlpm.dini-1,"0000111",_xlpm.fer)+6*NETWORKDAYS.INTL(_xlpm.ep,_xlpm.dini-1,"1111011",_xlpm.fer)+IF(OR(WEEKDAY(_xlpm.dini,2)>5,COUNTIF(_xlpm.fer,_xlpm.dini)>0),0,MAX(0,MIN(_xlpm.ini-_xlpm.dini,IF(WEEKDAY(_xlpm.dini,2)=5,14/24,17.5/24))-8/24)*24),_xlpm.hfin,9.5*NETWORKDAYS.INTL(_xlpm.ep,_xlpm.dfin-1,"0000111",_xlpm.fer)+6*NETWORKDAYS.INTL(_xlpm.ep,_xlpm.dfin-1,"1111011",_xlpm.fer)+IF(OR(WEEKDAY(_xlpm.dfin,2)>5,COUNTIF(_xlpm.fer,_xlpm.dfin)>0),0,MAX(0,MIN(_xlpm.fin-_xlpm.dfin,IF(WEEKDAY(_xlpm.dfin,2)=5,14/24,17.5/24))-8/24)*24),ROUND(MAX(0,_xlpm.hfin-_xlpm.hini),1))))) | Q27: 46251.415 | R27: =IF(SCTR_Brokers[[#This Row],[FechaRecepcion]]="","",_xlfn.LET(_xlpm.fer,LISTAS!$L$3:$L$100,_xlpm.ep,DATE(2000,1,1),_xlpm.ini,SCTR_Brokers[[#This Row],[FechaRecepcion]],_xlpm.fin,IF(SCTR_Brokers[[#This Row],[Fecha_Cierre]]<>"",SCTR_Brokers[[#This Row],[Fecha_Cierre]],NOW()),_xlpm.dini,INT(_xlpm.ini),_xlpm.dfin,INT(_xlpm.fin),_xlpm.hini,9.5*NETWORKDAYS.INTL(_xlpm.ep,_xlpm.dini-1,"0000111",_xlpm.fer)+6*NETWORKDAYS.INTL(_xlpm.ep,_xlpm.dini-1,"1111011",_xlpm.fer)+IF(OR(WEEKDAY(_xlpm.dini,2)>5,COUNTIF(_xlpm.fer,_xlpm.dini)>0),0,MAX(0,MIN(_xlpm.ini-_xlpm.dini,IF(WEEKDAY(_xlpm.dini,2)=5,14/24,17.5/24))-8/24)*24),_xlpm.hfin,9.5*NETWORKDAYS.INTL(_xlpm.ep,_xlpm.dfin-1,"0000111",_xlpm.fer)+6*NETWORKDAYS.INTL(_xlpm.ep,_xlpm.dfin-1,"1111011",_xlpm.fer)+IF(OR(WEEKDAY(_xlpm.dfin,2)>5,COUNTIF(_xlpm.fer,_xlpm.dfin)>0),0,MAX(0,MIN(_xlpm.fin-_xlpm.dfin,IF(WEEKDAY(_xlpm.dfin,2)=5,14/24,17.5/24))-8/24)*24),_xlpm.hrs,IF(SCTR_Brokers[[#This Row],[Estado]]="FINALIZADO",MAX(0,_xlpm.hfin-_xlpm.hini),IF(SCTR_Brokers[[#This Row],[Horas_Transcurridas]]="",MAX(0,_xlpm.hfin-_xlpm.hini),SCTR_Brokers[[#This Row],[Horas_Transcurridas]])),IF(_xlpm.hrs<=LISTAS!$E$3,LISTAS!$J$3,LISTAS!$J$4))) -> Dentro | T27: =IF(SCTR_Brokers[[#This Row],[FechaRecepcion]]="","",TEXT(SCTR_Brokers[[#This Row],[FechaRecepcion]],"mmmm")&" "&YEAR(SCTR_Brokers[[#This Row],[FechaRecepcion]])) -> agosto 2026 | U27: =IF(SCTR_Brokers[[#This Row],[Estado]]="FINALIZADO",1,0) -> 1 | V27: =IF(SCTR_Brokers[[#This Row],[FechaRecepcion]]="","",IF(SCTR_Brokers[[#This Row],[Estado]]="FINALIZADO",0,1)) -> 0 | W27: =IF(AND(SCTR_Brokers[[#This Row],[Estado]]="FINALIZADO",SCTR_Brokers[[#This Row],[Plazo]]=LISTAS!$J$3),1,0) -> 1 | X27: =IF(AND(SCTR_Brokers[[#This Row],[Estado]]="FINALIZADO",SCTR_Brokers[[#This Row],[Plazo]]=LISTAS!$J$4),1,0) -> 0 | Y27: =IF(AND(SCTR_Brokers[[#This Row],[Estado]]<>"FINALIZADO",SCTR_Brokers[[#This Row],[Plazo]]=LISTAS!$J$4),1,0) -> 0 | Z27: =IF(SCTR_Brokers[[#This Row],[Fecha_Solic_Informe]]="",0,1) -> 0 | AA27: =IF(SCTR_Brokers[[#This Row],[Fecha_Informe]]="",0,1) -> 0 | AB27: =IF(AND(SCTR_Brokers[[#This Row],[Fecha_Solic_Informe]]<>"",SCTR_Brokers[[#This Row],[Fecha_Informe]]=""),1,0) -> 0 | AC27: =IF(AND(SCTR_Brokers[[#This Row],[Fecha_Solic_Informe]]<>"",SCTR_Brokers[[#This Row],[Fecha_Informe]]<>""),ROUND((SCTR_Brokers[[#This Row],[Fecha_Informe]]-SCTR_Brokers[[#This Row],[Fecha_Solic_Informe]])*24,1),"")
A28: AAQkADdkNThjNzFkLWM0ZmMtNDJhYS04MDVlLTIwNzE4ZDI1Mzg4YgAQANSE-aJEkslGlaoAXMxZ9lw= | C28: =IF(SCTR_Brokers[[#This Row],[FechaRecepcion]]="","",SCTR_Brokers[[#This Row],[ConversationId]]&"-"&TEXT(SCTR_Brokers[[#This Row],[FechaRecepcion]],"aaaammddhhmmss")) -> AAQkADdkNThjNzFkLWM0ZmMtNDJhYS04MDVlLTIwNzE4ZDI1Mzg4YgAQANSE-aJEkslGlaoAXMxZ9lw=-20260817100012 | D28: RV: TAMSHI: IMPORTANTE_CASO: ZAMBRANO TUANAMA ANTONIO | E28: MARSH | F28: 46251.417 | G28: 46251.48 | H28: sctrsalud@mapfre.com.pe | I28: FINALIZADO | K28: SCTR SALUD | N28: =IF(SCTR_Brokers[[#This Row],[FechaRecepcion]]="","",IF(SCTR_Brokers[[#This Row],[Estado]]="FINALIZADO","",IF(SCTR_Brokers[[#This Row],[FechaUltimaRespuesta]]="","",_xlfn.LET(_xlpm.fer,LISTAS!$L$3:$L$100,_xlpm.ep,DATE(2000,1,1),_xlpm.ini,SCTR_Brokers[[#This Row],[FechaUltimaRespuesta]],_xlpm.fin,NOW(),_xlpm.dini,INT(_xlpm.ini),_xlpm.dfin,INT(_xlpm.fin),_xlpm.hini,9.5*NETWORKDAYS.INTL(_xlpm.ep,_xlpm.dini-1,"0000111",_xlpm.fer)+6*NETWORKDAYS.INTL(_xlpm.ep,_xlpm.dini-1,"1111011",_xlpm.fer)+IF(OR(WEEKDAY(_xlpm.dini,2)>5,COUNTIF(_xlpm.fer,_xlpm.dini)>0),0,MAX(0,MIN(_xlpm.ini-_xlpm.dini,IF(WEEKDAY(_xlpm.dini,2)=5,14/24,17.5/24))-8/24)*24),_xlpm.hfin,9.5*NETWORKDAYS.INTL(_xlpm.ep,_xlpm.dfin-1,"0000111",_xlpm.fer)+6*NETWORKDAYS.INTL(_xlpm.ep,_xlpm.dfin-1,"1111011",_xlpm.fer)+IF(OR(WEEKDAY(_xlpm.dfin,2)>5,COUNTIF(_xlpm.fer,_xlpm.dfin)>0),0,MAX(0,MIN(_xlpm.fin-_xlpm.dfin,IF(WEEKDAY(_xlpm.dfin,2)=5,14/24,17.5/24))-8/24)*24),ROUND(MAX(0,_xlpm.hfin-_xlpm.hini),1))))) | Q28: 46251.48 | R28: =IF(SCTR_Brokers[[#This Row],[FechaRecepcion]]="","",_xlfn.LET(_xlpm.fer,LISTAS!$L$3:$L$100,_xlpm.ep,DATE(2000,1,1),_xlpm.ini,SCTR_Brokers[[#This Row],[FechaRecepcion]],_xlpm.fin,IF(SCTR_Brokers[[#This Row],[Fecha_Cierre]]<>"",SCTR_Brokers[[#This Row],[Fecha_Cierre]],NOW()),_xlpm.dini,INT(_xlpm.ini),_xlpm.dfin,INT(_xlpm.fin),_xlpm.hini,9.5*NETWORKDAYS.INTL(_xlpm.ep,_xlpm.dini-1,"0000111",_xlpm.fer)+6*NETWORKDAYS.INTL(_xlpm.ep,_xlpm.dini-1,"1111011",_xlpm.fer)+IF(OR(WEEKDAY(_xlpm.dini,2)>5,COUNTIF(_xlpm.fer,_xlpm.dini)>0),0,MAX(0,MIN(_xlpm.ini-_xlpm.dini,IF(WEEKDAY(_xlpm.dini,2)=5,14/24,17.5/24))-8/24)*24),_xlpm.hfin,9.5*NETWORKDAYS.INTL(_xlpm.ep,_xlpm.dfin-1,"0000111",_xlpm.fer)+6*NETWORKDAYS.INTL(_xlpm.ep,_xlpm.dfin-1,"1111011",_xlpm.fer)+IF(OR(WEEKDAY(_xlpm.dfin,2)>5,COUNTIF(_xlpm.fer,_xlpm.dfin)>0),0,MAX(0,MIN(_xlpm.fin-_xlpm.dfin,IF(WEEKDAY(_xlpm.dfin,2)=5,14/24,17.5/24))-8/24)*24),_xlpm.hrs,IF(SCTR_Brokers[[#This Row],[Estado]]="FINALIZADO",MAX(0,_xlpm.hfin-_xlpm.hini),IF(SCTR_Brokers[[#This Row],[Horas_Transcurridas]]="",MAX(0,_xlpm.hfin-_xlpm.hini),SCTR_Brokers[[#This Row],[Horas_Transcurridas]])),IF(_xlpm.hrs<=LISTAS!$E$3,LISTAS!$J$3,LISTAS!$J$4))) -> Dentro | T28: =IF(SCTR_Brokers[[#This Row],[FechaRecepcion]]="","",TEXT(SCTR_Brokers[[#This Row],[FechaRecepcion]],"mmmm")&" "&YEAR(SCTR_Brokers[[#This Row],[FechaRecepcion]])) -> agosto 2026 | U28: =IF(SCTR_Brokers[[#This Row],[Estado]]="FINALIZADO",1,0) -> 1 | V28: =IF(SCTR_Brokers[[#This Row],[FechaRecepcion]]="","",IF(SCTR_Brokers[[#This Row],[Estado]]="FINALIZADO",0,1)) -> 0 | W28: =IF(AND(SCTR_Brokers[[#This Row],[Estado]]="FINALIZADO",SCTR_Brokers[[#This Row],[Plazo]]=LISTAS!$J$3),1,0) -> 1 | X28: =IF(AND(SCTR_Brokers[[#This Row],[Estado]]="FINALIZADO",SCTR_Brokers[[#This Row],[Plazo]]=LISTAS!$J$4),1,0) -> 0 | Y28: =IF(AND(SCTR_Brokers[[#This Row],[Estado]]<>"FINALIZADO",SCTR_Brokers[[#This Row],[Plazo]]=LISTAS!$J$4),1,0) -> 0 | Z28: =IF(SCTR_Brokers[[#This Row],[Fecha_Solic_Informe]]="",0,1) -> 0 | AA28: =IF(SCTR_Brokers[[#This Row],[Fecha_Informe]]="",0,1) -> 0 | AB28: =IF(AND(SCTR_Brokers[[#This Row],[Fecha_Solic_Informe]]<>"",SCTR_Brokers[[#This Row],[Fecha_Informe]]=""),1,0) -> 0 | AC28: =IF(AND(SCTR_Brokers[[#This Row],[Fecha_Solic_Informe]]<>"",SCTR_Brokers[[#This Row],[Fecha_Informe]]<>""),ROUND((SCTR_Brokers[[#This Row],[Fecha_Informe]]-SCTR_Brokers[[#This Row],[Fecha_Solic_Informe]])*24,1),"")
A29: AAQkADdkNThjNzFkLWM0ZmMtNDJhYS04MDVlLTIwNzE4ZDI1Mzg4YgAQAJSk1HVJhQ9CjRWRk8DjuCk= | C29: =IF(SCTR_Brokers[[#This Row],[FechaRecepcion]]="","",SCTR_Brokers[[#This Row],[ConversationId]]&"-"&TEXT(SCTR_Brokers[[#This Row],[FechaRecepcion]],"aaaammddhhmmss")) -> AAQkADdkNThjNzFkLWM0ZmMtNDJhYS04MDVlLTIwNzE4ZDI1Mzg4YgAQAJSk1HVJhQ9CjRWRk8DjuCk=-20260817100757 | D29: RE: PRIORIDAD // GRUPO INTERCORP // MK SMP CASO PROMOTOR DE CAMPO ACCDIDENTE // MAKRO | E29: MARSH | F29: 46251.422 | G29: 46251.422 | H29: Brenda.Salazar@mercermarshbeneficios.com | I29: FINALIZADO | K29: SCTR SALUD | N29: =IF(SCTR_Brokers[[#This Row],[FechaRecepcion]]="","",IF(SCTR_Brokers[[#This Row],[Estado]]="FINALIZADO","",IF(SCTR_Brokers[[#This Row],[FechaUltimaRespuesta]]="","",_xlfn.LET(_xlpm.fer,LISTAS!$L$3:$L$100,_xlpm.ep,DATE(2000,1,1),_xlpm.ini,SCTR_Brokers[[#This Row],[FechaUltimaRespuesta]],_xlpm.fin,NOW(),_xlpm.dini,INT(_xlpm.ini),_xlpm.dfin,INT(_xlpm.fin),_xlpm.hini,9.5*NETWORKDAYS.INTL(_xlpm.ep,_xlpm.dini-1,"0000111",_xlpm.fer)+6*NETWORKDAYS.INTL(_xlpm.ep,_xlpm.dini-1,"1111011",_xlpm.fer)+IF(OR(WEEKDAY(_xlpm.dini,2)>5,COUNTIF(_xlpm.fer,_xlpm.dini)>0),0,MAX(0,MIN(_xlpm.ini-_xlpm.dini,IF(WEEKDAY(_xlpm.dini,2)=5,14/24,17.5/24))-8/24)*24),_xlpm.hfin,9.5*NETWORKDAYS.INTL(_xlpm.ep,_xlpm.dfin-1,"0000111",_xlpm.fer)+6*NETWORKDAYS.INTL(_xlpm.ep,_xlpm.dfin-1,"1111011",_xlpm.fer)+IF(OR(WEEKDAY(_xlpm.dfin,2)>5,COUNTIF(_xlpm.fer,_xlpm.dfin)>0),0,MAX(0,MIN(_xlpm.fin-_xlpm.dfin,IF(WEEKDAY(_xlpm.dfin,2)=5,14/24,17.5/24))-8/24)*24),ROUND(MAX(0,_xlpm.hfin-_xlpm.hini),1))))) | Q29: 46251.422 | R29: =IF(SCTR_Brokers[[#This Row],[FechaRecepcion]]="","",_xlfn.LET(_xlpm.fer,LISTAS!$L$3:$L$100,_xlpm.ep,DATE(2000,1,1),_xlpm.ini,SCTR_Brokers[[#This Row],[FechaRecepcion]],_xlpm.fin,IF(SCTR_Brokers[[#This Row],[Fecha_Cierre]]<>"",SCTR_Brokers[[#This Row],[Fecha_Cierre]],NOW()),_xlpm.dini,INT(_xlpm.ini),_xlpm.dfin,INT(_xlpm.fin),_xlpm.hini,9.5*NETWORKDAYS.INTL(_xlpm.ep,_xlpm.dini-1,"0000111",_xlpm.fer)+6*NETWORKDAYS.INTL(_xlpm.ep,_xlpm.dini-1,"1111011",_xlpm.fer)+IF(OR(WEEKDAY(_xlpm.dini,2)>5,COUNTIF(_xlpm.fer,_xlpm.dini)>0),0,MAX(0,MIN(_xlpm.ini-_xlpm.dini,IF(WEEKDAY(_xlpm.dini,2)=5,14/24,17.5/24))-8/24)*24),_xlpm.hfin,9.5*NETWORKDAYS.INTL(_xlpm.ep,_xlpm.dfin-1,"0000111",_xlpm.fer)+6*NETWORKDAYS.INTL(_xlpm.ep,_xlpm.dfin-1,"1111011",_xlpm.fer)+IF(OR(WEEKDAY(_xlpm.dfin,2)>5,COUNTIF(_xlpm.fer,_xlpm.dfin)>0),0,MAX(0,MIN(_xlpm.fin-_xlpm.dfin,IF(WEEKDAY(_xlpm.dfin,2)=5,14/24,17.5/24))-8/24)*24),_xlpm.hrs,IF(SCTR_Brokers[[#This Row],[Estado]]="FINALIZADO",MAX(0,_xlpm.hfin-_xlpm.hini),IF(SCTR_Brokers[[#This Row],[Horas_Transcurridas]]="",MAX(0,_xlpm.hfin-_xlpm.hini),SCTR_Brokers[[#This Row],[Horas_Transcurridas]])),IF(_xlpm.hrs<=LISTAS!$E$3,LISTAS!$J$3,LISTAS!$J$4))) -> Dentro | T29: =IF(SCTR_Brokers[[#This Row],[FechaRecepcion]]="","",TEXT(SCTR_Brokers[[#This Row],[FechaRecepcion]],"mmmm")&" "&YEAR(SCTR_Brokers[[#This Row],[FechaRecepcion]])) -> agosto 2026 | U29: =IF(SCTR_Brokers[[#This Row],[Estado]]="FINALIZADO",1,0) -> 1 | V29: =IF(SCTR_Brokers[[#This Row],[FechaRecepcion]]="","",IF(SCTR_Brokers[[#This Row],[Estado]]="FINALIZADO",0,1)) -> 0 | W29: =IF(AND(SCTR_Brokers[[#This Row],[Estado]]="FINALIZADO",SCTR_Brokers[[#This Row],[Plazo]]=LISTAS!$J$3),1,0) -> 1 | X29: =IF(AND(SCTR_Brokers[[#This Row],[Estado]]="FINALIZADO",SCTR_Brokers[[#This Row],[Plazo]]=LISTAS!$J$4),1,0) -> 0 | Y29: =IF(AND(SCTR_Brokers[[#This Row],[Estado]]<>"FINALIZADO",SCTR_Brokers[[#This Row],[Plazo]]=LISTAS!$J$4),1,0) -> 0 | Z29: =IF(SCTR_Brokers[[#This Row],[Fecha_Solic_Informe]]="",0,1) -> 0 | AA29: =IF(SCTR_Brokers[[#This Row],[Fecha_Informe]]="",0,1) -> 0 | AB29: =IF(AND(SCTR_Brokers[[#This Row],[Fecha_Solic_Informe]]<>"",SCTR_Brokers[[#This Row],[Fecha_Informe]]=""),1,0) -> 0 | AC29: =IF(AND(SCTR_Brokers[[#This Row],[Fecha_Solic_Informe]]<>"",SCTR_Brokers[[#This Row],[Fecha_Informe]]<>""),ROUND((SCTR_Brokers[[#This Row],[Fecha_Informe]]-SCTR_Brokers[[#This Row],[Fecha_Solic_Informe]])*24,1),"")
... A31: AAQkADdkNThjNzFkLWM0ZmMtNDJhYS04MDVlLTIwNzE4ZDI1Mzg4YgAQAD8skMqf_3FGtrrySVSnC-0= | C31: =IF(SCTR_Brokers[[#This Row],[FechaRecepcion]]="","",SCTR_Brokers[[#This Row],[ConversationId]]&"-"&TEXT(SCTR_Brokers[[#This Row],[FechaRecepcion]],"aaaammddhhmmss")) -> AAQkADdkNThjNzFkLWM0ZmMtNDJhYS04MDVlLTIwNzE4ZDI1Mzg4YgAQAD8skMqf_3FGtrrySVSnC-0=-20260817120401 | D31: RE: MAPFRE SCTR SALUD - BLACIDO GOMEZ JOEL - ECOSEM HUARAUCACA | E31: GABEL | F31: 46251.503 | G31: 46251.503 | H31: lchacon@gabel.com.pe | I31: FINALIZADO | K31: SCTR SALUD | N31: =IF(SCTR_Brokers[[#This Row],[FechaRecepcion]]="","",IF(SCTR_Brokers[[#This Row],[Estado]]="FINALIZADO","",IF(SCTR_Brokers[[#This Row],[FechaUltimaRespuesta]]="","",_xlfn.LET(_xlpm.fer,LISTAS!$L$3:$L$100,_xlpm.ep,DATE(2000,1,1),_xlpm.ini,SCTR_Brokers[[#This Row],[FechaUltimaRespuesta]],_xlpm.fin,NOW(),_xlpm.dini,INT(_xlpm.ini),_xlpm.dfin,INT(_xlpm.fin),_xlpm.hini,9.5*NETWORKDAYS.INTL(_xlpm.ep,_xlpm.dini-1,"0000111",_xlpm.fer)+6*NETWORKDAYS.INTL(_xlpm.ep,_xlpm.dini-1,"1111011",_xlpm.fer)+IF(OR(WEEKDAY(_xlpm.dini,2)>5,COUNTIF(_xlpm.fer,_xlpm.dini)>0),0,MAX(0,MIN(_xlpm.ini-_xlpm.dini,IF(WEEKDAY(_xlpm.dini,2)=5,14/24,17.5/24))-8/24)*24),_xlpm.hfin,9.5*NETWORKDAYS.INTL(_xlpm.ep,_xlpm.dfin-1,"0000111",_xlpm.fer)+6*NETWORKDAYS.INTL(_xlpm.ep,_xlpm.dfin-1,"1111011",_xlpm.fer)+IF(OR(WEEKDAY(_xlpm.dfin,2)>5,COUNTIF(_xlpm.fer,_xlpm.dfin)>0),0,MAX(0,MIN(_xlpm.fin-_xlpm.dfin,IF(WEEKDAY(_xlpm.dfin,2)=5,14/24,17.5/24))-8/24)*24),ROUND(MAX(0,_xlpm.hfin-_xlpm.hini),1))))) | Q31: 46251.503 | R31: =IF(SCTR_Brokers[[#This Row],[FechaRecepcion]]="","",_xlfn.LET(_xlpm.fer,LISTAS!$L$3:$L$100,_xlpm.ep,DATE(2000,1,1),_xlpm.ini,SCTR_Brokers[[#This Row],[FechaRecepcion]],_xlpm.fin,IF(SCTR_Brokers[[#This Row],[Fecha_Cierre]]<>"",SCTR_Brokers[[#This Row],[Fecha_Cierre]],NOW()),_xlpm.dini,INT(_xlpm.ini),_xlpm.dfin,INT(_xlpm.fin),_xlpm.hini,9.5*NETWORKDAYS.INTL(_xlpm.ep,_xlpm.dini-1,"0000111",_xlpm.fer)+6*NETWORKDAYS.INTL(_xlpm.ep,_xlpm.dini-1,"1111011",_xlpm.fer)+IF(OR(WEEKDAY(_xlpm.dini,2)>5,COUNTIF(_xlpm.fer,_xlpm.dini)>0),0,MAX(0,MIN(_xlpm.ini-_xlpm.dini,IF(WEEKDAY(_xlpm.dini,2)=5,14/24,17.5/24))-8/24)*24),_xlpm.hfin,9.5*NETWORKDAYS.INTL(_xlpm.ep,_xlpm.dfin-1,"0000111",_xlpm.fer)+6*NETWORKDAYS.INTL(_xlpm.ep,_xlpm.dfin-1,"1111011",_xlpm.fer)+IF(OR(WEEKDAY(_xlpm.dfin,2)>5,COUNTIF(_xlpm.fer,_xlpm.dfin)>0),0,MAX(0,MIN(_xlpm.fin-_xlpm.dfin,IF(WEEKDAY(_xlpm.dfin,2)=5,14/24,17.5/24))-8/24)*24),_xlpm.hrs,IF(SCTR_Brokers[[#This Row],[Estado]]="FINALIZADO",MAX(0,_xlpm.hfin-_xlpm.hini),IF(SCTR_Brokers[[#This Row],[Horas_Transcurridas]]="",MAX(0,_xlpm.hfin-_xlpm.hini),SCTR_Brokers[[#This Row],[Horas_Transcurridas]])),IF(_xlpm.hrs<=LISTAS!$E$3,LISTAS!$J$3,LISTAS!$J$4))) -> Dentro | T31: =IF(SCTR_Brokers[[#This Row],[FechaRecepcion]]="","",TEXT(SCTR_Brokers[[#This Row],[FechaRecepcion]],"mmmm")&" "&YEAR(SCTR_Brokers[[#This Row],[FechaRecepcion]])) -> agosto 2026 | U31: =IF(SCTR_Brokers[[#This Row],[Estado]]="FINALIZADO",1,0) -> 1 | V31: =IF(SCTR_Brokers[[#This Row],[FechaRecepcion]]="","",IF(SCTR_Brokers[[#This Row],[Estado]]="FINALIZADO",0,1)) -> 0 | W31: =IF(AND(SCTR_Brokers[[#This Row],[Estado]]="FINALIZADO",SCTR_Brokers[[#This Row],[Plazo]]=LISTAS!$J$3),1,0) -> 1 | X31: =IF(AND(SCTR_Brokers[[#This Row],[Estado]]="FINALIZADO",SCTR_Brokers[[#This Row],[Plazo]]=LISTAS!$J$4),1,0) -> 0 | Y31: =IF(AND(SCTR_Brokers[[#This Row],[Estado]]<>"FINALIZADO",SCTR_Brokers[[#This Row],[Plazo]]=LISTAS!$J$4),1,0) -> 0 | Z31: =IF(SCTR_Brokers[[#This Row],[Fecha_Solic_Informe]]="",0,1) -> 0 | AA31: =IF(SCTR_Brokers[[#This Row],[Fecha_Informe]]="",0,1) -> 0 | AB31: =IF(AND(SCTR_Brokers[[#This Row],[Fecha_Solic_Informe]]<>"",SCTR_Brokers[[#This Row],[Fecha_Informe]]=""),1,0) -> 0 | AC31: =IF(AND(SCTR_Brokers[[#This Row],[Fecha_Solic_Informe]]<>"",SCTR_Brokers[[#This Row],[Fecha_Informe]]<>""),ROUND((SCTR_Brokers[[#This Row],[Fecha_Informe]]-SCTR_Brokers[[#This Row],[Fecha_Solic_Informe]])*24,1),"")
A32: AAQkADdkNThjNzFkLWM0ZmMtNDJhYS04MDVlLTIwNzE4ZDI1Mzg4YgAQAOUkxh_7kiNJmiDB2S_Ve3w= | C32: =IF(SCTR_Brokers[[#This Row],[FechaRecepcion]]="","",SCTR_Brokers[[#This Row],[ConversationId]]&"-"&TEXT(SCTR_Brokers[[#This Row],[FechaRecepcion]],"aaaammddhhmmss")) -> AAQkADdkNThjNzFkLWM0ZmMtNDJhYS04MDVlLTIwNzE4ZDI1Mzg4YgAQAOUkxh_7kiNJmiDB2S_Ve3w=-20260817143553 | D32: RE: EVALUACION DE SINIESTRO ASEG. CHICLLA MENDOZA CHRISTIAN - SKECHERS | E32: GABEL | F32: 46251.608 | G32: 46252.435 | H32: sctrsalud@mapfre.com.pe | I32: FINALIZADO | K32: AUDITORIA MÉDICA | L32: Buenos días, Dra._x000D_ _x000D_ Su apoyo con la evaluación del siniestro, adjunto la documentación pendiente enviada por cliente._x000D_ _x000D_ Muchas gracias_x000D_ _x000D_ _x000D_ Saludos,_x000D_ _x000D_ _x000D_ _x000D_ Alicia Sancca Medina_x000D_ _x000D_ Área de SCTR Salud_x000D_ _x000D_ Siniestros y Prestaciones_x000D_ _x000D_ Mapfre Perú_x000D_ _x000D_ Av. Arm | M32: DRA ANA | N32: =IF(SCTR_Brokers[[#This Row],[FechaRecepcion]]="","",IF(SCTR_Brokers[[#This Row],[Estado]]="FINALIZADO","",IF(SCTR_Brokers[[#This Row],[FechaUltimaRespuesta]]="","",_xlfn.LET(_xlpm.fer,LISTAS!$L$3:$L$100,_xlpm.ep,DATE(2000,1,1),_xlpm.ini,SCTR_Brokers[[#This Row],[FechaUltimaRespuesta]],_xlpm.fin,NOW(),_xlpm.dini,INT(_xlpm.ini),_xlpm.dfin,INT(_xlpm.fin),_xlpm.hini,9.5*NETWORKDAYS.INTL(_xlpm.ep,_xlpm.dini-1,"0000111",_xlpm.fer)+6*NETWORKDAYS.INTL(_xlpm.ep,_xlpm.dini-1,"1111011",_xlpm.fer)+IF(OR(WEEKDAY(_xlpm.dini,2)>5,COUNTIF(_xlpm.fer,_xlpm.dini)>0),0,MAX(0,MIN(_xlpm.ini-_xlpm.dini,IF(WEEKDAY(_xlpm.dini,2)=5,14/24,17.5/24))-8/24)*24),_xlpm.hfin,9.5*NETWORKDAYS.INTL(_xlpm.ep,_xlpm.dfin-1,"0000111",_xlpm.fer)+6*NETWORKDAYS.INTL(_xlpm.ep,_xlpm.dfin-1,"1111011",_xlpm.fer)+IF(OR(WEEKDAY(_xlpm.dfin,2)>5,COUNTIF(_xlpm.fer,_xlpm.dfin)>0),0,MAX(0,MIN(_xlpm.fin-_xlpm.dfin,IF(WEEKDAY(_xlpm.dfin,2)=5,14/24,17.5/24))-8/24)*24),ROUND(MAX(0,_xlpm.hfin-_xlpm.hini),1))))) | O32: 46252.382 | Q32: 46252.435 | R32: =IF(SCTR_Brokers[[#This Row],[FechaRecepcion]]="","",_xlfn.LET(_xlpm.fer,LISTAS!$L$3:$L$100,_xlpm.ep,DATE(2000,1,1),_xlpm.ini,SCTR_Brokers[[#This Row],[FechaRecepcion]],_xlpm.fin,IF(SCTR_Brokers[[#This Row],[Fecha_Cierre]]<>"",SCTR_Brokers[[#This Row],[Fecha_Cierre]],NOW()),_xlpm.dini,INT(_xlpm.ini),_xlpm.dfin,INT(_xlpm.fin),_xlpm.hini,9.5*NETWORKDAYS.INTL(_xlpm.ep,_xlpm.dini-1,"0000111",_xlpm.fer)+6*NETWORKDAYS.INTL(_xlpm.ep,_xlpm.dini-1,"1111011",_xlpm.fer)+IF(OR(WEEKDAY(_xlpm.dini,2)>5,COUNTIF(_xlpm.fer,_xlpm.dini)>0),0,MAX(0,MIN(_xlpm.ini-_xlpm.dini,IF(WEEKDAY(_xlpm.dini,2)=5,14/24,17.5/24))-8/24)*24),_xlpm.hfin,9.5*NETWORKDAYS.INTL(_xlpm.ep,_xlpm.dfin-1,"0000111",_xlpm.fer)+6*NETWORKDAYS.INTL(_xlpm.ep,_xlpm.dfin-1,"1111011",_xlpm.fer)+IF(OR(WEEKDAY(_xlpm.dfin,2)>5,COUNTIF(_xlpm.fer,_xlpm.dfin)>0),0,MAX(0,MIN(_xlpm.fin-_xlpm.dfin,IF(WEEKDAY(_xlpm.dfin,2)=5,14/24,17.5/24))-8/24)*24),_xlpm.hrs,IF(SCTR_Brokers[[#This Row],[Estado]]="FINALIZADO",MAX(0,_xlpm.hfin-_xlpm.hini),IF(SCTR_Brokers[[#This Row],[Horas_Transcurridas]]="",MAX(0,_xlpm.hfin-_xlpm.hini),SCTR_Brokers[[#This Row],[Horas_Transcurridas]])),IF(_xlpm.hrs<=LISTAS!$E$3,LISTAS!$J$3,LISTAS!$J$4))) -> Dentro | T32: =IF(SCTR_Brokers[[#This Row],[FechaRecepcion]]="","",TEXT(SCTR_Brokers[[#This Row],[FechaRecepcion]],"mmmm")&" "&YEAR(SCTR_Brokers[[#This Row],[FechaRecepcion]])) -> agosto 2026 | U32: =IF(SCTR_Brokers[[#This Row],[Estado]]="FINALIZADO",1,0) -> 1 | V32: =IF(SCTR_Brokers[[#This Row],[FechaRecepcion]]="","",IF(SCTR_Brokers[[#This Row],[Estado]]="FINALIZADO",0,1)) -> 0 | W32: =IF(AND(SCTR_Brokers[[#This Row],[Estado]]="FINALIZADO",SCTR_Brokers[[#This Row],[Plazo]]=LISTAS!$J$3),1,0) -> 1 | X32: =IF(AND(SCTR_Brokers[[#This Row],[Estado]]="FINALIZADO",SCTR_Brokers[[#This Row],[Plazo]]=LISTAS!$J$4),1,0) -> 0 | Y32: =IF(AND(SCTR_Brokers[[#This Row],[Estado]]<>"FINALIZADO",SCTR_Brokers[[#This Row],[Plazo]]=LISTAS!$J$4),1,0) -> 0 | Z32: =IF(SCTR_Brokers[[#This Row],[Fecha_Solic_Informe]]="",0,1) -> 1 | AA32: =IF(SCTR_Brokers[[#This Row],[Fecha_Informe]]="",0,1) -> 0 | AB32: =IF(AND(SCTR_Brokers[[#This Row],[Fecha_Solic_Informe]]<>"",SCTR_Brokers[[#This Row],[Fecha_Informe]]=""),1,0) -> 1 | AC32: =IF(AND(SCTR_Brokers[[#This Row],[Fecha_Solic_Informe]]<>"",SCTR_Brokers[[#This Row],[Fecha_Informe]]<>""),ROUND((SCTR_Brokers[[#This Row],[Fecha_Informe]]-SCTR_Brokers[[#This Row],[Fecha_Solic_Informe]])*24,1),"")
A33: AAQkADdkNThjNzFkLWM0ZmMtNDJhYS04MDVlLTIwNzE4ZDI1Mzg4YgAQAJce04pfmOxCjc66JQ_YqAI= | C33: =IF(SCTR_Brokers[[#This Row],[FechaRecepcion]]="","",SCTR_Brokers[[#This Row],[ConversationId]]&"-"&TEXT(SCTR_Brokers[[#This Row],[FechaRecepcion]],"aaaammddhhmmss")) -> AAQkADdkNThjNzFkLWM0ZmMtNDJhYS04MDVlLTIwNzE4ZDI1Mzg4YgAQAJce04pfmOxCjc66JQ_YqAI=-20260817154843 | D33: RE: TAMSHI: ACCIDENTE LABORAL_REATEGUI CURICHIMBA MARCOS (mordedura de serpiente) | E33: MARSH | F33: 46251.659 | G33: 46251.659 | H33: Katherine.Andrade@marsh.com | I33: FINALIZADO | K33: SCTR SALUD | N33: =IF(SCTR_Brokers[[#This Row],[FechaRecepcion]]="","",IF(SCTR_Brokers[[#This Row],[Estado]]="FINALIZADO","",IF(SCTR_Brokers[[#This Row],[FechaUltimaRespuesta]]="","",_xlfn.LET(_xlpm.fer,LISTAS!$L$3:$L$100,_xlpm.ep,DATE(2000,1,1),_xlpm.ini,SCTR_Brokers[[#This Row],[FechaUltimaRespuesta]],_xlpm.fin,NOW(),_xlpm.dini,INT(_xlpm.ini),_xlpm.dfin,INT(_xlpm.fin),_xlpm.hini,9.5*NETWORKDAYS.INTL(_xlpm.ep,_xlpm.dini-1,"0000111",_xlpm.fer)+6*NETWORKDAYS.INTL(_xlpm.ep,_xlpm.dini-1,"1111011",_xlpm.fer)+IF(OR(WEEKDAY(_xlpm.dini,2)>5,COUNTIF(_xlpm.fer,_xlpm.dini)>0),0,MAX(0,MIN(_xlpm.ini-_xlpm.dini,IF(WEEKDAY(_xlpm.dini,2)=5,14/24,17.5/24))-8/24)*24),_xlpm.hfin,9.5*NETWORKDAYS.INTL(_xlpm.ep,_xlpm.dfin-1,"0000111",_xlpm.fer)+6*NETWORKDAYS.INTL(_xlpm.ep,_xlpm.dfin-1,"1111011",_xlpm.fer)+IF(OR(WEEKDAY(_xlpm.dfin,2)>5,COUNTIF(_xlpm.fer,_xlpm.dfin)>0),0,MAX(0,MIN(_xlpm.fin-_xlpm.dfin,IF(WEEKDAY(_xlpm.dfin,2)=5,14/24,17.5/24))-8/24)*24),ROUND(MAX(0,_xlpm.hfin-_xlpm.hini),1))))) | Q33: 46251.666 | R33: =IF(SCTR_Brokers[[#This Row],[FechaRecepcion]]="","",_xlfn.LET(_xlpm.fer,LISTAS!$L$3:$L$100,_xlpm.ep,DATE(2000,1,1),_xlpm.ini,SCTR_Brokers[[#This Row],[FechaRecepcion]],_xlpm.fin,IF(SCTR_Brokers[[#This Row],[Fecha_Cierre]]<>"",SCTR_Brokers[[#This Row],[Fecha_Cierre]],NOW()),_xlpm.dini,INT(_xlpm.ini),_xlpm.dfin,INT(_xlpm.fin),_xlpm.hini,9.5*NETWORKDAYS.INTL(_xlpm.ep,_xlpm.dini-1,"0000111",_xlpm.fer)+6*NETWORKDAYS.INTL(_xlpm.ep,_xlpm.dini-1,"1111011",_xlpm.fer)+IF(OR(WEEKDAY(_xlpm.dini,2)>5,COUNTIF(_xlpm.fer,_xlpm.dini)>0),0,MAX(0,MIN(_xlpm.ini-_xlpm.dini,IF(WEEKDAY(_xlpm.dini,2)=5,14/24,17.5/24))-8/24)*24),_xlpm.hfin,9.5*NETWORKDAYS.INTL(_xlpm.ep,_xlpm.dfin-1,"0000111",_xlpm.fer)+6*NETWORKDAYS.INTL(_xlpm.ep,_xlpm.dfin-1,"1111011",_xlpm.fer)+IF(OR(WEEKDAY(_xlpm.dfin,2)>5,COUNTIF(_xlpm.fer,_xlpm.dfin)>0),0,MAX(0,MIN(_xlpm.fin-_xlpm.dfin,IF(WEEKDAY(_xlpm.dfin,2)=5,14/24,17.5/24))-8/24)*24),_xlpm.hrs,IF(SCTR_Brokers[[#This Row],[Estado]]="FINALIZADO",MAX(0,_xlpm.hfin-_xlpm.hini),IF(SCTR_Brokers[[#This Row],[Horas_Transcurridas]]="",MAX(0,_xlpm.hfin-_xlpm.hini),SCTR_Brokers[[#This Row],[Horas_Transcurridas]])),IF(_xlpm.hrs<=LISTAS!$E$3,LISTAS!$J$3,LISTAS!$J$4))) -> Dentro | T33: =IF(SCTR_Brokers[[#This Row],[FechaRecepcion]]="","",TEXT(SCTR_Brokers[[#This Row],[FechaRecepcion]],"mmmm")&" "&YEAR(SCTR_Brokers[[#This Row],[FechaRecepcion]])) -> agosto 2026 | U33: =IF(SCTR_Brokers[[#This Row],[Estado]]="FINALIZADO",1,0) -> 1 | V33: =IF(SCTR_Brokers[[#This Row],[FechaRecepcion]]="","",IF(SCTR_Brokers[[#This Row],[Estado]]="FINALIZADO",0,1)) -> 0 | W33: =IF(AND(SCTR_Brokers[[#This Row],[Estado]]="FINALIZADO",SCTR_Brokers[[#This Row],[Plazo]]=LISTAS!$J$3),1,0) -> 1 | X33: =IF(AND(SCTR_Brokers[[#This Row],[Estado]]="FINALIZADO",SCTR_Brokers[[#This Row],[Plazo]]=LISTAS!$J$4),1,0) -> 0 | Y33: =IF(AND(SCTR_Brokers[[#This Row],[Estado]]<>"FINALIZADO",SCTR_Brokers[[#This Row],[Plazo]]=LISTAS!$J$4),1,0) -> 0 | Z33: =IF(SCTR_Brokers[[#This Row],[Fecha_Solic_Informe]]="",0,1) -> 0 | AA33: =IF(SCTR_Brokers[[#This Row],[Fecha_Informe]]="",0,1) -> 0 | AB33: =IF(AND(SCTR_Brokers[[#This Row],[Fecha_Solic_Informe]]<>"",SCTR_Brokers[[#This Row],[Fecha_Informe]]=""),1,0) -> 0 | AC33: =IF(AND(SCTR_Brokers[[#This Row],[Fecha_Solic_Informe]]<>"",SCTR_Brokers[[#This Row],[Fecha_Informe]]<>""),ROUND((SCTR_Brokers[[#This Row],[Fecha_Informe]]-SCTR_Brokers[[#This Row],[Fecha_Solic_Informe]])*24,1),"")
A34: AAQkADdkNThjNzFkLWM0ZmMtNDJhYS04MDVlLTIwNzE4ZDI1Mzg4YgAQANgmCUHEJVVIljOU-AWYE_M= | C34: =IF(SCTR_Brokers[[#This Row],[FechaRecepcion]]="","",SCTR_Brokers[[#This Row],[ConversationId]]&"-"&TEXT(SCTR_Brokers[[#This Row],[FechaRecepcion]],"aaaammddhhmmss")) -> AAQkADdkNThjNzFkLWM0ZmMtNDJhYS04MDVlLTIwNzE4ZDI1Mzg4YgAQANgmCUHEJVVIljOU-AWYE_M=-20260817171923 | D34: GRUPO EULEN - ACTIVACION SCTR SALUD - ANGELICA LORENZO SENTENO DNI: 10702647 | E34: UIB | F34: 46251.722 | G34: 46252.414 | H34: sctrsalud@mapfre.com.pe | I34: FINALIZADO | K34: SCTR SALUD | N34: =IF(SCTR_Brokers[[#This Row],[FechaRecepcion]]="","",IF(SCTR_Brokers[[#This Row],[Estado]]="FINALIZADO","",IF(SCTR_Brokers[[#This Row],[FechaUltimaRespuesta]]="","",_xlfn.LET(_xlpm.fer,LISTAS!$L$3:$L$100,_xlpm.ep,DATE(2000,1,1),_xlpm.ini,SCTR_Brokers[[#This Row],[FechaUltimaRespuesta]],_xlpm.fin,NOW(),_xlpm.dini,INT(_xlpm.ini),_xlpm.dfin,INT(_xlpm.fin),_xlpm.hini,9.5*NETWORKDAYS.INTL(_xlpm.ep,_xlpm.dini-1,"0000111",_xlpm.fer)+6*NETWORKDAYS.INTL(_xlpm.ep,_xlpm.dini-1,"1111011",_xlpm.fer)+IF(OR(WEEKDAY(_xlpm.dini,2)>5,COUNTIF(_xlpm.fer,_xlpm.dini)>0),0,MAX(0,MIN(_xlpm.ini-_xlpm.dini,IF(WEEKDAY(_xlpm.dini,2)=5,14/24,17.5/24))-8/24)*24),_xlpm.hfin,9.5*NETWORKDAYS.INTL(_xlpm.ep,_xlpm.dfin-1,"0000111",_xlpm.fer)+6*NETWORKDAYS.INTL(_xlpm.ep,_xlpm.dfin-1,"1111011",_xlpm.fer)+IF(OR(WEEKDAY(_xlpm.dfin,2)>5,COUNTIF(_xlpm.fer,_xlpm.dfin)>0),0,MAX(0,MIN(_xlpm.fin-_xlpm.dfin,IF(WEEKDAY(_xlpm.dfin,2)=5,14/24,17.5/24))-8/24)*24),ROUND(MAX(0,_xlpm.hfin-_xlpm.hini),1))))) | Q34: 46252.414 | R34: =IF(SCTR_Brokers[[#This Row],[FechaRecepcion]]="","",_xlfn.LET(_xlpm.fer,LISTAS!$L$3:$L$100,_xlpm.ep,DATE(2000,1,1),_xlpm.ini,SCTR_Brokers[[#This Row],[FechaRecepcion]],_xlpm.fin,IF(SCTR_Brokers[[#This Row],[Fecha_Cierre]]<>"",SCTR_Brokers[[#This Row],[Fecha_Cierre]],NOW()),_xlpm.dini,INT(_xlpm.ini),_xlpm.dfin,INT(_xlpm.fin),_xlpm.hini,9.5*NETWORKDAYS.INTL(_xlpm.ep,_xlpm.dini-1,"0000111",_xlpm.fer)+6*NETWORKDAYS.INTL(_xlpm.ep,_xlpm.dini-1,"1111011",_xlpm.fer)+IF(OR(WEEKDAY(_xlpm.dini,2)>5,COUNTIF(_xlpm.fer,_xlpm.dini)>0),0,MAX(0,MIN(_xlpm.ini-_xlpm.dini,IF(WEEKDAY(_xlpm.dini,2)=5,14/24,17.5/24))-8/24)*24),_xlpm.hfin,9.5*NETWORKDAYS.INTL(_xlpm.ep,_xlpm.dfin-1,"0000111",_xlpm.fer)+6*NETWORKDAYS.INTL(_xlpm.ep,_xlpm.dfin-1,"1111011",_xlpm.fer)+IF(OR(WEEKDAY(_xlpm.dfin,2)>5,COUNTIF(_xlpm.fer,_xlpm.dfin)>0),0,MAX(0,MIN(_xlpm.fin-_xlpm.dfin,IF(WEEKDAY(_xlpm.dfin,2)=5,14/24,17.5/24))-8/24)*24),_xlpm.hrs,IF(SCTR_Brokers[[#This Row],[Estado]]="FINALIZADO",MAX(0,_xlpm.hfin-_xlpm.hini),IF(SCTR_Brokers[[#This Row],[Horas_Transcurridas]]="",MAX(0,_xlpm.hfin-_xlpm.hini),SCTR_Brokers[[#This Row],[Horas_Transcurridas]])),IF(_xlpm.hrs<=LISTAS!$E$3,LISTAS!$J$3,LISTAS!$J$4))) -> Dentro | T34: =IF(SCTR_Brokers[[#This Row],[FechaRecepcion]]="","",TEXT(SCTR_Brokers[[#This Row],[FechaRecepcion]],"mmmm")&" "&YEAR(SCTR_Brokers[[#This Row],[FechaRecepcion]])) -> agosto 2026 | U34: =IF(SCTR_Brokers[[#This Row],[Estado]]="FINALIZADO",1,0) -> 1 | V34: =IF(SCTR_Brokers[[#This Row],[FechaRecepcion]]="","",IF(SCTR_Brokers[[#This Row],[Estado]]="FINALIZADO",0,1)) -> 0 | W34: =IF(AND(SCTR_Brokers[[#This Row],[Estado]]="FINALIZADO",SCTR_Brokers[[#This Row],[Plazo]]=LISTAS!$J$3),1,0) -> 1 | X34: =IF(AND(SCTR_Brokers[[#This Row],[Estado]]="FINALIZADO",SCTR_Brokers[[#This Row],[Plazo]]=LISTAS!$J$4),1,0) -> 0 | Y34: =IF(AND(SCTR_Brokers[[#This Row],[Estado]]<>"FINALIZADO",SCTR_Brokers[[#This Row],[Plazo]]=LISTAS!$J$4),1,0) -> 0 | Z34: =IF(SCTR_Brokers[[#This Row],[Fecha_Solic_Informe]]="",0,1) -> 0 | AA34: =IF(SCTR_Brokers[[#This Row],[Fecha_Informe]]="",0,1) -> 0 | AB34: =IF(AND(SCTR_Brokers[[#This Row],[Fecha_Solic_Informe]]<>"",SCTR_Brokers[[#This Row],[Fecha_Informe]]=""),1,0) -> 0 | AC34: =IF(AND(SCTR_Brokers[[#This Row],[Fecha_Solic_Informe]]<>"",SCTR_Brokers[[#This Row],[Fecha_Informe]]<>""),ROUND((SCTR_Brokers[[#This Row],[Fecha_Informe]]-SCTR_Brokers[[#This Row],[Fecha_Solic_Informe]])*24,1),"")
A35: AAQkADdkNThjNzFkLWM0ZmMtNDJhYS04MDVlLTIwNzE4ZDI1Mzg4YgAQAM9tjetLPAtPgKsVDxqNIko= | C35: =IF(SCTR_Brokers[[#This Row],[FechaRecepcion]]="","",SCTR_Brokers[[#This Row],[ConversationId]]&"-"&TEXT(SCTR_Brokers[[#This Row],[FechaRecepcion]],"aaaammddhhmmss")) -> AAQkADdkNThjNzFkLWM0ZmMtNDJhYS04MDVlLTIwNzE4ZDI1Mzg4YgAQAM9tjetLPAtPgKsVDxqNIko=-20260817180520 | D35: RE: CASO - MOLINA ELME SINTHIA MARISOL | E35: UIB | F35: 46251.754 | G35: 46252.537 | H35: cmendez@uiblatam.com | I35: FINALIZADO | K35: SCTR SALUD | N35: =IF(SCTR_Brokers[[#This Row],[FechaRecepcion]]="","",IF(SCTR_Brokers[[#This Row],[Estado]]="FINALIZADO","",IF(SCTR_Brokers[[#This Row],[FechaUltimaRespuesta]]="","",_xlfn.LET(_xlpm.fer,LISTAS!$L$3:$L$100,_xlpm.ep,DATE(2000,1,1),_xlpm.ini,SCTR_Brokers[[#This Row],[FechaUltimaRespuesta]],_xlpm.fin,NOW(),_xlpm.dini,INT(_xlpm.ini),_xlpm.dfin,INT(_xlpm.fin),_xlpm.hini,9.5*NETWORKDAYS.INTL(_xlpm.ep,_xlpm.dini-1,"0000111",_xlpm.fer)+6*NETWORKDAYS.INTL(_xlpm.ep,_xlpm.dini-1,"1111011",_xlpm.fer)+IF(OR(WEEKDAY(_xlpm.dini,2)>5,COUNTIF(_xlpm.fer,_xlpm.dini)>0),0,MAX(0,MIN(_xlpm.ini-_xlpm.dini,IF(WEEKDAY(_xlpm.dini,2)=5,14/24,17.5/24))-8/24)*24),_xlpm.hfin,9.5*NETWORKDAYS.INTL(_xlpm.ep,_xlpm.dfin-1,"0000111",_xlpm.fer)+6*NETWORKDAYS.INTL(_xlpm.ep,_xlpm.dfin-1,"1111011",_xlpm.fer)+IF(OR(WEEKDAY(_xlpm.dfin,2)>5,COUNTIF(_xlpm.fer,_xlpm.dfin)>0),0,MAX(0,MIN(_xlpm.fin-_xlpm.dfin,IF(WEEKDAY(_xlpm.dfin,2)=5,14/24,17.5/24))-8/24)*24),ROUND(MAX(0,_xlpm.hfin-_xlpm.hini),1))))) | Q35: 46252.537 | R35: =IF(SCTR_Brokers[[#This Row],[FechaRecepcion]]="","",_xlfn.LET(_xlpm.fer,LISTAS!$L$3:$L$100,_xlpm.ep,DATE(2000,1,1),_xlpm.ini,SCTR_Brokers[[#This Row],[FechaRecepcion]],_xlpm.fin,IF(SCTR_Brokers[[#This Row],[Fecha_Cierre]]<>"",SCTR_Brokers[[#This Row],[Fecha_Cierre]],NOW()),_xlpm.dini,INT(_xlpm.ini),_xlpm.dfin,INT(_xlpm.fin),_xlpm.hini,9.5*NETWORKDAYS.INTL(_xlpm.ep,_xlpm.dini-1,"0000111",_xlpm.fer)+6*NETWORKDAYS.INTL(_xlpm.ep,_xlpm.dini-1,"1111011",_xlpm.fer)+IF(OR(WEEKDAY(_xlpm.dini,2)>5,COUNTIF(_xlpm.fer,_xlpm.dini)>0),0,MAX(0,MIN(_xlpm.ini-_xlpm.dini,IF(WEEKDAY(_xlpm.dini,2)=5,14/24,17.5/24))-8/24)*24),_xlpm.hfin,9.5*NETWORKDAYS.INTL(_xlpm.ep,_xlpm.dfin-1,"0000111",_xlpm.fer)+6*NETWORKDAYS.INTL(_xlpm.ep,_xlpm.dfin-1,"1111011",_xlpm.fer)+IF(OR(WEEKDAY(_xlpm.dfin,2)>5,COUNTIF(_xlpm.fer,_xlpm.dfin)>0),0,MAX(0,MIN(_xlpm.fin-_xlpm.dfin,IF(WEEKDAY(_xlpm.dfin,2)=5,14/24,17.5/24))-8/24)*24),_xlpm.hrs,IF(SCTR_Brokers[[#This Row],[Estado]]="FINALIZADO",MAX(0,_xlpm.hfin-_xlpm.hini),IF(SCTR_Brokers[[#This Row],[Horas_Transcurridas]]="",MAX(0,_xlpm.hfin-_xlpm.hini),SCTR_Brokers[[#This Row],[Horas_Transcurridas]])),IF(_xlpm.hrs<=LISTAS!$E$3,LISTAS!$J$3,LISTAS!$J$4))) -> Dentro | T35: =IF(SCTR_Brokers[[#This Row],[FechaRecepcion]]="","",TEXT(SCTR_Brokers[[#This Row],[FechaRecepcion]],"mmmm")&" "&YEAR(SCTR_Brokers[[#This Row],[FechaRecepcion]])) -> agosto 2026 | U35: =IF(SCTR_Brokers[[#This Row],[Estado]]="FINALIZADO",1,0) -> 1 | V35: =IF(SCTR_Brokers[[#This Row],[FechaRecepcion]]="","",IF(SCTR_Brokers[[#This Row],[Estado]]="FINALIZADO",0,1)) -> 0 | W35: =IF(AND(SCTR_Brokers[[#This Row],[Estado]]="FINALIZADO",SCTR_Brokers[[#This Row],[Plazo]]=LISTAS!$J$3),1,0) -> 1 | X35: =IF(AND(SCTR_Brokers[[#This Row],[Estado]]="FINALIZADO",SCTR_Brokers[[#This Row],[Plazo]]=LISTAS!$J$4),1,0) -> 0 | Y35: =IF(AND(SCTR_Brokers[[#This Row],[Estado]]<>"FINALIZADO",SCTR_Brokers[[#This Row],[Plazo]]=LISTAS!$J$4),1,0) -> 0 | Z35: =IF(SCTR_Brokers[[#This Row],[Fecha_Solic_Informe]]="",0,1) -> 0 | AA35: =IF(SCTR_Brokers[[#This Row],[Fecha_Informe]]="",0,1) -> 0 | AB35: =IF(AND(SCTR_Brokers[[#This Row],[Fecha_Solic_Informe]]<>"",SCTR_Brokers[[#This Row],[Fecha_Informe]]=""),1,0) -> 0 | AC35: =IF(AND(SCTR_Brokers[[#This Row],[Fecha_Solic_Informe]]<>"",SCTR_Brokers[[#This Row],[Fecha_Informe]]<>""),ROUND((SCTR_Brokers[[#This Row],[Fecha_Informe]]-SCTR_Brokers[[#This Row],[Fecha_Solic_Informe]])*24,1),"")
A36: AAQkADdkNThjNzFkLWM0ZmMtNDJhYS04MDVlLTIwNzE4ZDI1Mzg4YgAQAHUL3lsl5ORPuwIMqDM_rpA= | C36: =IF(SCTR_Brokers[[#This Row],[FechaRecepcion]]="","",SCTR_Brokers[[#This Row],[ConversationId]]&"-"&TEXT(SCTR_Brokers[[#This Row],[FechaRecepcion]],"aaaammddhhmmss")) -> AAQkADdkNThjNzFkLWM0ZmMtNDJhYS04MDVlLTIwNzE4ZDI1Mzg4YgAQAHUL3lsl5ORPuwIMqDM_rpA=-20260818091518 | D36: GoodYear - SCTR Salud - Accidente con Quemadura - C. San Gabriel | E36: MARSH | F36: 46252.386 | G36: 46260.735 | H36: sctrsalud@mapfre.com.pe | I36: FINALIZADO | K36: SCTR SALUD | N36: =IF(SCTR_Brokers[[#This Row],[FechaRecepcion]]="","",IF(SCTR_Brokers[[#This Row],[Estado]]="FINALIZADO","",IF(SCTR_Brokers[[#This Row],[FechaUltimaRespuesta]]="","",_xlfn.LET(_xlpm.fer,LISTAS!$L$3:$L$100,_xlpm.ep,DATE(2000,1,1),_xlpm.ini,SCTR_Brokers[[#This Row],[FechaUltimaRespuesta]],_xlpm.fin,NOW(),_xlpm.dini,INT(_xlpm.ini),_xlpm.dfin,INT(_xlpm.fin),_xlpm.hini,9.5*NETWORKDAYS.INTL(_xlpm.ep,_xlpm.dini-1,"0000111",_xlpm.fer)+6*NETWORKDAYS.INTL(_xlpm.ep,_xlpm.dini-1,"1111011",_xlpm.fer)+IF(OR(WEEKDAY(_xlpm.dini,2)>5,COUNTIF(_xlpm.fer,_xlpm.dini)>0),0,MAX(0,MIN(_xlpm.ini-_xlpm.dini,IF(WEEKDAY(_xlpm.dini,2)=5,14/24,17.5/24))-8/24)*24),_xlpm.hfin,9.5*NETWORKDAYS.INTL(_xlpm.ep,_xlpm.dfin-1,"0000111",_xlpm.fer)+6*NETWORKDAYS.INTL(_xlpm.ep,_xlpm.dfin-1,"1111011",_xlpm.fer)+IF(OR(WEEKDAY(_xlpm.dfin,2)>5,COUNTIF(_xlpm.fer,_xlpm.dfin)>0),0,MAX(0,MIN(_xlpm.fin-_xlpm.dfin,IF(WEEKDAY(_xlpm.dfin,2)=5,14/24,17.5/24))-8/24)*24),ROUND(MAX(0,_xlpm.hfin-_xlpm.hini),1))))) | Q36: 46260.735 | R36: =IF(SCTR_Brokers[[#This Row],[FechaRecepcion]]="","",_xlfn.LET(_xlpm.fer,LISTAS!$L$3:$L$100,_xlpm.ep,DATE(2000,1,1),_xlpm.ini,SCTR_Brokers[[#This Row],[FechaRecepcion]],_xlpm.fin,IF(SCTR_Brokers[[#This Row],[Fecha_Cierre]]<>"",SCTR_Brokers[[#This Row],[Fecha_Cierre]],NOW()),_xlpm.dini,INT(_xlpm.ini),_xlpm.dfin,INT(_xlpm.fin),_xlpm.hini,9.5*NETWORKDAYS.INTL(_xlpm.ep,_xlpm.dini-1,"0000111",_xlpm.fer)+6*NETWORKDAYS.INTL(_xlpm.ep,_xlpm.dini-1,"1111011",_xlpm.fer)+IF(OR(WEEKDAY(_xlpm.dini,2)>5,COUNTIF(_xlpm.fer,_xlpm.dini)>0),0,MAX(0,MIN(_xlpm.ini-_xlpm.dini,IF(WEEKDAY(_xlpm.dini,2)=5,14/24,17.5/24))-8/24)*24),_xlpm.hfin,9.5*NETWORKDAYS.INTL(_xlpm.ep,_xlpm.dfin-1,"0000111",_xlpm.fer)+6*NETWORKDAYS.INTL(_xlpm.ep,_xlpm.dfin-1,"1111011",_xlpm.fer)+IF(OR(WEEKDAY(_xlpm.dfin,2)>5,COUNTIF(_xlpm.fer,_xlpm.dfin)>0),0,MAX(0,MIN(_xlpm.fin-_xlpm.dfin,IF(WEEKDAY(_xlpm.dfin,2)=5,14/24,17.5/24))-8/24)*24),_xlpm.hrs,IF(SCTR_Brokers[[#This Row],[Estado]]="FINALIZADO",MAX(0,_xlpm.hfin-_xlpm.hini),IF(SCTR_Brokers[[#This Row],[Horas_Transcurridas]]="",MAX(0,_xlpm.hfin-_xlpm.hini),SCTR_Brokers[[#This Row],[Horas_Transcurridas]])),IF(_xlpm.hrs<=LISTAS!$E$3,LISTAS!$J$3,LISTAS!$J$4))) -> Fuera | T36: =IF(SCTR_Brokers[[#This Row],[FechaRecepcion]]="","",TEXT(SCTR_Brokers[[#This Row],[FechaRecepcion]],"mmmm")&" "&YEAR(SCTR_Brokers[[#This Row],[FechaRecepcion]])) -> agosto 2026 | U36: =IF(SCTR_Brokers[[#This Row],[Estado]]="FINALIZADO",1,0) -> 1 | V36: =IF(SCTR_Brokers[[#This Row],[FechaRecepcion]]="","",IF(SCTR_Brokers[[#This Row],[Estado]]="FINALIZADO",0,1)) -> 0 | W36: =IF(AND(SCTR_Brokers[[#This Row],[Estado]]="FINALIZADO",SCTR_Brokers[[#This Row],[Plazo]]=LISTAS!$J$3),1,0) -> 0 | X36: =IF(AND(SCTR_Brokers[[#This Row],[Estado]]="FINALIZADO",SCTR_Brokers[[#This Row],[Plazo]]=LISTAS!$J$4),1,0) -> 1 | Y36: =IF(AND(SCTR_Brokers[[#This Row],[Estado]]<>"FINALIZADO",SCTR_Brokers[[#This Row],[Plazo]]=LISTAS!$J$4),1,0) -> 0 | Z36: =IF(SCTR_Brokers[[#This Row],[Fecha_Solic_Informe]]="",0,1) -> 0 | AA36: =IF(SCTR_Brokers[[#This Row],[Fecha_Informe]]="",0,1) -> 0 | AB36: =IF(AND(SCTR_Brokers[[#This Row],[Fecha_Solic_Informe]]<>"",SCTR_Brokers[[#This Row],[Fecha_Informe]]=""),1,0) -> 0 | AC36: =IF(AND(SCTR_Brokers[[#This Row],[Fecha_Solic_Informe]]<>"",SCTR_Brokers[[#This Row],[Fecha_Informe]]<>""),ROUND((SCTR_Brokers[[#This Row],[Fecha_Informe]]-SCTR_Brokers[[#This Row],[Fecha_Solic_Informe]])*24,1),"")
A37: AAQkADdkNThjNzFkLWM0ZmMtNDJhYS04MDVlLTIwNzE4ZDI1Mzg4YgAQAFOGHfQqkU1jvsHHeuiXfGM= | C37: =IF(SCTR_Brokers[[#This Row],[FechaRecepcion]]="","",SCTR_Brokers[[#This Row],[ConversationId]]&"-"&TEXT(SCTR_Brokers[[#This Row],[FechaRecepcion]],"aaaammddhhmmss")) -> AAQkADdkNThjNzFkLWM0ZmMtNDJhYS04MDVlLTIwNzE4ZDI1Mzg4YgAQAFOGHfQqkU1jvsHHeuiXfGM=-20260818111534 | D37: DON POLLO LA LIBERTAD // SCTR SALUD - ACCIDENTE DE TRABAJO: ANGULO ARTIAGA LUIS MARIO | E37: MARSH | F37: 46252.469 | G37: 46252.469 | H37: Marsh.SiniestrosRRLL@marsh.com | I37: FINALIZADO | J37: | POSIBLE DERIVACIÓN 19/08/2026 09:00 | K37: SCTR SALUD | N37: =IF(SCTR_Brokers[[#This Row],[FechaRecepcion]]="","",IF(SCTR_Brokers[[#This Row],[Estado]]="FINALIZADO","",IF(SCTR_Brokers[[#This Row],[FechaUltimaRespuesta]]="","",_xlfn.LET(_xlpm.fer,LISTAS!$L$3:$L$100,_xlpm.ep,DATE(2000,1,1),_xlpm.ini,SCTR_Brokers[[#This Row],[FechaUltimaRespuesta]],_xlpm.fin,NOW(),_xlpm.dini,INT(_xlpm.ini),_xlpm.dfin,INT(_xlpm.fin),_xlpm.hini,9.5*NETWORKDAYS.INTL(_xlpm.ep,_xlpm.dini-1,"0000111",_xlpm.fer)+6*NETWORKDAYS.INTL(_xlpm.ep,_xlpm.dini-1,"1111011",_xlpm.fer)+IF(OR(WEEKDAY(_xlpm.dini,2)>5,COUNTIF(_xlpm.fer,_xlpm.dini)>0),0,MAX(0,MIN(_xlpm.ini-_xlpm.dini,IF(WEEKDAY(_xlpm.dini,2)=5,14/24,17.5/24))-8/24)*24),_xlpm.hfin,9.5*NETWORKDAYS.INTL(_xlpm.ep,_xlpm.dfin-1,"0000111",_xlpm.fer)+6*NETWORKDAYS.INTL(_xlpm.ep,_xlpm.dfin-1,"1111011",_xlpm.fer)+IF(OR(WEEKDAY(_xlpm.dfin,2)>5,COUNTIF(_xlpm.fer,_xlpm.dfin)>0),0,MAX(0,MIN(_xlpm.fin-_xlpm.dfin,IF(WEEKDAY(_xlpm.dfin,2)=5,14/24,17.5/24))-8/24)*24),ROUND(MAX(0,_xlpm.hfin-_xlpm.hini),1))))) | R37: =IF(SCTR_Brokers[[#This Row],[FechaRecepcion]]="","",_xlfn.LET(_xlpm.fer,LISTAS!$L$3:$L$100,_xlpm.ep,DATE(2000,1,1),_xlpm.ini,SCTR_Brokers[[#This Row],[FechaRecepcion]],_xlpm.fin,IF(SCTR_Brokers[[#This Row],[Fecha_Cierre]]<>"",SCTR_Brokers[[#This Row],[Fecha_Cierre]],NOW()),_xlpm.dini,INT(_xlpm.ini),_xlpm.dfin,INT(_xlpm.fin),_xlpm.hini,9.5*NETWORKDAYS.INTL(_xlpm.ep,_xlpm.dini-1,"0000111",_xlpm.fer)+6*NETWORKDAYS.INTL(_xlpm.ep,_xlpm.dini-1,"1111011",_xlpm.fer)+IF(OR(WEEKDAY(_xlpm.dini,2)>5,COUNTIF(_xlpm.fer,_xlpm.dini)>0),0,MAX(0,MIN(_xlpm.ini-_xlpm.dini,IF(WEEKDAY(_xlpm.dini,2)=5,14/24,17.5/24))-8/24)*24),_xlpm.hfin,9.5*NETWORKDAYS.INTL(_xlpm.ep,_xlpm.dfin-1,"0000111",_xlpm.fer)+6*NETWORKDAYS.INTL(_xlpm.ep,_xlpm.dfin-1,"1111011",_xlpm.fer)+IF(OR(WEEKDAY(_xlpm.dfin,2)>5,COUNTIF(_xlpm.fer,_xlpm.dfin)>0),0,MAX(0,MIN(_xlpm.fin-_xlpm.dfin,IF(WEEKDAY(_xlpm.dfin,2)=5,14/24,17.5/24))-8/24)*24),_xlpm.hrs,IF(SCTR_Brokers[[#This Row],[Estado]]="FINALIZADO",MAX(0,_xlpm.hfin-_xlpm.hini),IF(SCTR_Brokers[[#This Row],[Horas_Transcurridas]]="",MAX(0,_xlpm.hfin-_xlpm.hini),SCTR_Brokers[[#This Row],[Horas_Transcurridas]])),IF(_xlpm.hrs<=LISTAS!$E$3,LISTAS!$J$3,LISTAS!$J$4))) -> Fuera | T37: =IF(SCTR_Brokers[[#This Row],[FechaRecepcion]]="","",TEXT(SCTR_Brokers[[#This Row],[FechaRecepcion]],"mmmm")&" "&YEAR(SCTR_Brokers[[#This Row],[FechaRecepcion]])) -> agosto 2026 | U37: =IF(SCTR_Brokers[[#This Row],[Estado]]="FINALIZADO",1,0) -> 1 | V37: =IF(SCTR_Brokers[[#This Row],[FechaRecepcion]]="","",IF(SCTR_Brokers[[#This Row],[Estado]]="FINALIZADO",0,1)) -> 0 | W37: =IF(AND(SCTR_Brokers[[#This Row],[Estado]]="FINALIZADO",SCTR_Brokers[[#This Row],[Plazo]]=LISTAS!$J$3),1,0) -> 0 | X37: =IF(AND(SCTR_Brokers[[#This Row],[Estado]]="FINALIZADO",SCTR_Brokers[[#This Row],[Plazo]]=LISTAS!$J$4),1,0) -> 1 | Y37: =IF(AND(SCTR_Brokers[[#This Row],[Estado]]<>"FINALIZADO",SCTR_Brokers[[#This Row],[Plazo]]=LISTAS!$J$4),1,0) -> 0 | Z37: =IF(SCTR_Brokers[[#This Row],[Fecha_Solic_Informe]]="",0,1) -> 0 | AA37: =IF(SCTR_Brokers[[#This Row],[Fecha_Informe]]="",0,1) -> 0 | AB37: =IF(AND(SCTR_Brokers[[#This Row],[Fecha_Solic_Informe]]<>"",SCTR_Brokers[[#This Row],[Fecha_Informe]]=""),1,0) -> 0 | AC37: =IF(AND(SCTR_Brokers[[#This Row],[Fecha_Solic_Informe]]<>"",SCTR_Brokers[[#This Row],[Fecha_Informe]]<>""),ROUND((SCTR_Brokers[[#This Row],[Fecha_Informe]]-SCTR_Brokers[[#This Row],[Fecha_Solic_Informe]])*24,1),"")
A38: AAQkADdkNThjNzFkLWM0ZmMtNDJhYS04MDVlLTIwNzE4ZDI1Mzg4YgAQAMuH-dMLUk4CiFiyemFmjgw= | C38: =IF(SCTR_Brokers[[#This Row],[FechaRecepcion]]="","",SCTR_Brokers[[#This Row],[ConversationId]]&"-"&TEXT(SCTR_Brokers[[#This Row],[FechaRecepcion]],"aaaammddhhmmss")) -> AAQkADdkNThjNzFkLWM0ZmMtNDJhYS04MDVlLTIwNzE4ZDI1Mzg4YgAQAMuH-dMLUk4CiFiyemFmjgw=-20260818112508 | D38: RV: ACCIDENTE DE TRABAJO- COLABORADORA COCINA ANDREA GAMIO ZEVALLOS | E38: MARSH | F38: 46252.476 | G38: 46253.738 | H38: sctrsalud@mapfre.com.pe | I38: FINALIZADO | K38: SCTR SALUD | N38: =IF(SCTR_Brokers[[#This Row],[FechaRecepcion]]="","",IF(SCTR_Brokers[[#This Row],[Estado]]="FINALIZADO","",IF(SCTR_Brokers[[#This Row],[FechaUltimaRespuesta]]="","",_xlfn.LET(_xlpm.fer,LISTAS!$L$3:$L$100,_xlpm.ep,DATE(2000,1,1),_xlpm.ini,SCTR_Brokers[[#This Row],[FechaUltimaRespuesta]],_xlpm.fin,NOW(),_xlpm.dini,INT(_xlpm.ini),_xlpm.dfin,INT(_xlpm.fin),_xlpm.hini,9.5*NETWORKDAYS.INTL(_xlpm.ep,_xlpm.dini-1,"0000111",_xlpm.fer)+6*NETWORKDAYS.INTL(_xlpm.ep,_xlpm.dini-1,"1111011",_xlpm.fer)+IF(OR(WEEKDAY(_xlpm.dini,2)>5,COUNTIF(_xlpm.fer,_xlpm.dini)>0),0,MAX(0,MIN(_xlpm.ini-_xlpm.dini,IF(WEEKDAY(_xlpm.dini,2)=5,14/24,17.5/24))-8/24)*24),_xlpm.hfin,9.5*NETWORKDAYS.INTL(_xlpm.ep,_xlpm.dfin-1,"0000111",_xlpm.fer)+6*NETWORKDAYS.INTL(_xlpm.ep,_xlpm.dfin-1,"1111011",_xlpm.fer)+IF(OR(WEEKDAY(_xlpm.dfin,2)>5,COUNTIF(_xlpm.fer,_xlpm.dfin)>0),0,MAX(0,MIN(_xlpm.fin-_xlpm.dfin,IF(WEEKDAY(_xlpm.dfin,2)=5,14/24,17.5/24))-8/24)*24),ROUND(MAX(0,_xlpm.hfin-_xlpm.hini),1))))) | Q38: 46253.738 | R38: =IF(SCTR_Brokers[[#This Row],[FechaRecepcion]]="","",_xlfn.LET(_xlpm.fer,LISTAS!$L$3:$L$100,_xlpm.ep,DATE(2000,1,1),_xlpm.ini,SCTR_Brokers[[#This Row],[FechaRecepcion]],_xlpm.fin,IF(SCTR_Brokers[[#This Row],[Fecha_Cierre]]<>"",SCTR_Brokers[[#This Row],[Fecha_Cierre]],NOW()),_xlpm.dini,INT(_xlpm.ini),_xlpm.dfin,INT(_xlpm.fin),_xlpm.hini,9.5*NETWORKDAYS.INTL(_xlpm.ep,_xlpm.dini-1,"0000111",_xlpm.fer)+6*NETWORKDAYS.INTL(_xlpm.ep,_xlpm.dini-1,"1111011",_xlpm.fer)+IF(OR(WEEKDAY(_xlpm.dini,2)>5,COUNTIF(_xlpm.fer,_xlpm.dini)>0),0,MAX(0,MIN(_xlpm.ini-_xlpm.dini,IF(WEEKDAY(_xlpm.dini,2)=5,14/24,17.5/24))-8/24)*24),_xlpm.hfin,9.5*NETWORKDAYS.INTL(_xlpm.ep,_xlpm.dfin-1,"0000111",_xlpm.fer)+6*NETWORKDAYS.INTL(_xlpm.ep,_xlpm.dfin-1,"1111011",_xlpm.fer)+IF(OR(WEEKDAY(_xlpm.dfin,2)>5,COUNTIF(_xlpm.fer,_xlpm.dfin)>0),0,MAX(0,MIN(_xlpm.fin-_xlpm.dfin,IF(WEEKDAY(_xlpm.dfin,2)=5,14/24,17.5/24))-8/24)*24),_xlpm.hrs,IF(SCTR_Brokers[[#This Row],[Estado]]="FINALIZADO",MAX(0,_xlpm.hfin-_xlpm.hini),IF(SCTR_Brokers[[#This Row],[Horas_Transcurridas]]="",MAX(0,_xlpm.hfin-_xlpm.hini),SCTR_Brokers[[#This Row],[Horas_Transcurridas]])),IF(_xlpm.hrs<=LISTAS!$E$3,LISTAS!$J$3,LISTAS!$J$4))) -> Fuera | T38: =IF(SCTR_Brokers[[#This Row],[FechaRecepcion]]="","",TEXT(SCTR_Brokers[[#This Row],[FechaRecepcion]],"mmmm")&" "&YEAR(SCTR_Brokers[[#This Row],[FechaRecepcion]])) -> agosto 2026 | U38: =IF(SCTR_Brokers[[#This Row],[Estado]]="FINALIZADO",1,0) -> 1 | V38: =IF(SCTR_Brokers[[#This Row],[FechaRecepcion]]="","",IF(SCTR_Brokers[[#This Row],[Estado]]="FINALIZADO",0,1)) -> 0 | W38: =IF(AND(SCTR_Brokers[[#This Row],[Estado]]="FINALIZADO",SCTR_Brokers[[#This Row],[Plazo]]=LISTAS!$J$3),1,0) -> 0 | X38: =IF(AND(SCTR_Brokers[[#This Row],[Estado]]="FINALIZADO",SCTR_Brokers[[#This Row],[Plazo]]=LISTAS!$J$4),1,0) -> 1 | Y38: =IF(AND(SCTR_Brokers[[#This Row],[Estado]]<>"FINALIZADO",SCTR_Brokers[[#This Row],[Plazo]]=LISTAS!$J$4),1,0) -> 0 | Z38: =IF(SCTR_Brokers[[#This Row],[Fecha_Solic_Informe]]="",0,1) -> 0 | AA38: =IF(SCTR_Brokers[[#This Row],[Fecha_Informe]]="",0,1) -> 0 | AB38: =IF(AND(SCTR_Brokers[[#This Row],[Fecha_Solic_Informe]]<>"",SCTR_Brokers[[#This Row],[Fecha_Informe]]=""),1,0) -> 0 | AC38: =IF(AND(SCTR_Brokers[[#This Row],[Fecha_Solic_Informe]]<>"",SCTR_Brokers[[#This Row],[Fecha_Informe]]<>""),ROUND((SCTR_Brokers[[#This Row],[Fecha_Informe]]-SCTR_Brokers[[#This Row],[Fecha_Solic_Informe]])*24,1),"")
A39: AAQkADdkNThjNzFkLWM0ZmMtNDJhYS04MDVlLTIwNzE4ZDI1Mzg4YgAQAIXUVz1Cok_FtJuJK1aUloI= | C39: =IF(SCTR_Brokers[[#This Row],[FechaRecepcion]]="","",SCTR_Brokers[[#This Row],[ConversationId]]&"-"&TEXT(SCTR_Brokers[[#This Row],[FechaRecepcion]],"aaaammddhhmmss")) -> AAQkADdkNThjNzFkLWM0ZmMtNDJhYS04MDVlLTIwNzE4ZDI1Mzg4YgAQAIXUVz1Cok_FtJuJK1aUloI=-20260818115527 | D39: DON POLLO LA LIBERTAD // SCTR SALUD - ACCIDENTE DE TRABAJO: CASTRO PALACIOS AGUSTIN | E39: MARSH | F39: 46252.497 | G39: 46252.497 | H39: Marsh.SiniestrosRRLL@marsh.com | I39: FINALIZADO | J39: | POSIBLE DERIVACIÓN 19/08/2026 09:00 | K39: SCTR SALUD | N39: =IF(SCTR_Brokers[[#This Row],[FechaRecepcion]]="","",IF(SCTR_Brokers[[#This Row],[Estado]]="FINALIZADO","",IF(SCTR_Brokers[[#This Row],[FechaUltimaRespuesta]]="","",_xlfn.LET(_xlpm.fer,LISTAS!$L$3:$L$100,_xlpm.ep,DATE(2000,1,1),_xlpm.ini,SCTR_Brokers[[#This Row],[FechaUltimaRespuesta]],_xlpm.fin,NOW(),_xlpm.dini,INT(_xlpm.ini),_xlpm.dfin,INT(_xlpm.fin),_xlpm.hini,9.5*NETWORKDAYS.INTL(_xlpm.ep,_xlpm.dini-1,"0000111",_xlpm.fer)+6*NETWORKDAYS.INTL(_xlpm.ep,_xlpm.dini-1,"1111011",_xlpm.fer)+IF(OR(WEEKDAY(_xlpm.dini,2)>5,COUNTIF(_xlpm.fer,_xlpm.dini)>0),0,MAX(0,MIN(_xlpm.ini-_xlpm.dini,IF(WEEKDAY(_xlpm.dini,2)=5,14/24,17.5/24))-8/24)*24),_xlpm.hfin,9.5*NETWORKDAYS.INTL(_xlpm.ep,_xlpm.dfin-1,"0000111",_xlpm.fer)+6*NETWORKDAYS.INTL(_xlpm.ep,_xlpm.dfin-1,"1111011",_xlpm.fer)+IF(OR(WEEKDAY(_xlpm.dfin,2)>5,COUNTIF(_xlpm.fer,_xlpm.dfin)>0),0,MAX(0,MIN(_xlpm.fin-_xlpm.dfin,IF(WEEKDAY(_xlpm.dfin,2)=5,14/24,17.5/24))-8/24)*24),ROUND(MAX(0,_xlpm.hfin-_xlpm.hini),1))))) | R39: =IF(SCTR_Brokers[[#This Row],[FechaRecepcion]]="","",_xlfn.LET(_xlpm.fer,LISTAS!$L$3:$L$100,_xlpm.ep,DATE(2000,1,1),_xlpm.ini,SCTR_Brokers[[#This Row],[FechaRecepcion]],_xlpm.fin,IF(SCTR_Brokers[[#This Row],[Fecha_Cierre]]<>"",SCTR_Brokers[[#This Row],[Fecha_Cierre]],NOW()),_xlpm.dini,INT(_xlpm.ini),_xlpm.dfin,INT(_xlpm.fin),_xlpm.hini,9.5*NETWORKDAYS.INTL(_xlpm.ep,_xlpm.dini-1,"0000111",_xlpm.fer)+6*NETWORKDAYS.INTL(_xlpm.ep,_xlpm.dini-1,"1111011",_xlpm.fer)+IF(OR(WEEKDAY(_xlpm.dini,2)>5,COUNTIF(_xlpm.fer,_xlpm.dini)>0),0,MAX(0,MIN(_xlpm.ini-_xlpm.dini,IF(WEEKDAY(_xlpm.dini,2)=5,14/24,17.5/24))-8/24)*24),_xlpm.hfin,9.5*NETWORKDAYS.INTL(_xlpm.ep,_xlpm.dfin-1,"0000111",_xlpm.fer)+6*NETWORKDAYS.INTL(_xlpm.ep,_xlpm.dfin-1,"1111011",_xlpm.fer)+IF(OR(WEEKDAY(_xlpm.dfin,2)>5,COUNTIF(_xlpm.fer,_xlpm.dfin)>0),0,MAX(0,MIN(_xlpm.fin-_xlpm.dfin,IF(WEEKDAY(_xlpm.dfin,2)=5,14/24,17.5/24))-8/24)*24),_xlpm.hrs,IF(SCTR_Brokers[[#This Row],[Estado]]="FINALIZADO",MAX(0,_xlpm.hfin-_xlpm.hini),IF(SCTR_Brokers[[#This Row],[Horas_Transcurridas]]="",MAX(0,_xlpm.hfin-_xlpm.hini),SCTR_Brokers[[#This Row],[Horas_Transcurridas]])),IF(_xlpm.hrs<=LISTAS!$E$3,LISTAS!$J$3,LISTAS!$J$4))) -> Fuera | T39: =IF(SCTR_Brokers[[#This Row],[FechaRecepcion]]="","",TEXT(SCTR_Brokers[[#This Row],[FechaRecepcion]],"mmmm")&" "&YEAR(SCTR_Brokers[[#This Row],[FechaRecepcion]])) -> agosto 2026 | U39: =IF(SCTR_Brokers[[#This Row],[Estado]]="FINALIZADO",1,0) -> 1 | V39: =IF(SCTR_Brokers[[#This Row],[FechaRecepcion]]="","",IF(SCTR_Brokers[[#This Row],[Estado]]="FINALIZADO",0,1)) -> 0 | W39: =IF(AND(SCTR_Brokers[[#This Row],[Estado]]="FINALIZADO",SCTR_Brokers[[#This Row],[Plazo]]=LISTAS!$J$3),1,0) -> 0 | X39: =IF(AND(SCTR_Brokers[[#This Row],[Estado]]="FINALIZADO",SCTR_Brokers[[#This Row],[Plazo]]=LISTAS!$J$4),1,0) -> 1 | Y39: =IF(AND(SCTR_Brokers[[#This Row],[Estado]]<>"FINALIZADO",SCTR_Brokers[[#This Row],[Plazo]]=LISTAS!$J$4),1,0) -> 0 | Z39: =IF(SCTR_Brokers[[#This Row],[Fecha_Solic_Informe]]="",0,1) -> 0 | AA39: =IF(SCTR_Brokers[[#This Row],[Fecha_Informe]]="",0,1) -> 0 | AB39: =IF(AND(SCTR_Brokers[[#This Row],[Fecha_Solic_Informe]]<>"",SCTR_Brokers[[#This Row],[Fecha_Informe]]=""),1,0) -> 0 | AC39: =IF(AND(SCTR_Brokers[[#This Row],[Fecha_Solic_Informe]]<>"",SCTR_Brokers[[#This Row],[Fecha_Informe]]<>""),ROUND((SCTR_Brokers[[#This Row],[Fecha_Informe]]-SCTR_Brokers[[#This Row],[Fecha_Solic_Informe]])*24,1),"")
A40: AAQkADdkNThjNzFkLWM0ZmMtNDJhYS04MDVlLTIwNzE4ZDI1Mzg4YgAQANgmCUHEJVVIljOU-AWYE_M= | C40: =IF(SCTR_Brokers[[#This Row],[FechaRecepcion]]="","",SCTR_Brokers[[#This Row],[ConversationId]]&"-"&TEXT(SCTR_Brokers[[#This Row],[FechaRecepcion]],"aaaammddhhmmss")) -> AAQkADdkNThjNzFkLWM0ZmMtNDJhYS04MDVlLTIwNzE4ZDI1Mzg4YgAQANgmCUHEJVVIljOU-AWYE_M=-20260818123958 | D40: RE: GRUPO EULEN - ACTIVACION SCTR SALUD - ANGELICA LORENZO SENTENO DNI: 10702647 | E40: UIB | F40: 46252.528 | G40: 46260.657 | H40: sctrsalud@mapfre.com.pe | I40: FINALIZADO | K40: SCTR SALUD | N40: =IF(SCTR_Brokers[[#This Row],[FechaRecepcion]]="","",IF(SCTR_Brokers[[#This Row],[Estado]]="FINALIZADO","",IF(SCTR_Brokers[[#This Row],[FechaUltimaRespuesta]]="","",_xlfn.LET(_xlpm.fer,LISTAS!$L$3:$L$100,_xlpm.ep,DATE(2000,1,1),_xlpm.ini,SCTR_Brokers[[#This Row],[FechaUltimaRespuesta]],_xlpm.fin,NOW(),_xlpm.dini,INT(_xlpm.ini),_xlpm.dfin,INT(_xlpm.fin),_xlpm.hini,9.5*NETWORKDAYS.INTL(_xlpm.ep,_xlpm.dini-1,"0000111",_xlpm.fer)+6*NETWORKDAYS.INTL(_xlpm.ep,_xlpm.dini-1,"1111011",_xlpm.fer)+IF(OR(WEEKDAY(_xlpm.dini,2)>5,COUNTIF(_xlpm.fer,_xlpm.dini)>0),0,MAX(0,MIN(_xlpm.ini-_xlpm.dini,IF(WEEKDAY(_xlpm.dini,2)=5,14/24,17.5/24))-8/24)*24),_xlpm.hfin,9.5*NETWORKDAYS.INTL(_xlpm.ep,_xlpm.dfin-1,"0000111",_xlpm.fer)+6*NETWORKDAYS.INTL(_xlpm.ep,_xlpm.dfin-1,"1111011",_xlpm.fer)+IF(OR(WEEKDAY(_xlpm.dfin,2)>5,COUNTIF(_xlpm.fer,_xlpm.dfin)>0),0,MAX(0,MIN(_xlpm.fin-_xlpm.dfin,IF(WEEKDAY(_xlpm.dfin,2)=5,14/24,17.5/24))-8/24)*24),ROUND(MAX(0,_xlpm.hfin-_xlpm.hini),1))))) | Q40: 46260.657 | R40: =IF(SCTR_Brokers[[#This Row],[FechaRecepcion]]="","",_xlfn.LET(_xlpm.fer,LISTAS!$L$3:$L$100,_xlpm.ep,DATE(2000,1,1),_xlpm.ini,SCTR_Brokers[[#This Row],[FechaRecepcion]],_xlpm.fin,IF(SCTR_Brokers[[#This Row],[Fecha_Cierre]]<>"",SCTR_Brokers[[#This Row],[Fecha_Cierre]],NOW()),_xlpm.dini,INT(_xlpm.ini),_xlpm.dfin,INT(_xlpm.fin),_xlpm.hini,9.5*NETWORKDAYS.INTL(_xlpm.ep,_xlpm.dini-1,"0000111",_xlpm.fer)+6*NETWORKDAYS.INTL(_xlpm.ep,_xlpm.dini-1,"1111011",_xlpm.fer)+IF(OR(WEEKDAY(_xlpm.dini,2)>5,COUNTIF(_xlpm.fer,_xlpm.dini)>0),0,MAX(0,MIN(_xlpm.ini-_xlpm.dini,IF(WEEKDAY(_xlpm.dini,2)=5,14/24,17.5/24))-8/24)*24),_xlpm.hfin,9.5*NETWORKDAYS.INTL(_xlpm.ep,_xlpm.dfin-1,"0000111",_xlpm.fer)+6*NETWORKDAYS.INTL(_xlpm.ep,_xlpm.dfin-1,"1111011",_xlpm.fer)+IF(OR(WEEKDAY(_xlpm.dfin,2)>5,COUNTIF(_xlpm.fer,_xlpm.dfin)>0),0,MAX(0,MIN(_xlpm.fin-_xlpm.dfin,IF(WEEKDAY(_xlpm.dfin,2)=5,14/24,17.5/24))-8/24)*24),_xlpm.hrs,IF(SCTR_Brokers[[#This Row],[Estado]]="FINALIZADO",MAX(0,_xlpm.hfin-_xlpm.hini),IF(SCTR_Brokers[[#This Row],[Horas_Transcurridas]]="",MAX(0,_xlpm.hfin-_xlpm.hini),SCTR_Brokers[[#This Row],[Horas_Transcurridas]])),IF(_xlpm.hrs<=LISTAS!$E$3,LISTAS!$J$3,LISTAS!$J$4))) -> Fuera | T40: =IF(SCTR_Brokers[[#This Row],[FechaRecepcion]]="","",TEXT(SCTR_Brokers[[#This Row],[FechaRecepcion]],"mmmm")&" "&YEAR(SCTR_Brokers[[#This Row],[FechaRecepcion]])) -> agosto 2026 | U40: =IF(SCTR_Brokers[[#This Row],[Estado]]="FINALIZADO",1,0) -> 1 | V40: =IF(SCTR_Brokers[[#This Row],[FechaRecepcion]]="","",IF(SCTR_Brokers[[#This Row],[Estado]]="FINALIZADO",0,1)) -> 0 | W40: =IF(AND(SCTR_Brokers[[#This Row],[Estado]]="FINALIZADO",SCTR_Brokers[[#This Row],[Plazo]]=LISTAS!$J$3),1,0) -> 0 | X40: =IF(AND(SCTR_Brokers[[#This Row],[Estado]]="FINALIZADO",SCTR_Brokers[[#This Row],[Plazo]]=LISTAS!$J$4),1,0) -> 1 | Y40: =IF(AND(SCTR_Brokers[[#This Row],[Estado]]<>"FINALIZADO",SCTR_Brokers[[#This Row],[Plazo]]=LISTAS!$J$4),1,0) -> 0 | Z40: =IF(SCTR_Brokers[[#This Row],[Fecha_Solic_Informe]]="",0,1) -> 0 | AA40: =IF(SCTR_Brokers[[#This Row],[Fecha_Informe]]="",0,1) -> 0 | AB40: =IF(AND(SCTR_Brokers[[#This Row],[Fecha_Solic_Informe]]<>"",SCTR_Brokers[[#This Row],[Fecha_Informe]]=""),1,0) -> 0 | AC40: =IF(AND(SCTR_Brokers[[#This Row],[Fecha_Solic_Informe]]<>"",SCTR_Brokers[[#This Row],[Fecha_Informe]]<>""),ROUND((SCTR_Brokers[[#This Row],[Fecha_Informe]]-SCTR_Brokers[[#This Row],[Fecha_Solic_Informe]])*24,1),"")
A41: AAQkADdkNThjNzFkLWM0ZmMtNDJhYS04MDVlLTIwNzE4ZDI1Mzg4YgAQAMgSKhk6K79HgQMdRODPPuk= | C41: =IF(SCTR_Brokers[[#This Row],[FechaRecepcion]]="","",SCTR_Brokers[[#This Row],[ConversationId]]&"-"&TEXT(SCTR_Brokers[[#This Row],[FechaRecepcion]],"aaaammddhhmmss")) -> AAQkADdkNThjNzFkLWM0ZmMtNDJhYS04MDVlLTIwNzE4ZDI1Mzg4YgAQAMgSKhk6K79HgQMdRODPPuk=-20260818143925 | D41: RV: Solicitud de soporte – Terapias MAPFRE en Tarapoto - Royer Yaricahua Tapullima // DON POLLO TROPICAL | E41: MARSH | F41: 46252.611 | G41: 46252.611 | H41: fernando.perez-torres@mercermarshbeneficios.com | I41: FINALIZADO | K41: SCTR SALUD | N41: =IF(SCTR_Brokers[[#This Row],[FechaRecepcion]]="","",IF(SCTR_Brokers[[#This Row],[Estado]]="FINALIZADO","",IF(SCTR_Brokers[[#This Row],[FechaUltimaRespuesta]]="","",_xlfn.LET(_xlpm.fer,LISTAS!$L$3:$L$100,_xlpm.ep,DATE(2000,1,1),_xlpm.ini,SCTR_Brokers[[#This Row],[FechaUltimaRespuesta]],_xlpm.fin,NOW(),_xlpm.dini,INT(_xlpm.ini),_xlpm.dfin,INT(_xlpm.fin),_xlpm.hini,9.5*NETWORKDAYS.INTL(_xlpm.ep,_xlpm.dini-1,"0000111",_xlpm.fer)+6*NETWORKDAYS.INTL(_xlpm.ep,_xlpm.dini-1,"1111011",_xlpm.fer)+IF(OR(WEEKDAY(_xlpm.dini,2)>5,COUNTIF(_xlpm.fer,_xlpm.dini)>0),0,MAX(0,MIN(_xlpm.ini-_xlpm.dini,IF(WEEKDAY(_xlpm.dini,2)=5,14/24,17.5/24))-8/24)*24),_xlpm.hfin,9.5*NETWORKDAYS.INTL(_xlpm.ep,_xlpm.dfin-1,"0000111",_xlpm.fer)+6*NETWORKDAYS.INTL(_xlpm.ep,_xlpm.dfin-1,"1111011",_xlpm.fer)+IF(OR(WEEKDAY(_xlpm.dfin,2)>5,COUNTIF(_xlpm.fer,_xlpm.dfin)>0),0,MAX(0,MIN(_xlpm.fin-_xlpm.dfin,IF(WEEKDAY(_xlpm.dfin,2)=5,14/24,17.5/24))-8/24)*24),ROUND(MAX(0,_xlpm.hfin-_xlpm.hini),1))))) | Q41: 46252.643 | R41: =IF(SCTR_Brokers[[#This Row],[FechaRecepcion]]="","",_xlfn.LET(_xlpm.fer,LISTAS!$L$3:$L$100,_xlpm.ep,DATE(2000,1,1),_xlpm.ini,SCTR_Brokers[[#This Row],[FechaRecepcion]],_xlpm.fin,IF(SCTR_Brokers[[#This Row],[Fecha_Cierre]]<>"",SCTR_Brokers[[#This Row],[Fecha_Cierre]],NOW()),_xlpm.dini,INT(_xlpm.ini),_xlpm.dfin,INT(_xlpm.fin),_xlpm.hini,9.5*NETWORKDAYS.INTL(_xlpm.ep,_xlpm.dini-1,"0000111",_xlpm.fer)+6*NETWORKDAYS.INTL(_xlpm.ep,_xlpm.dini-1,"1111011",_xlpm.fer)+IF(OR(WEEKDAY(_xlpm.dini,2)>5,COUNTIF(_xlpm.fer,_xlpm.dini)>0),0,MAX(0,MIN(_xlpm.ini-_xlpm.dini,IF(WEEKDAY(_xlpm.dini,2)=5,14/24,17.5/24))-8/24)*24),_xlpm.hfin,9.5*NETWORKDAYS.INTL(_xlpm.ep,_xlpm.dfin-1,"0000111",_xlpm.fer)+6*NETWORKDAYS.INTL(_xlpm.ep,_xlpm.dfin-1,"1111011",_xlpm.fer)+IF(OR(WEEKDAY(_xlpm.dfin,2)>5,COUNTIF(_xlpm.fer,_xlpm.dfin)>0),0,MAX(0,MIN(_xlpm.fin-_xlpm.dfin,IF(WEEKDAY(_xlpm.dfin,2)=5,14/24,17.5/24))-8/24)*24),_xlpm.hrs,IF(SCTR_Brokers[[#This Row],[Estado]]="FINALIZADO",MAX(0,_xlpm.hfin-_xlpm.hini),IF(SCTR_Brokers[[#This Row],[Horas_Transcurridas]]="",MAX(0,_xlpm.hfin-_xlpm.hini),SCTR_Brokers[[#This Row],[Horas_Transcurridas]])),IF(_xlpm.hrs<=LISTAS!$E$3,LISTAS!$J$3,LISTAS!$J$4))) -> Dentro | T41: =IF(SCTR_Brokers[[#This Row],[FechaRecepcion]]="","",TEXT(SCTR_Brokers[[#This Row],[FechaRecepcion]],"mmmm")&" "&YEAR(SCTR_Brokers[[#This Row],[FechaRecepcion]])) -> agosto 2026 | U41: =IF(SCTR_Brokers[[#This Row],[Estado]]="FINALIZADO",1,0) -> 1 | V41: =IF(SCTR_Brokers[[#This Row],[FechaRecepcion]]="","",IF(SCTR_Brokers[[#This Row],[Estado]]="FINALIZADO",0,1)) -> 0 | W41: =IF(AND(SCTR_Brokers[[#This Row],[Estado]]="FINALIZADO",SCTR_Brokers[[#This Row],[Plazo]]=LISTAS!$J$3),1,0) -> 1 | X41: =IF(AND(SCTR_Brokers[[#This Row],[Estado]]="FINALIZADO",SCTR_Brokers[[#This Row],[Plazo]]=LISTAS!$J$4),1,0) -> 0 | Y41: =IF(AND(SCTR_Brokers[[#This Row],[Estado]]<>"FINALIZADO",SCTR_Brokers[[#This Row],[Plazo]]=LISTAS!$J$4),1,0) -> 0 | Z41: =IF(SCTR_Brokers[[#This Row],[Fecha_Solic_Informe]]="",0,1) -> 0 | AA41: =IF(SCTR_Brokers[[#This Row],[Fecha_Informe]]="",0,1) -> 0 | AB41: =IF(AND(SCTR_Brokers[[#This Row],[Fecha_Solic_Informe]]<>"",SCTR_Brokers[[#This Row],[Fecha_Informe]]=""),1,0) -> 0 | AC41: =IF(AND(SCTR_Brokers[[#This Row],[Fecha_Solic_Informe]]<>"",SCTR_Brokers[[#This Row],[Fecha_Informe]]<>""),ROUND((SCTR_Brokers[[#This Row],[Fecha_Informe]]-SCTR_Brokers[[#This Row],[Fecha_Solic_Informe]])*24,1),"")
A42: AAQkADdkNThjNzFkLWM0ZmMtNDJhYS04MDVlLTIwNzE4ZDI1Mzg4YgAQAPFbcqJeg0qGkSE5XuTK5O8= | C42: =IF(SCTR_Brokers[[#This Row],[FechaRecepcion]]="","",SCTR_Brokers[[#This Row],[ConversationId]]&"-"&TEXT(SCTR_Brokers[[#This Row],[FechaRecepcion]],"aaaammddhhmmss")) -> AAQkADdkNThjNzFkLWM0ZmMtNDJhYS04MDVlLTIwNzE4ZDI1Mzg4YgAQAPFbcqJeg0qGkSE5XuTK5O8=-20260818144209 | D42: RE: URGENTE *** REEMBOLSO ACCIDENTE DE TRABAJO (ZONA ALEJADA) // SCTR SALUD 7021800070721 // DON POLLO LA LIBERTAD S.A.C. // ASEGURADO: ANGULO ARTIAGA, LUIS MARIO | E42: MARSH | F42: 46252.613 | G42: 46253.504 | H42: sctrsalud@mapfre.com.pe | I42: FINALIZADO | J42: | POSIBLE DERIVACIÓN 19/08/2026 09:00 | K42: SCTR SALUD | N42: =IF(SCTR_Brokers[[#This Row],[FechaRecepcion]]="","",IF(SCTR_Brokers[[#This Row],[Estado]]="FINALIZADO","",IF(SCTR_Brokers[[#This Row],[FechaUltimaRespuesta]]="","",_xlfn.LET(_xlpm.fer,LISTAS!$L$3:$L$100,_xlpm.ep,DATE(2000,1,1),_xlpm.ini,SCTR_Brokers[[#This Row],[FechaUltimaRespuesta]],_xlpm.fin,NOW(),_xlpm.dini,INT(_xlpm.ini),_xlpm.dfin,INT(_xlpm.fin),_xlpm.hini,9.5*NETWORKDAYS.INTL(_xlpm.ep,_xlpm.dini-1,"0000111",_xlpm.fer)+6*NETWORKDAYS.INTL(_xlpm.ep,_xlpm.dini-1,"1111011",_xlpm.fer)+IF(OR(WEEKDAY(_xlpm.dini,2)>5,COUNTIF(_xlpm.fer,_xlpm.dini)>0),0,MAX(0,MIN(_xlpm.ini-_xlpm.dini,IF(WEEKDAY(_xlpm.dini,2)=5,14/24,17.5/24))-8/24)*24),_xlpm.hfin,9.5*NETWORKDAYS.INTL(_xlpm.ep,_xlpm.dfin-1,"0000111",_xlpm.fer)+6*NETWORKDAYS.INTL(_xlpm.ep,_xlpm.dfin-1,"1111011",_xlpm.fer)+IF(OR(WEEKDAY(_xlpm.dfin,2)>5,COUNTIF(_xlpm.fer,_xlpm.dfin)>0),0,MAX(0,MIN(_xlpm.fin-_xlpm.dfin,IF(WEEKDAY(_xlpm.dfin,2)=5,14/24,17.5/24))-8/24)*24),ROUND(MAX(0,_xlpm.hfin-_xlpm.hini),1))))) | Q42: 46253.504 | R42: =IF(SCTR_Brokers[[#This Row],[FechaRecepcion]]="","",_xlfn.LET(_xlpm.fer,LISTAS!$L$3:$L$100,_xlpm.ep,DATE(2000,1,1),_xlpm.ini,SCTR_Brokers[[#This Row],[FechaRecepcion]],_xlpm.fin,IF(SCTR_Brokers[[#This Row],[Fecha_Cierre]]<>"",SCTR_Brokers[[#This Row],[Fecha_Cierre]],NOW()),_xlpm.dini,INT(_xlpm.ini),_xlpm.dfin,INT(_xlpm.fin),_xlpm.hini,9.5*NETWORKDAYS.INTL(_xlpm.ep,_xlpm.dini-1,"0000111",_xlpm.fer)+6*NETWORKDAYS.INTL(_xlpm.ep,_xlpm.dini-1,"1111011",_xlpm.fer)+IF(OR(WEEKDAY(_xlpm.dini,2)>5,COUNTIF(_xlpm.fer,_xlpm.dini)>0),0,MAX(0,MIN(_xlpm.ini-_xlpm.dini,IF(WEEKDAY(_xlpm.dini,2)=5,14/24,17.5/24))-8/24)*24),_xlpm.hfin,9.5*NETWORKDAYS.INTL(_xlpm.ep,_xlpm.dfin-1,"0000111",_xlpm.fer)+6*NETWORKDAYS.INTL(_xlpm.ep,_xlpm.dfin-1,"1111011",_xlpm.fer)+IF(OR(WEEKDAY(_xlpm.dfin,2)>5,COUNTIF(_xlpm.fer,_xlpm.dfin)>0),0,MAX(0,MIN(_xlpm.fin-_xlpm.dfin,IF(WEEKDAY(_xlpm.dfin,2)=5,14/24,17.5/24))-8/24)*24),_xlpm.hrs,IF(SCTR_Brokers[[#This Row],[Estado]]="FINALIZADO",MAX(0,_xlpm.hfin-_xlpm.hini),IF(SCTR_Brokers[[#This Row],[Horas_Transcurridas]]="",MAX(0,_xlpm.hfin-_xlpm.hini),SCTR_Brokers[[#This Row],[Horas_Transcurridas]])),IF(_xlpm.hrs<=LISTAS!$E$3,LISTAS!$J$3,LISTAS!$J$4))) -> Fuera | T42: =IF(SCTR_Brokers[[#This Row],[FechaRecepcion]]="","",TEXT(SCTR_Brokers[[#This Row],[FechaRecepcion]],"mmmm")&" "&YEAR(SCTR_Brokers[[#This Row],[FechaRecepcion]])) -> agosto 2026 | U42: =IF(SCTR_Brokers[[#This Row],[Estado]]="FINALIZADO",1,0) -> 1 | V42: =IF(SCTR_Brokers[[#This Row],[FechaRecepcion]]="","",IF(SCTR_Brokers[[#This Row],[Estado]]="FINALIZADO",0,1)) -> 0 | W42: =IF(AND(SCTR_Brokers[[#This Row],[Estado]]="FINALIZADO",SCTR_Brokers[[#This Row],[Plazo]]=LISTAS!$J$3),1,0) -> 0 | X42: =IF(AND(SCTR_Brokers[[#This Row],[Estado]]="FINALIZADO",SCTR_Brokers[[#This Row],[Plazo]]=LISTAS!$J$4),1,0) -> 1 | Y42: =IF(AND(SCTR_Brokers[[#This Row],[Estado]]<>"FINALIZADO",SCTR_Brokers[[#This Row],[Plazo]]=LISTAS!$J$4),1,0) -> 0 | Z42: =IF(SCTR_Brokers[[#This Row],[Fecha_Solic_Informe]]="",0,1) -> 0 | AA42: =IF(SCTR_Brokers[[#This Row],[Fecha_Informe]]="",0,1) -> 0 | AB42: =IF(AND(SCTR_Brokers[[#This Row],[Fecha_Solic_Informe]]<>"",SCTR_Brokers[[#This Row],[Fecha_Informe]]=""),1,0) -> 0 | AC42: =IF(AND(SCTR_Brokers[[#This Row],[Fecha_Solic_Informe]]<>"",SCTR_Brokers[[#This Row],[Fecha_Informe]]<>""),ROUND((SCTR_Brokers[[#This Row],[Fecha_Informe]]-SCTR_Brokers[[#This Row],[Fecha_Solic_Informe]])*24,1),"")
A43: AAQkADdkNThjNzFkLWM0ZmMtNDJhYS04MDVlLTIwNzE4ZDI1Mzg4YgAQAMsK5VMVFdBHmL90t5-5qO0= | C43: =IF(SCTR_Brokers[[#This Row],[FechaRecepcion]]="","",SCTR_Brokers[[#This Row],[ConversationId]]&"-"&TEXT(SCTR_Brokers[[#This Row],[FechaRecepcion]],"aaaammddhhmmss")) -> AAQkADdkNThjNzFkLWM0ZmMtNDJhYS04MDVlLTIwNzE4ZDI1Mzg4YgAQAMsK5VMVFdBHmL90t5-5qO0=-20260818145637 | D43: RE: CORPORACION DE INDUSTRIAS STANDFORD Atención SCTR Giovana Espíritu Pascual | E43: MARSH | F43: 46252.623 | G43: 46252.623 | H43: luis.zeballos@mercermarshbeneficios.com | I43: FINALIZADO | J43: | DERIVADO 20/08/2026 12:00 | K43: SCTR SALUD | N43: =IF(SCTR_Brokers[[#This Row],[FechaRecepcion]]="","",IF(SCTR_Brokers[[#This Row],[Estado]]="FINALIZADO","",IF(SCTR_Brokers[[#This Row],[FechaUltimaRespuesta]]="","",_xlfn.LET(_xlpm.fer,LISTAS!$L$3:$L$100,_xlpm.ep,DATE(2000,1,1),_xlpm.ini,SCTR_Brokers[[#This Row],[FechaUltimaRespuesta]],_xlpm.fin,NOW(),_xlpm.dini,INT(_xlpm.ini),_xlpm.dfin,INT(_xlpm.fin),_xlpm.hini,9.5*NETWORKDAYS.INTL(_xlpm.ep,_xlpm.dini-1,"0000111",_xlpm.fer)+6*NETWORKDAYS.INTL(_xlpm.ep,_xlpm.dini-1,"1111011",_xlpm.fer)+IF(OR(WEEKDAY(_xlpm.dini,2)>5,COUNTIF(_xlpm.fer,_xlpm.dini)>0),0,MAX(0,MIN(_xlpm.ini-_xlpm.dini,IF(WEEKDAY(_xlpm.dini,2)=5,14/24,17.5/24))-8/24)*24),_xlpm.hfin,9.5*NETWORKDAYS.INTL(_xlpm.ep,_xlpm.dfin-1,"0000111",_xlpm.fer)+6*NETWORKDAYS.INTL(_xlpm.ep,_xlpm.dfin-1,"1111011",_xlpm.fer)+IF(OR(WEEKDAY(_xlpm.dfin,2)>5,COUNTIF(_xlpm.fer,_xlpm.dfin)>0),0,MAX(0,MIN(_xlpm.fin-_xlpm.dfin,IF(WEEKDAY(_xlpm.dfin,2)=5,14/24,17.5/24))-8/24)*24),ROUND(MAX(0,_xlpm.hfin-_xlpm.hini),1))))) | Q43: 46252.623 | R43: =IF(SCTR_Brokers[[#This Row],[FechaRecepcion]]="","",_xlfn.LET(_xlpm.fer,LISTAS!$L$3:$L$100,_xlpm.ep,DATE(2000,1,1),_xlpm.ini,SCTR_Brokers[[#This Row],[FechaRecepcion]],_xlpm.fin,IF(SCTR_Brokers[[#This Row],[Fecha_Cierre]]<>"",SCTR_Brokers[[#This Row],[Fecha_Cierre]],NOW()),_xlpm.dini,INT(_xlpm.ini),_xlpm.dfin,INT(_xlpm.fin),_xlpm.hini,9.5*NETWORKDAYS.INTL(_xlpm.ep,_xlpm.dini-1,"0000111",_xlpm.fer)+6*NETWORKDAYS.INTL(_xlpm.ep,_xlpm.dini-1,"1111011",_xlpm.fer)+IF(OR(WEEKDAY(_xlpm.dini,2)>5,COUNTIF(_xlpm.fer,_xlpm.dini)>0),0,MAX(0,MIN(_xlpm.ini-_xlpm.dini,IF(WEEKDAY(_xlpm.dini,2)=5,14/24,17.5/24))-8/24)*24),_xlpm.hfin,9.5*NETWORKDAYS.INTL(_xlpm.ep,_xlpm.dfin-1,"0000111",_xlpm.fer)+6*NETWORKDAYS.INTL(_xlpm.ep,_xlpm.dfin-1,"1111011",_xlpm.fer)+IF(OR(WEEKDAY(_xlpm.dfin,2)>5,COUNTIF(_xlpm.fer,_xlpm.dfin)>0),0,MAX(0,MIN(_xlpm.fin-_xlpm.dfin,IF(WEEKDAY(_xlpm.dfin,2)=5,14/24,17.5/24))-8/24)*24),_xlpm.hrs,IF(SCTR_Brokers[[#This Row],[Estado]]="FINALIZADO",MAX(0,_xlpm.hfin-_xlpm.hini),IF(SCTR_Brokers[[#This Row],[Horas_Transcurridas]]="",MAX(0,_xlpm.hfin-_xlpm.hini),SCTR_Brokers[[#This Row],[Horas_Transcurridas]])),IF(_xlpm.hrs<=LISTAS!$E$3,LISTAS!$J$3,LISTAS!$J$4))) -> Dentro | S43: SI | T43: =IF(SCTR_Brokers[[#This Row],[FechaRecepcion]]="","",TEXT(SCTR_Brokers[[#This Row],[FechaRecepcion]],"mmmm")&" "&YEAR(SCTR_Brokers[[#This Row],[FechaRecepcion]])) -> agosto 2026 | U43: =IF(SCTR_Brokers[[#This Row],[Estado]]="FINALIZADO",1,0) -> 1 | V43: =IF(SCTR_Brokers[[#This Row],[FechaRecepcion]]="","",IF(SCTR_Brokers[[#This Row],[Estado]]="FINALIZADO",0,1)) -> 0 | W43: =IF(AND(SCTR_Brokers[[#This Row],[Estado]]="FINALIZADO",SCTR_Brokers[[#This Row],[Plazo]]=LISTAS!$J$3),1,0) -> 1 | X43: =IF(AND(SCTR_Brokers[[#This Row],[Estado]]="FINALIZADO",SCTR_Brokers[[#This Row],[Plazo]]=LISTAS!$J$4),1,0) -> 0 | Y43: =IF(AND(SCTR_Brokers[[#This Row],[Estado]]<>"FINALIZADO",SCTR_Brokers[[#This Row],[Plazo]]=LISTAS!$J$4),1,0) -> 0 | Z43: =IF(SCTR_Brokers[[#This Row],[Fecha_Solic_Informe]]="",0,1) -> 0 | AA43: =IF(SCTR_Brokers[[#This Row],[Fecha_Informe]]="",0,1) -> 0 | AB43: =IF(AND(SCTR_Brokers[[#This Row],[Fecha_Solic_Informe]]<>"",SCTR_Brokers[[#This Row],[Fecha_Informe]]=""),1,0) -> 0 | AC43: =IF(AND(SCTR_Brokers[[#This Row],[Fecha_Solic_Informe]]<>"",SCTR_Brokers[[#This Row],[Fecha_Informe]]<>""),ROUND((SCTR_Brokers[[#This Row],[Fecha_Informe]]-SCTR_Brokers[[#This Row],[Fecha_Solic_Informe]])*24,1),"")
A44: AAQkADdkNThjNzFkLWM0ZmMtNDJhYS04MDVlLTIwNzE4ZDI1Mzg4YgAQAGWEP1Zwf0U7jF6Qf1EmcyA= | C44: =IF(SCTR_Brokers[[#This Row],[FechaRecepcion]]="","",SCTR_Brokers[[#This Row],[ConversationId]]&"-"&TEXT(SCTR_Brokers[[#This Row],[FechaRecepcion]],"aaaammddhhmmss")) -> AAQkADdkNThjNzFkLWM0ZmMtNDJhYS04MDVlLTIwNzE4ZDI1Mzg4YgAQAGWEP1Zwf0U7jF6Qf1EmcyA=-20260818145649 | D44: SIMA PERU // SOLICITUD DE CABESTRIILO // QUIÑONES RONCA ALEXIS VALENTIN | E44: MARSH | F44: 46252.623 | G44: 46252.645 | H44: sctrsalud@mapfre.com.pe | I44: FINALIZADO | K44: SCTR SALUD | N44: =IF(SCTR_Brokers[[#This Row],[FechaRecepcion]]="","",IF(SCTR_Brokers[[#This Row],[Estado]]="FINALIZADO","",IF(SCTR_Brokers[[#This Row],[FechaUltimaRespuesta]]="","",_xlfn.LET(_xlpm.fer,LISTAS!$L$3:$L$100,_xlpm.ep,DATE(2000,1,1),_xlpm.ini,SCTR_Brokers[[#This Row],[FechaUltimaRespuesta]],_xlpm.fin,NOW(),_xlpm.dini,INT(_xlpm.ini),_xlpm.dfin,INT(_xlpm.fin),_xlpm.hini,9.5*NETWORKDAYS.INTL(_xlpm.ep,_xlpm.dini-1,"0000111",_xlpm.fer)+6*NETWORKDAYS.INTL(_xlpm.ep,_xlpm.dini-1,"1111011",_xlpm.fer)+IF(OR(WEEKDAY(_xlpm.dini,2)>5,COUNTIF(_xlpm.fer,_xlpm.dini)>0),0,MAX(0,MIN(_xlpm.ini-_xlpm.dini,IF(WEEKDAY(_xlpm.dini,2)=5,14/24,17.5/24))-8/24)*24),_xlpm.hfin,9.5*NETWORKDAYS.INTL(_xlpm.ep,_xlpm.dfin-1,"0000111",_xlpm.fer)+6*NETWORKDAYS.INTL(_xlpm.ep,_xlpm.dfin-1,"1111011",_xlpm.fer)+IF(OR(WEEKDAY(_xlpm.dfin,2)>5,COUNTIF(_xlpm.fer,_xlpm.dfin)>0),0,MAX(0,MIN(_xlpm.fin-_xlpm.dfin,IF(WEEKDAY(_xlpm.dfin,2)=5,14/24,17.5/24))-8/24)*24),ROUND(MAX(0,_xlpm.hfin-_xlpm.hini),1))))) | Q44: 46252.645 | R44: =IF(SCTR_Brokers[[#This Row],[FechaRecepcion]]="","",_xlfn.LET(_xlpm.fer,LISTAS!$L$3:$L$100,_xlpm.ep,DATE(2000,1,1),_xlpm.ini,SCTR_Brokers[[#This Row],[FechaRecepcion]],_xlpm.fin,IF(SCTR_Brokers[[#This Row],[Fecha_Cierre]]<>"",SCTR_Brokers[[#This Row],[Fecha_Cierre]],NOW()),_xlpm.dini,INT(_xlpm.ini),_xlpm.dfin,INT(_xlpm.fin),_xlpm.hini,9.5*NETWORKDAYS.INTL(_xlpm.ep,_xlpm.dini-1,"0000111",_xlpm.fer)+6*NETWORKDAYS.INTL(_xlpm.ep,_xlpm.dini-1,"1111011",_xlpm.fer)+IF(OR(WEEKDAY(_xlpm.dini,2)>5,COUNTIF(_xlpm.fer,_xlpm.dini)>0),0,MAX(0,MIN(_xlpm.ini-_xlpm.dini,IF(WEEKDAY(_xlpm.dini,2)=5,14/24,17.5/24))-8/24)*24),_xlpm.hfin,9.5*NETWORKDAYS.INTL(_xlpm.ep,_xlpm.dfin-1,"0000111",_xlpm.fer)+6*NETWORKDAYS.INTL(_xlpm.ep,_xlpm.dfin-1,"1111011",_xlpm.fer)+IF(OR(WEEKDAY(_xlpm.dfin,2)>5,COUNTIF(_xlpm.fer,_xlpm.dfin)>0),0,MAX(0,MIN(_xlpm.fin-_xlpm.dfin,IF(WEEKDAY(_xlpm.dfin,2)=5,14/24,17.5/24))-8/24)*24),_xlpm.hrs,IF(SCTR_Brokers[[#This Row],[Estado]]="FINALIZADO",MAX(0,_xlpm.hfin-_xlpm.hini),IF(SCTR_Brokers[[#This Row],[Horas_Transcurridas]]="",MAX(0,_xlpm.hfin-_xlpm.hini),SCTR_Brokers[[#This Row],[Horas_Transcurridas]])),IF(_xlpm.hrs<=LISTAS!$E$3,LISTAS!$J$3,LISTAS!$J$4))) -> Dentro | T44: =IF(SCTR_Brokers[[#This Row],[FechaRecepcion]]="","",TEXT(SCTR_Brokers[[#This Row],[FechaRecepcion]],"mmmm")&" "&YEAR(SCTR_Brokers[[#This Row],[FechaRecepcion]])) -> agosto 2026 | U44: =IF(SCTR_Brokers[[#This Row],[Estado]]="FINALIZADO",1,0) -> 1 | V44: =IF(SCTR_Brokers[[#This Row],[FechaRecepcion]]="","",IF(SCTR_Brokers[[#This Row],[Estado]]="FINALIZADO",0,1)) -> 0 | W44: =IF(AND(SCTR_Brokers[[#This Row],[Estado]]="FINALIZADO",SCTR_Brokers[[#This Row],[Plazo]]=LISTAS!$J$3),1,0) -> 1 | X44: =IF(AND(SCTR_Brokers[[#This Row],[Estado]]="FINALIZADO",SCTR_Brokers[[#This Row],[Plazo]]=LISTAS!$J$4),1,0) -> 0 | Y44: =IF(AND(SCTR_Brokers[[#This Row],[Estado]]<>"FINALIZADO",SCTR_Brokers[[#This Row],[Plazo]]=LISTAS!$J$4),1,0) -> 0 | Z44: =IF(SCTR_Brokers[[#This Row],[Fecha_Solic_Informe]]="",0,1) -> 0 | AA44: =IF(SCTR_Brokers[[#This Row],[Fecha_Informe]]="",0,1) -> 0 | AB44: =IF(AND(SCTR_Brokers[[#This Row],[Fecha_Solic_Informe]]<>"",SCTR_Brokers[[#This Row],[Fecha_Informe]]=""),1,0) -> 0 | AC44: =IF(AND(SCTR_Brokers[[#This Row],[Fecha_Solic_Informe]]<>"",SCTR_Brokers[[#This Row],[Fecha_Informe]]<>""),ROUND((SCTR_Brokers[[#This Row],[Fecha_Informe]]-SCTR_Brokers[[#This Row],[Fecha_Solic_Informe]])*24,1),"")
A45: AAQkADdkNThjNzFkLWM0ZmMtNDJhYS04MDVlLTIwNzE4ZDI1Mzg4YgAQAKzFBRLFTp9Hv4nEDKB77k8= | C45: =IF(SCTR_Brokers[[#This Row],[FechaRecepcion]]="","",SCTR_Brokers[[#This Row],[ConversationId]]&"-"&TEXT(SCTR_Brokers[[#This Row],[FechaRecepcion]],"aaaammddhhmmss")) -> AAQkADdkNThjNzFkLWM0ZmMtNDJhYS04MDVlLTIwNzE4ZDI1Mzg4YgAQAKzFBRLFTp9Hv4nEDKB77k8=-20260818153938 | D45: SCTR -SNACKS - RV: REPORTE DE ACCIDENTE E INCIDENTE: RIOFRIO ABARCA LUIS ALBERTO / VENTAS / CALLAO | E45: MARSH | F45: 46252.653 | G45: 46253.414 | H45: sctrsalud@mapfre.com.pe | I45: FINALIZADO | K45: SCTR SALUD | N45: =IF(SCTR_Brokers[[#This Row],[FechaRecepcion]]="","",IF(SCTR_Brokers[[#This Row],[Estado]]="FINALIZADO","",IF(SCTR_Brokers[[#This Row],[FechaUltimaRespuesta]]="","",_xlfn.LET(_xlpm.fer,LISTAS!$L$3:$L$100,_xlpm.ep,DATE(2000,1,1),_xlpm.ini,SCTR_Brokers[[#This Row],[FechaUltimaRespuesta]],_xlpm.fin,NOW(),_xlpm.dini,INT(_xlpm.ini),_xlpm.dfin,INT(_xlpm.fin),_xlpm.hini,9.5*NETWORKDAYS.INTL(_xlpm.ep,_xlpm.dini-1,"0000111",_xlpm.fer)+6*NETWORKDAYS.INTL(_xlpm.ep,_xlpm.dini-1,"1111011",_xlpm.fer)+IF(OR(WEEKDAY(_xlpm.dini,2)>5,COUNTIF(_xlpm.fer,_xlpm.dini)>0),0,MAX(0,MIN(_xlpm.ini-_xlpm.dini,IF(WEEKDAY(_xlpm.dini,2)=5,14/24,17.5/24))-8/24)*24),_xlpm.hfin,9.5*NETWORKDAYS.INTL(_xlpm.ep,_xlpm.dfin-1,"0000111",_xlpm.fer)+6*NETWORKDAYS.INTL(_xlpm.ep,_xlpm.dfin-1,"1111011",_xlpm.fer)+IF(OR(WEEKDAY(_xlpm.dfin,2)>5,COUNTIF(_xlpm.fer,_xlpm.dfin)>0),0,MAX(0,MIN(_xlpm.fin-_xlpm.dfin,IF(WEEKDAY(_xlpm.dfin,2)=5,14/24,17.5/24))-8/24)*24),ROUND(MAX(0,_xlpm.hfin-_xlpm.hini),1))))) | Q45: 46253.414 | R45: =IF(SCTR_Brokers[[#This Row],[FechaRecepcion]]="","",_xlfn.LET(_xlpm.fer,LISTAS!$L$3:$L$100,_xlpm.ep,DATE(2000,1,1),_xlpm.ini,SCTR_Brokers[[#This Row],[FechaRecepcion]],_xlpm.fin,IF(SCTR_Brokers[[#This Row],[Fecha_Cierre]]<>"",SCTR_Brokers[[#This Row],[Fecha_Cierre]],NOW()),_xlpm.dini,INT(_xlpm.ini),_xlpm.dfin,INT(_xlpm.fin),_xlpm.hini,9.5*NETWORKDAYS.INTL(_xlpm.ep,_xlpm.dini-1,"0000111",_xlpm.fer)+6*NETWORKDAYS.INTL(_xlpm.ep,_xlpm.dini-1,"1111011",_xlpm.fer)+IF(OR(WEEKDAY(_xlpm.dini,2)>5,COUNTIF(_xlpm.fer,_xlpm.dini)>0),0,MAX(0,MIN(_xlpm.ini-_xlpm.dini,IF(WEEKDAY(_xlpm.dini,2)=5,14/24,17.5/24))-8/24)*24),_xlpm.hfin,9.5*NETWORKDAYS.INTL(_xlpm.ep,_xlpm.dfin-1,"0000111",_xlpm.fer)+6*NETWORKDAYS.INTL(_xlpm.ep,_xlpm.dfin-1,"1111011",_xlpm.fer)+IF(OR(WEEKDAY(_xlpm.dfin,2)>5,COUNTIF(_xlpm.fer,_xlpm.dfin)>0),0,MAX(0,MIN(_xlpm.fin-_xlpm.dfin,IF(WEEKDAY(_xlpm.dfin,2)=5,14/24,17.5/24))-8/24)*24),_xlpm.hrs,IF(SCTR_Brokers[[#This Row],[Estado]]="FINALIZADO",MAX(0,_xlpm.hfin-_xlpm.hini),IF(SCTR_Brokers[[#This Row],[Horas_Transcurridas]]="",MAX(0,_xlpm.hfin-_xlpm.hini),SCTR_Brokers[[#This Row],[Horas_Transcurridas]])),IF(_xlpm.hrs<=LISTAS!$E$3,LISTAS!$J$3,LISTAS!$J$4))) -> Dentro | T45: =IF(SCTR_Brokers[[#This Row],[FechaRecepcion]]="","",TEXT(SCTR_Brokers[[#This Row],[FechaRecepcion]],"mmmm")&" "&YEAR(SCTR_Brokers[[#This Row],[FechaRecepcion]])) -> agosto 2026 | U45: =IF(SCTR_Brokers[[#This Row],[Estado]]="FINALIZADO",1,0) -> 1 | V45: =IF(SCTR_Brokers[[#This Row],[FechaRecepcion]]="","",IF(SCTR_Brokers[[#This Row],[Estado]]="FINALIZADO",0,1)) -> 0 | W45: =IF(AND(SCTR_Brokers[[#This Row],[Estado]]="FINALIZADO",SCTR_Brokers[[#This Row],[Plazo]]=LISTAS!$J$3),1,0) -> 1 | X45: =IF(AND(SCTR_Brokers[[#This Row],[Estado]]="FINALIZADO",SCTR_Brokers[[#This Row],[Plazo]]=LISTAS!$J$4),1,0) -> 0 | Y45: =IF(AND(SCTR_Brokers[[#This Row],[Estado]]<>"FINALIZADO",SCTR_Brokers[[#This Row],[Plazo]]=LISTAS!$J$4),1,0) -> 0 | Z45: =IF(SCTR_Brokers[[#This Row],[Fecha_Solic_Informe]]="",0,1) -> 0 | AA45: =IF(SCTR_Brokers[[#This Row],[Fecha_Informe]]="",0,1) -> 0 | AB45: =IF(AND(SCTR_Brokers[[#This Row],[Fecha_Solic_Informe]]<>"",SCTR_Brokers[[#This Row],[Fecha_Informe]]=""),1,0) -> 0 | AC45: =IF(AND(SCTR_Brokers[[#This Row],[Fecha_Solic_Informe]]<>"",SCTR_Brokers[[#This Row],[Fecha_Informe]]<>""),ROUND((SCTR_Brokers[[#This Row],[Fecha_Informe]]-SCTR_Brokers[[#This Row],[Fecha_Solic_Informe]])*24,1),"")
A46: AAQkADdkNThjNzFkLWM0ZmMtNDJhYS04MDVlLTIwNzE4ZDI1Mzg4YgAQAFHyOYkqvY9Nqu2tOgis9Mo= | C46: =IF(SCTR_Brokers[[#This Row],[FechaRecepcion]]="","",SCTR_Brokers[[#This Row],[ConversationId]]&"-"&TEXT(SCTR_Brokers[[#This Row],[FechaRecepcion]],"aaaammddhhmmss")) -> AAQkADdkNThjNzFkLWM0ZmMtNDJhYS04MDVlLTIwNzE4ZDI1Mzg4YgAQAFHyOYkqvY9Nqu2tOgis9Mo=-20260818164904 | D46: RE: NOTIFICACION SCTR SALUD - Solicitud de desactivación de SCTR: HOCES COLLAZOS, DANNY ALEXANDER - MAERSK | E46: MARSH | F46: 46252.701 | G46: 46252.701 | H46: William.Garcia@marsh.com | I46: FINALIZADO | K46: SCTR SALUD | N46: =IF(SCTR_Brokers[[#This Row],[FechaRecepcion]]="","",IF(SCTR_Brokers[[#This Row],[Estado]]="FINALIZADO","",IF(SCTR_Brokers[[#This Row],[FechaUltimaRespuesta]]="","",_xlfn.LET(_xlpm.fer,LISTAS!$L$3:$L$100,_xlpm.ep,DATE(2000,1,1),_xlpm.ini,SCTR_Brokers[[#This Row],[FechaUltimaRespuesta]],_xlpm.fin,NOW(),_xlpm.dini,INT(_xlpm.ini),_xlpm.dfin,INT(_xlpm.fin),_xlpm.hini,9.5*NETWORKDAYS.INTL(_xlpm.ep,_xlpm.dini-1,"0000111",_xlpm.fer)+6*NETWORKDAYS.INTL(_xlpm.ep,_xlpm.dini-1,"1111011",_xlpm.fer)+IF(OR(WEEKDAY(_xlpm.dini,2)>5,COUNTIF(_xlpm.fer,_xlpm.dini)>0),0,MAX(0,MIN(_xlpm.ini-_xlpm.dini,IF(WEEKDAY(_xlpm.dini,2)=5,14/24,17.5/24))-8/24)*24),_xlpm.hfin,9.5*NETWORKDAYS.INTL(_xlpm.ep,_xlpm.dfin-1,"0000111",_xlpm.fer)+6*NETWORKDAYS.INTL(_xlpm.ep,_xlpm.dfin-1,"1111011",_xlpm.fer)+IF(OR(WEEKDAY(_xlpm.dfin,2)>5,COUNTIF(_xlpm.fer,_xlpm.dfin)>0),0,MAX(0,MIN(_xlpm.fin-_xlpm.dfin,IF(WEEKDAY(_xlpm.dfin,2)=5,14/24,17.5/24))-8/24)*24),ROUND(MAX(0,_xlpm.hfin-_xlpm.hini),1))))) | Q46: 46253.751 | R46: =IF(SCTR_Brokers[[#This Row],[FechaRecepcion]]="","",_xlfn.LET(_xlpm.fer,LISTAS!$L$3:$L$100,_xlpm.ep,DATE(2000,1,1),_xlpm.ini,SCTR_Brokers[[#This Row],[FechaRecepcion]],_xlpm.fin,IF(SCTR_Brokers[[#This Row],[Fecha_Cierre]]<>"",SCTR_Brokers[[#This Row],[Fecha_Cierre]],NOW()),_xlpm.dini,INT(_xlpm.ini),_xlpm.dfin,INT(_xlpm.fin),_xlpm.hini,9.5*NETWORKDAYS.INTL(_xlpm.ep,_xlpm.dini-1,"0000111",_xlpm.fer)+6*NETWORKDAYS.INTL(_xlpm.ep,_xlpm.dini-1,"1111011",_xlpm.fer)+IF(OR(WEEKDAY(_xlpm.dini,2)>5,COUNTIF(_xlpm.fer,_xlpm.dini)>0),0,MAX(0,MIN(_xlpm.ini-_xlpm.dini,IF(WEEKDAY(_xlpm.dini,2)=5,14/24,17.5/24))-8/24)*24),_xlpm.hfin,9.5*NETWORKDAYS.INTL(_xlpm.ep,_xlpm.dfin-1,"0000111",_xlpm.fer)+6*NETWORKDAYS.INTL(_xlpm.ep,_xlpm.dfin-1,"1111011",_xlpm.fer)+IF(OR(WEEKDAY(_xlpm.dfin,2)>5,COUNTIF(_xlpm.fer,_xlpm.dfin)>0),0,MAX(0,MIN(_xlpm.fin-_xlpm.dfin,IF(WEEKDAY(_xlpm.dfin,2)=5,14/24,17.5/24))-8/24)*24),_xlpm.hrs,IF(SCTR_Brokers[[#This Row],[Estado]]="FINALIZADO",MAX(0,_xlpm.hfin-_xlpm.hini),IF(SCTR_Brokers[[#This Row],[Horas_Transcurridas]]="",MAX(0,_xlpm.hfin-_xlpm.hini),SCTR_Brokers[[#This Row],[Horas_Transcurridas]])),IF(_xlpm.hrs<=LISTAS!$E$3,LISTAS!$J$3,LISTAS!$J$4))) -> Fuera | T46: =IF(SCTR_Brokers[[#This Row],[FechaRecepcion]]="","",TEXT(SCTR_Brokers[[#This Row],[FechaRecepcion]],"mmmm")&" "&YEAR(SCTR_Brokers[[#This Row],[FechaRecepcion]])) -> agosto 2026 | U46: =IF(SCTR_Brokers[[#This Row],[Estado]]="FINALIZADO",1,0) -> 1 | V46: =IF(SCTR_Brokers[[#This Row],[FechaRecepcion]]="","",IF(SCTR_Brokers[[#This Row],[Estado]]="FINALIZADO",0,1)) -> 0 | W46: =IF(AND(SCTR_Brokers[[#This Row],[Estado]]="FINALIZADO",SCTR_Brokers[[#This Row],[Plazo]]=LISTAS!$J$3),1,0) -> 0 | X46: =IF(AND(SCTR_Brokers[[#This Row],[Estado]]="FINALIZADO",SCTR_Brokers[[#This Row],[Plazo]]=LISTAS!$J$4),1,0) -> 1 | Y46: =IF(AND(SCTR_Brokers[[#This Row],[Estado]]<>"FINALIZADO",SCTR_Brokers[[#This Row],[Plazo]]=LISTAS!$J$4),1,0) -> 0 | Z46: =IF(SCTR_Brokers[[#This Row],[Fecha_Solic_Informe]]="",0,1) -> 0 | AA46: =IF(SCTR_Brokers[[#This Row],[Fecha_Informe]]="",0,1) -> 0 | AB46: =IF(AND(SCTR_Brokers[[#This Row],[Fecha_Solic_Informe]]<>"",SCTR_Brokers[[#This Row],[Fecha_Informe]]=""),1,0) -> 0 | AC46: =IF(AND(SCTR_Brokers[[#This Row],[Fecha_Solic_Informe]]<>"",SCTR_Brokers[[#This Row],[Fecha_Informe]]<>""),ROUND((SCTR_Brokers[[#This Row],[Fecha_Informe]]-SCTR_Brokers[[#This Row],[Fecha_Solic_Informe]])*24,1),"")
A47: AAQkADdkNThjNzFkLWM0ZmMtNDJhYS04MDVlLTIwNzE4ZDI1Mzg4YgAQAMR9p1oZsUwdunasYyVc6U4= | C47: =IF(SCTR_Brokers[[#This Row],[FechaRecepcion]]="","",SCTR_Brokers[[#This Row],[ConversationId]]&"-"&TEXT(SCTR_Brokers[[#This Row],[FechaRecepcion]],"aaaammddhhmmss")) -> AAQkADdkNThjNzFkLWM0ZmMtNDJhYS04MDVlLTIwNzE4ZDI1Mzg4YgAQAMR9p1oZsUwdunasYyVc6U4=-20260818174722 | D47: EMERGENT COLD PERU : Carta de garantía: Caso de colaborador Alvino Osorio Jairo Luis | E47: MARSH | F47: 46252.741 | G47: 46252.741 | H47: Katherine.Andrade@marsh.com | I47: FINALIZADO | K47: SCTR SALUD | N47: =IF(SCTR_Brokers[[#This Row],[FechaRecepcion]]="","",IF(SCTR_Brokers[[#This Row],[Estado]]="FINALIZADO","",IF(SCTR_Brokers[[#This Row],[FechaUltimaRespuesta]]="","",_xlfn.LET(_xlpm.fer,LISTAS!$L$3:$L$100,_xlpm.ep,DATE(2000,1,1),_xlpm.ini,SCTR_Brokers[[#This Row],[FechaUltimaRespuesta]],_xlpm.fin,NOW(),_xlpm.dini,INT(_xlpm.ini),_xlpm.dfin,INT(_xlpm.fin),_xlpm.hini,9.5*NETWORKDAYS.INTL(_xlpm.ep,_xlpm.dini-1,"0000111",_xlpm.fer)+6*NETWORKDAYS.INTL(_xlpm.ep,_xlpm.dini-1,"1111011",_xlpm.fer)+IF(OR(WEEKDAY(_xlpm.dini,2)>5,COUNTIF(_xlpm.fer,_xlpm.dini)>0),0,MAX(0,MIN(_xlpm.ini-_xlpm.dini,IF(WEEKDAY(_xlpm.dini,2)=5,14/24,17.5/24))-8/24)*24),_xlpm.hfin,9.5*NETWORKDAYS.INTL(_xlpm.ep,_xlpm.dfin-1,"0000111",_xlpm.fer)+6*NETWORKDAYS.INTL(_xlpm.ep,_xlpm.dfin-1,"1111011",_xlpm.fer)+IF(OR(WEEKDAY(_xlpm.dfin,2)>5,COUNTIF(_xlpm.fer,_xlpm.dfin)>0),0,MAX(0,MIN(_xlpm.fin-_xlpm.dfin,IF(WEEKDAY(_xlpm.dfin,2)=5,14/24,17.5/24))-8/24)*24),ROUND(MAX(0,_xlpm.hfin-_xlpm.hini),1))))) | Q47: 46252.753 | R47: =IF(SCTR_Brokers[[#This Row],[FechaRecepcion]]="","",_xlfn.LET(_xlpm.fer,LISTAS!$L$3:$L$100,_xlpm.ep,DATE(2000,1,1),_xlpm.ini,SCTR_Brokers[[#This Row],[FechaRecepcion]],_xlpm.fin,IF(SCTR_Brokers[[#This Row],[Fecha_Cierre]]<>"",SCTR_Brokers[[#This Row],[Fecha_Cierre]],NOW()),_xlpm.dini,INT(_xlpm.ini),_xlpm.dfin,INT(_xlpm.fin),_xlpm.hini,9.5*NETWORKDAYS.INTL(_xlpm.ep,_xlpm.dini-1,"0000111",_xlpm.fer)+6*NETWORKDAYS.INTL(_xlpm.ep,_xlpm.dini-1,"1111011",_xlpm.fer)+IF(OR(WEEKDAY(_xlpm.dini,2)>5,COUNTIF(_xlpm.fer,_xlpm.dini)>0),0,MAX(0,MIN(_xlpm.ini-_xlpm.dini,IF(WEEKDAY(_xlpm.dini,2)=5,14/24,17.5/24))-8/24)*24),_xlpm.hfin,9.5*NETWORKDAYS.INTL(_xlpm.ep,_xlpm.dfin-1,"0000111",_xlpm.fer)+6*NETWORKDAYS.INTL(_xlpm.ep,_xlpm.dfin-1,"1111011",_xlpm.fer)+IF(OR(WEEKDAY(_xlpm.dfin,2)>5,COUNTIF(_xlpm.fer,_xlpm.dfin)>0),0,MAX(0,MIN(_xlpm.fin-_xlpm.dfin,IF(WEEKDAY(_xlpm.dfin,2)=5,14/24,17.5/24))-8/24)*24),_xlpm.hrs,IF(SCTR_Brokers[[#This Row],[Estado]]="FINALIZADO",MAX(0,_xlpm.hfin-_xlpm.hini),IF(SCTR_Brokers[[#This Row],[Horas_Transcurridas]]="",MAX(0,_xlpm.hfin-_xlpm.hini),SCTR_Brokers[[#This Row],[Horas_Transcurridas]])),IF(_xlpm.hrs<=LISTAS!$E$3,LISTAS!$J$3,LISTAS!$J$4))) -> Dentro | T47: =IF(SCTR_Brokers[[#This Row],[FechaRecepcion]]="","",TEXT(SCTR_Brokers[[#This Row],[FechaRecepcion]],"mmmm")&" "&YEAR(SCTR_Brokers[[#This Row],[FechaRecepcion]])) -> agosto 2026 | U47: =IF(SCTR_Brokers[[#This Row],[Estado]]="FINALIZADO",1,0) -> 1 | V47: =IF(SCTR_Brokers[[#This Row],[FechaRecepcion]]="","",IF(SCTR_Brokers[[#This Row],[Estado]]="FINALIZADO",0,1)) -> 0 | W47: =IF(AND(SCTR_Brokers[[#This Row],[Estado]]="FINALIZADO",SCTR_Brokers[[#This Row],[Plazo]]=LISTAS!$J$3),1,0) -> 1 | X47: =IF(AND(SCTR_Brokers[[#This Row],[Estado]]="FINALIZADO",SCTR_Brokers[[#This Row],[Plazo]]=LISTAS!$J$4),1,0) -> 0 | Y47: =IF(AND(SCTR_Brokers[[#This Row],[Estado]]<>"FINALIZADO",SCTR_Brokers[[#This Row],[Plazo]]=LISTAS!$J$4),1,0) -> 0 | Z47: =IF(SCTR_Brokers[[#This Row],[Fecha_Solic_Informe]]="",0,1) -> 0 | AA47: =IF(SCTR_Brokers[[#This Row],[Fecha_Informe]]="",0,1) -> 0 | AB47: =IF(AND(SCTR_Brokers[[#This Row],[Fecha_Solic_Informe]]<>"",SCTR_Brokers[[#This Row],[Fecha_Informe]]=""),1,0) -> 0 | AC47: =IF(AND(SCTR_Brokers[[#This Row],[Fecha_Solic_Informe]]<>"",SCTR_Brokers[[#This Row],[Fecha_Informe]]<>""),ROUND((SCTR_Brokers[[#This Row],[Fecha_Informe]]-SCTR_Brokers[[#This Row],[Fecha_Solic_Informe]])*24,1),"")
A48: AAQkADdkNThjNzFkLWM0ZmMtNDJhYS04MDVlLTIwNzE4ZDI1Mzg4YgAQALLK7MWxQEmCvxHKC-OI7y4= | C48: =IF(SCTR_Brokers[[#This Row],[FechaRecepcion]]="","",SCTR_Brokers[[#This Row],[ConversationId]]&"-"&TEXT(SCTR_Brokers[[#This Row],[FechaRecepcion]],"aaaammddhhmmss")) -> AAQkADdkNThjNzFkLWM0ZmMtNDJhYS04MDVlLTIwNzE4ZDI1Mzg4YgAQALLK7MWxQEmCvxHKC-OI7y4=-20260818195352 | D48: CARTA DE GARANTIA_ASEG. LURDES CAMAN CHAVEZ DNI 48448559 _CORPORACION TURISTICA PERUANA S.A.C. RUC 20265815830 | E48: GABEL | F48: 46252.829 | G48: 46253.452 | H48: LKCALD1@mapfre.com.pe | I48: FINALIZADO | J48: | CERRADO POR RESPUESTA DE LKCALD1@mapfre.com.pe | K48: AUDITORIA MÉDICA | L48: Buenos días,_x000D_ _x000D_ Dra., por favor su apoyo evaluando si tiene cobertura procedimientos solicitados._x000D_ _x000D_ @Calderon Ugarte, Liseth Katherine favor de informar a clínica según respuesta de la doctora._x000D_ _x000D_ _x000D_ Saludos,_x000D_ _x000D_ _x000D_ _x000D_ Alicia Sancca Medina_x000D_ _x000D_ Área de SCTR Sa | M48: DRA ANA | N48: =IF(SCTR_Brokers[[#This Row],[FechaRecepcion]]="","",IF(SCTR_Brokers[[#This Row],[Estado]]="FINALIZADO","",IF(SCTR_Brokers[[#This Row],[FechaUltimaRespuesta]]="","",_xlfn.LET(_xlpm.fer,LISTAS!$L$3:$L$100,_xlpm.ep,DATE(2000,1,1),_xlpm.ini,SCTR_Brokers[[#This Row],[FechaUltimaRespuesta]],_xlpm.fin,NOW(),_xlpm.dini,INT(_xlpm.ini),_xlpm.dfin,INT(_xlpm.fin),_xlpm.hini,9.5*NETWORKDAYS.INTL(_xlpm.ep,_xlpm.dini-1,"0000111",_xlpm.fer)+6*NETWORKDAYS.INTL(_xlpm.ep,_xlpm.dini-1,"1111011",_xlpm.fer)+IF(OR(WEEKDAY(_xlpm.dini,2)>5,COUNTIF(_xlpm.fer,_xlpm.dini)>0),0,MAX(0,MIN(_xlpm.ini-_xlpm.dini,IF(WEEKDAY(_xlpm.dini,2)=5,14/24,17.5/24))-8/24)*24),_xlpm.hfin,9.5*NETWORKDAYS.INTL(_xlpm.ep,_xlpm.dfin-1,"0000111",_xlpm.fer)+6*NETWORKDAYS.INTL(_xlpm.ep,_xlpm.dfin-1,"1111011",_xlpm.fer)+IF(OR(WEEKDAY(_xlpm.dfin,2)>5,COUNTIF(_xlpm.fer,_xlpm.dfin)>0),0,MAX(0,MIN(_xlpm.fin-_xlpm.dfin,IF(WEEKDAY(_xlpm.dfin,2)=5,14/24,17.5/24))-8/24)*24),ROUND(MAX(0,_xlpm.hfin-_xlpm.hini),1))))) | O48: 46253.421 | Q48: 46253.452 | R48: =IF(SCTR_Brokers[[#This Row],[FechaRecepcion]]="","",_xlfn.LET(_xlpm.fer,LISTAS!$L$3:$L$100,_xlpm.ep,DATE(2000,1,1),_xlpm.ini,SCTR_Brokers[[#This Row],[FechaRecepcion]],_xlpm.fin,IF(SCTR_Brokers[[#This Row],[Fecha_Cierre]]<>"",SCTR_Brokers[[#This Row],[Fecha_Cierre]],NOW()),_xlpm.dini,INT(_xlpm.ini),_xlpm.dfin,INT(_xlpm.fin),_xlpm.hini,9.5*NETWORKDAYS.INTL(_xlpm.ep,_xlpm.dini-1,"0000111",_xlpm.fer)+6*NETWORKDAYS.INTL(_xlpm.ep,_xlpm.dini-1,"1111011",_xlpm.fer)+IF(OR(WEEKDAY(_xlpm.dini,2)>5,COUNTIF(_xlpm.fer,_xlpm.dini)>0),0,MAX(0,MIN(_xlpm.ini-_xlpm.dini,IF(WEEKDAY(_xlpm.dini,2)=5,14/24,17.5/24))-8/24)*24),_xlpm.hfin,9.5*NETWORKDAYS.INTL(_xlpm.ep,_xlpm.dfin-1,"0000111",_xlpm.fer)+6*NETWORKDAYS.INTL(_xlpm.ep,_xlpm.dfin-1,"1111011",_xlpm.fer)+IF(OR(WEEKDAY(_xlpm.dfin,2)>5,COUNTIF(_xlpm.fer,_xlpm.dfin)>0),0,MAX(0,MIN(_xlpm.fin-_xlpm.dfin,IF(WEEKDAY(_xlpm.dfin,2)=5,14/24,17.5/24))-8/24)*24),_xlpm.hrs,IF(SCTR_Brokers[[#This Row],[Estado]]="FINALIZADO",MAX(0,_xlpm.hfin-_xlpm.hini),IF(SCTR_Brokers[[#This Row],[Horas_Transcurridas]]="",MAX(0,_xlpm.hfin-_xlpm.hini),SCTR_Brokers[[#This Row],[Horas_Transcurridas]])),IF(_xlpm.hrs<=LISTAS!$E$3,LISTAS!$J$3,LISTAS!$J$4))) -> Dentro | T48: =IF(SCTR_Brokers[[#This Row],[FechaRecepcion]]="","",TEXT(SCTR_Brokers[[#This Row],[FechaRecepcion]],"mmmm")&" "&YEAR(SCTR_Brokers[[#This Row],[FechaRecepcion]])) -> agosto 2026 | U48: =IF(SCTR_Brokers[[#This Row],[Estado]]="FINALIZADO",1,0) -> 1 | V48: =IF(SCTR_Brokers[[#This Row],[FechaRecepcion]]="","",IF(SCTR_Brokers[[#This Row],[Estado]]="FINALIZADO",0,1)) -> 0 | W48: =IF(AND(SCTR_Brokers[[#This Row],[Estado]]="FINALIZADO",SCTR_Brokers[[#This Row],[Plazo]]=LISTAS!$J$3),1,0) -> 1 | X48: =IF(AND(SCTR_Brokers[[#This Row],[Estado]]="FINALIZADO",SCTR_Brokers[[#This Row],[Plazo]]=LISTAS!$J$4),1,0) -> 0 | Y48: =IF(AND(SCTR_Brokers[[#This Row],[Estado]]<>"FINALIZADO",SCTR_Brokers[[#This Row],[Plazo]]=LISTAS!$J$4),1,0) -> 0 | Z48: =IF(SCTR_Brokers[[#This Row],[Fecha_Solic_Informe]]="",0,1) -> 1 | AA48: =IF(SCTR_Brokers[[#This Row],[Fecha_Informe]]="",0,1) -> 0 | AB48: =IF(AND(SCTR_Brokers[[#This Row],[Fecha_Solic_Informe]]<>"",SCTR_Brokers[[#This Row],[Fecha_Informe]]=""),1,0) -> 1 | AC48: =IF(AND(SCTR_Brokers[[#This Row],[Fecha_Solic_Informe]]<>"",SCTR_Brokers[[#This Row],[Fecha_Informe]]<>""),ROUND((SCTR_Brokers[[#This Row],[Fecha_Informe]]-SCTR_Brokers[[#This Row],[Fecha_Solic_Informe]])*24,1),"")
A49: AAQkADdkNThjNzFkLWM0ZmMtNDJhYS04MDVlLTIwNzE4ZDI1Mzg4YgAQAAeLqbz90KpLvLqMB-j0Cuk= | C49: =IF(SCTR_Brokers[[#This Row],[FechaRecepcion]]="","",SCTR_Brokers[[#This Row],[ConversationId]]&"-"&TEXT(SCTR_Brokers[[#This Row],[FechaRecepcion]],"aaaammddhhmmss")) -> AAQkADdkNThjNzFkLWM0ZmMtNDJhYS04MDVlLTIwNzE4ZDI1Mzg4YgAQAAeLqbz90KpLvLqMB-j0Cuk=-20260819084809 | D49: RE: **URGENTE**PATRIMONIO EN FIDEICOMISO - SCTR SALUD MAPFRE - RODRIGUEZ YCOMENA ALDEN - CARTA DE GARANTIA OBSERVADA. | E49: ARTHUR GALLAGHER | F49: 46253.367 | G49: 46253.431 | H49: sctrsalud@mapfre.com.pe | I49: FINALIZADO | J49: | DERIVADO 20/08/2026 12:00 | K49: AUDITORIA MÉDICA | L49: Buenos días,_x000D_ _x000D_ Hola Dra., su apoyo elaborando el informe de rechazo del presente siniestro._x000D_ _x000D_ _x000D_ Saludos,_x000D_ _x000D_ _x000D_ _x000D_ Alicia Sancca Medina_x000D_ _x000D_ Área de SCTR Salud_x000D_ _x000D_ Siniestros y Prestaciones_x000D_ _x000D_ Mapfre Perú_x000D_ _x000D_ Av. Armendáriz 345, Miraflores._x000D_ _x000D_ _x000D_ _x000D_ #CuidamosLoQ | N49: =IF(SCTR_Brokers[[#This Row],[FechaRecepcion]]="","",IF(SCTR_Brokers[[#This Row],[Estado]]="FINALIZADO","",IF(SCTR_Brokers[[#This Row],[FechaUltimaRespuesta]]="","",_xlfn.LET(_xlpm.fer,LISTAS!$L$3:$L$100,_xlpm.ep,DATE(2000,1,1),_xlpm.ini,SCTR_Brokers[[#This Row],[FechaUltimaRespuesta]],_xlpm.fin,NOW(),_xlpm.dini,INT(_xlpm.ini),_xlpm.dfin,INT(_xlpm.fin),_xlpm.hini,9.5*NETWORKDAYS.INTL(_xlpm.ep,_xlpm.dini-1,"0000111",_xlpm.fer)+6*NETWORKDAYS.INTL(_xlpm.ep,_xlpm.dini-1,"1111011",_xlpm.fer)+IF(OR(WEEKDAY(_xlpm.dini,2)>5,COUNTIF(_xlpm.fer,_xlpm.dini)>0),0,MAX(0,MIN(_xlpm.ini-_xlpm.dini,IF(WEEKDAY(_xlpm.dini,2)=5,14/24,17.5/24))-8/24)*24),_xlpm.hfin,9.5*NETWORKDAYS.INTL(_xlpm.ep,_xlpm.dfin-1,"0000111",_xlpm.fer)+6*NETWORKDAYS.INTL(_xlpm.ep,_xlpm.dfin-1,"1111011",_xlpm.fer)+IF(OR(WEEKDAY(_xlpm.dfin,2)>5,COUNTIF(_xlpm.fer,_xlpm.dfin)>0),0,MAX(0,MIN(_xlpm.fin-_xlpm.dfin,IF(WEEKDAY(_xlpm.dfin,2)=5,14/24,17.5/24))-8/24)*24),ROUND(MAX(0,_xlpm.hfin-_xlpm.hini),1))))) | O49: 46253.431 | Q49: 46253.431 | R49: =IF(SCTR_Brokers[[#This Row],[FechaRecepcion]]="","",_xlfn.LET(_xlpm.fer,LISTAS!$L$3:$L$100,_xlpm.ep,DATE(2000,1,1),_xlpm.ini,SCTR_Brokers[[#This Row],[FechaRecepcion]],_xlpm.fin,IF(SCTR_Brokers[[#This Row],[Fecha_Cierre]]<>"",SCTR_Brokers[[#This Row],[Fecha_Cierre]],NOW()),_xlpm.dini,INT(_xlpm.ini),_xlpm.dfin,INT(_xlpm.fin),_xlpm.hini,9.5*NETWORKDAYS.INTL(_xlpm.ep,_xlpm.dini-1,"0000111",_xlpm.fer)+6*NETWORKDAYS.INTL(_xlpm.ep,_xlpm.dini-1,"1111011",_xlpm.fer)+IF(OR(WEEKDAY(_xlpm.dini,2)>5,COUNTIF(_xlpm.fer,_xlpm.dini)>0),0,MAX(0,MIN(_xlpm.ini-_xlpm.dini,IF(WEEKDAY(_xlpm.dini,2)=5,14/24,17.5/24))-8/24)*24),_xlpm.hfin,9.5*NETWORKDAYS.INTL(_xlpm.ep,_xlpm.dfin-1,"0000111",_xlpm.fer)+6*NETWORKDAYS.INTL(_xlpm.ep,_xlpm.dfin-1,"1111011",_xlpm.fer)+IF(OR(WEEKDAY(_xlpm.dfin,2)>5,COUNTIF(_xlpm.fer,_xlpm.dfin)>0),0,MAX(0,MIN(_xlpm.fin-_xlpm.dfin,IF(WEEKDAY(_xlpm.dfin,2)=5,14/24,17.5/24))-8/24)*24),_xlpm.hrs,IF(SCTR_Brokers[[#This Row],[Estado]]="FINALIZADO",MAX(0,_xlpm.hfin-_xlpm.hini),IF(SCTR_Brokers[[#This Row],[Horas_Transcurridas]]="",MAX(0,_xlpm.hfin-_xlpm.hini),SCTR_Brokers[[#This Row],[Horas_Transcurridas]])),IF(_xlpm.hrs<=LISTAS!$E$3,LISTAS!$J$3,LISTAS!$J$4))) -> Dentro | S49: SI | T49: =IF(SCTR_Brokers[[#This Row],[FechaRecepcion]]="","",TEXT(SCTR_Brokers[[#This Row],[FechaRecepcion]],"mmmm")&" "&YEAR(SCTR_Brokers[[#This Row],[FechaRecepcion]])) -> agosto 2026 | U49: =IF(SCTR_Brokers[[#This Row],[Estado]]="FINALIZADO",1,0) -> 1 | V49: =IF(SCTR_Brokers[[#This Row],[FechaRecepcion]]="","",IF(SCTR_Brokers[[#This Row],[Estado]]="FINALIZADO",0,1)) -> 0 | W49: =IF(AND(SCTR_Brokers[[#This Row],[Estado]]="FINALIZADO",SCTR_Brokers[[#This Row],[Plazo]]=LISTAS!$J$3),1,0) -> 1 | X49: =IF(AND(SCTR_Brokers[[#This Row],[Estado]]="FINALIZADO",SCTR_Brokers[[#This Row],[Plazo]]=LISTAS!$J$4),1,0) -> 0 | Y49: =IF(AND(SCTR_Brokers[[#This Row],[Estado]]<>"FINALIZADO",SCTR_Brokers[[#This Row],[Plazo]]=LISTAS!$J$4),1,0) -> 0 | Z49: =IF(SCTR_Brokers[[#This Row],[Fecha_Solic_Informe]]="",0,1) -> 1 | AA49: =IF(SCTR_Brokers[[#This Row],[Fecha_Informe]]="",0,1) -> 0 | AB49: =IF(AND(SCTR_Brokers[[#This Row],[Fecha_Solic_Informe]]<>"",SCTR_Brokers[[#This Row],[Fecha_Informe]]=""),1,0) -> 1 | AC49: =IF(AND(SCTR_Brokers[[#This Row],[Fecha_Solic_Informe]]<>"",SCTR_Brokers[[#This Row],[Fecha_Informe]]<>""),ROUND((SCTR_Brokers[[#This Row],[Fecha_Informe]]-SCTR_Brokers[[#This Row],[Fecha_Solic_Informe]])*24,1),"")
A50: AAQkADdkNThjNzFkLWM0ZmMtNDJhYS04MDVlLTIwNzE4ZDI1Mzg4YgAQAKzFBRLFTp9Hv4nEDKB77k8= | C50: =IF(SCTR_Brokers[[#This Row],[FechaRecepcion]]="","",SCTR_Brokers[[#This Row],[ConversationId]]&"-"&TEXT(SCTR_Brokers[[#This Row],[FechaRecepcion]],"aaaammddhhmmss")) -> AAQkADdkNThjNzFkLWM0ZmMtNDJhYS04MDVlLTIwNzE4ZDI1Mzg4YgAQAKzFBRLFTp9Hv4nEDKB77k8=-20260819114004 | D50: RE: SCTR -SNACKS - RV: REPORTE DE ACCIDENTE E INCIDENTE: RIOFRIO ABARCA LUIS ALBERTO / VENTAS / CALLAO | E50: MARSH | F50: 46253.486 | G50: 46253.506 | H50: BATHER1@mapfre.com.pe | I50: FINALIZADO | J50: | CERRADO POR RESPUESTA DE BATHER1@mapfre.com.pe | K50: SCTR SALUD | N50: =IF(SCTR_Brokers[[#This Row],[FechaRecepcion]]="","",IF(SCTR_Brokers[[#This Row],[Estado]]="FINALIZADO","",IF(SCTR_Brokers[[#This Row],[FechaUltimaRespuesta]]="","",_xlfn.LET(_xlpm.fer,LISTAS!$L$3:$L$100,_xlpm.ep,DATE(2000,1,1),_xlpm.ini,SCTR_Brokers[[#This Row],[FechaUltimaRespuesta]],_xlpm.fin,NOW(),_xlpm.dini,INT(_xlpm.ini),_xlpm.dfin,INT(_xlpm.fin),_xlpm.hini,9.5*NETWORKDAYS.INTL(_xlpm.ep,_xlpm.dini-1,"0000111",_xlpm.fer)+6*NETWORKDAYS.INTL(_xlpm.ep,_xlpm.dini-1,"1111011",_xlpm.fer)+IF(OR(WEEKDAY(_xlpm.dini,2)>5,COUNTIF(_xlpm.fer,_xlpm.dini)>0),0,MAX(0,MIN(_xlpm.ini-_xlpm.dini,IF(WEEKDAY(_xlpm.dini,2)=5,14/24,17.5/24))-8/24)*24),_xlpm.hfin,9.5*NETWORKDAYS.INTL(_xlpm.ep,_xlpm.dfin-1,"0000111",_xlpm.fer)+6*NETWORKDAYS.INTL(_xlpm.ep,_xlpm.dfin-1,"1111011",_xlpm.fer)+IF(OR(WEEKDAY(_xlpm.dfin,2)>5,COUNTIF(_xlpm.fer,_xlpm.dfin)>0),0,MAX(0,MIN(_xlpm.fin-_xlpm.dfin,IF(WEEKDAY(_xlpm.dfin,2)=5,14/24,17.5/24))-8/24)*24),ROUND(MAX(0,_xlpm.hfin-_xlpm.hini),1))))) | Q50: 46253.506 | R50: =IF(SCTR_Brokers[[#This Row],[FechaRecepcion]]="","",_xlfn.LET(_xlpm.fer,LISTAS!$L$3:$L$100,_xlpm.ep,DATE(2000,1,1),_xlpm.ini,SCTR_Brokers[[#This Row],[FechaRecepcion]],_xlpm.fin,IF(SCTR_Brokers[[#This Row],[Fecha_Cierre]]<>"",SCTR_Brokers[[#This Row],[Fecha_Cierre]],NOW()),_xlpm.dini,INT(_xlpm.ini),_xlpm.dfin,INT(_xlpm.fin),_xlpm.hini,9.5*NETWORKDAYS.INTL(_xlpm.ep,_xlpm.dini-1,"0000111",_xlpm.fer)+6*NETWORKDAYS.INTL(_xlpm.ep,_xlpm.dini-1,"1111011",_xlpm.fer)+IF(OR(WEEKDAY(_xlpm.dini,2)>5,COUNTIF(_xlpm.fer,_xlpm.dini)>0),0,MAX(0,MIN(_xlpm.ini-_xlpm.dini,IF(WEEKDAY(_xlpm.dini,2)=5,14/24,17.5/24))-8/24)*24),_xlpm.hfin,9.5*NETWORKDAYS.INTL(_xlpm.ep,_xlpm.dfin-1,"0000111",_xlpm.fer)+6*NETWORKDAYS.INTL(_xlpm.ep,_xlpm.dfin-1,"1111011",_xlpm.fer)+IF(OR(WEEKDAY(_xlpm.dfin,2)>5,COUNTIF(_xlpm.fer,_xlpm.dfin)>0),0,MAX(0,MIN(_xlpm.fin-_xlpm.dfin,IF(WEEKDAY(_xlpm.dfin,2)=5,14/24,17.5/24))-8/24)*24),_xlpm.hrs,IF(SCTR_Brokers[[#This Row],[Estado]]="FINALIZADO",MAX(0,_xlpm.hfin-_xlpm.hini),IF(SCTR_Brokers[[#This Row],[Horas_Transcurridas]]="",MAX(0,_xlpm.hfin-_xlpm.hini),SCTR_Brokers[[#This Row],[Horas_Transcurridas]])),IF(_xlpm.hrs<=LISTAS!$E$3,LISTAS!$J$3,LISTAS!$J$4))) -> Dentro | T50: =IF(SCTR_Brokers[[#This Row],[FechaRecepcion]]="","",TEXT(SCTR_Brokers[[#This Row],[FechaRecepcion]],"mmmm")&" "&YEAR(SCTR_Brokers[[#This Row],[FechaRecepcion]])) -> agosto 2026 | U50: =IF(SCTR_Brokers[[#This Row],[Estado]]="FINALIZADO",1,0) -> 1 | V50: =IF(SCTR_Brokers[[#This Row],[FechaRecepcion]]="","",IF(SCTR_Brokers[[#This Row],[Estado]]="FINALIZADO",0,1)) -> 0 | W50: =IF(AND(SCTR_Brokers[[#This Row],[Estado]]="FINALIZADO",SCTR_Brokers[[#This Row],[Plazo]]=LISTAS!$J$3),1,0) -> 1 | X50: =IF(AND(SCTR_Brokers[[#This Row],[Estado]]="FINALIZADO",SCTR_Brokers[[#This Row],[Plazo]]=LISTAS!$J$4),1,0) -> 0 | Y50: =IF(AND(SCTR_Brokers[[#This Row],[Estado]]<>"FINALIZADO",SCTR_Brokers[[#This Row],[Plazo]]=LISTAS!$J$4),1,0) -> 0 | Z50: =IF(SCTR_Brokers[[#This Row],[Fecha_Solic_Informe]]="",0,1) -> 0 | AA50: =IF(SCTR_Brokers[[#This Row],[Fecha_Informe]]="",0,1) -> 0 | AB50: =IF(AND(SCTR_Brokers[[#This Row],[Fecha_Solic_Informe]]<>"",SCTR_Brokers[[#This Row],[Fecha_Informe]]=""),1,0) -> 0 | AC50: =IF(AND(SCTR_Brokers[[#This Row],[Fecha_Solic_Informe]]<>"",SCTR_Brokers[[#This Row],[Fecha_Informe]]<>""),ROUND((SCTR_Brokers[[#This Row],[Fecha_Informe]]-SCTR_Brokers[[#This Row],[Fecha_Solic_Informe]])*24,1),"")
A51: AAQkADdkNThjNzFkLWM0ZmMtNDJhYS04MDVlLTIwNzE4ZDI1Mzg4YgAQAFSn_rQh8tVOrXdOXJVAqqs= | C51: =IF(SCTR_Brokers[[#This Row],[FechaRecepcion]]="","",SCTR_Brokers[[#This Row],[ConversationId]]&"-"&TEXT(SCTR_Brokers[[#This Row],[FechaRecepcion]],"aaaammddhhmmss")) -> AAQkADdkNThjNzFkLWM0ZmMtNDJhYS04MDVlLTIwNzE4ZDI1Mzg4YgAQAFSn_rQh8tVOrXdOXJVAqqs=-20260819114645 | D51: RV: ** observado ** SNACKS AMERICA LATINA || TRAMA FINAL JULIO | E51: MARSH | F51: 46253.491 | G51: 46254.516 | H51: sctrsalud@mapfre.com.pe | I51: FINALIZADO | K51: SCTR SALUD | N51: =IF(SCTR_Brokers[[#This Row],[FechaRecepcion]]="","",IF(SCTR_Brokers[[#This Row],[Estado]]="FINALIZADO","",IF(SCTR_Brokers[[#This Row],[FechaUltimaRespuesta]]="","",_xlfn.LET(_xlpm.fer,LISTAS!$L$3:$L$100,_xlpm.ep,DATE(2000,1,1),_xlpm.ini,SCTR_Brokers[[#This Row],[FechaUltimaRespuesta]],_xlpm.fin,NOW(),_xlpm.dini,INT(_xlpm.ini),_xlpm.dfin,INT(_xlpm.fin),_xlpm.hini,9.5*NETWORKDAYS.INTL(_xlpm.ep,_xlpm.dini-1,"0000111",_xlpm.fer)+6*NETWORKDAYS.INTL(_xlpm.ep,_xlpm.dini-1,"1111011",_xlpm.fer)+IF(OR(WEEKDAY(_xlpm.dini,2)>5,COUNTIF(_xlpm.fer,_xlpm.dini)>0),0,MAX(0,MIN(_xlpm.ini-_xlpm.dini,IF(WEEKDAY(_xlpm.dini,2)=5,14/24,17.5/24))-8/24)*24),_xlpm.hfin,9.5*NETWORKDAYS.INTL(_xlpm.ep,_xlpm.dfin-1,"0000111",_xlpm.fer)+6*NETWORKDAYS.INTL(_xlpm.ep,_xlpm.dfin-1,"1111011",_xlpm.fer)+IF(OR(WEEKDAY(_xlpm.dfin,2)>5,COUNTIF(_xlpm.fer,_xlpm.dfin)>0),0,MAX(0,MIN(_xlpm.fin-_xlpm.dfin,IF(WEEKDAY(_xlpm.dfin,2)=5,14/24,17.5/24))-8/24)*24),ROUND(MAX(0,_xlpm.hfin-_xlpm.hini),1))))) | Q51: 46254.516 | R51: =IF(SCTR_Brokers[[#This Row],[FechaRecepcion]]="","",_xlfn.LET(_xlpm.fer,LISTAS!$L$3:$L$100,_xlpm.ep,DATE(2000,1,1),_xlpm.ini,SCTR_Brokers[[#This Row],[FechaRecepcion]],_xlpm.fin,IF(SCTR_Brokers[[#This Row],[Fecha_Cierre]]<>"",SCTR_Brokers[[#This Row],[Fecha_Cierre]],NOW()),_xlpm.dini,INT(_xlpm.ini),_xlpm.dfin,INT(_xlpm.fin),_xlpm.hini,9.5*NETWORKDAYS.INTL(_xlpm.ep,_xlpm.dini-1,"0000111",_xlpm.fer)+6*NETWORKDAYS.INTL(_xlpm.ep,_xlpm.dini-1,"1111011",_xlpm.fer)+IF(OR(WEEKDAY(_xlpm.dini,2)>5,COUNTIF(_xlpm.fer,_xlpm.dini)>0),0,MAX(0,MIN(_xlpm.ini-_xlpm.dini,IF(WEEKDAY(_xlpm.dini,2)=5,14/24,17.5/24))-8/24)*24),_xlpm.hfin,9.5*NETWORKDAYS.INTL(_xlpm.ep,_xlpm.dfin-1,"0000111",_xlpm.fer)+6*NETWORKDAYS.INTL(_xlpm.ep,_xlpm.dfin-1,"1111011",_xlpm.fer)+IF(OR(WEEKDAY(_xlpm.dfin,2)>5,COUNTIF(_xlpm.fer,_xlpm.dfin)>0),0,MAX(0,MIN(_xlpm.fin-_xlpm.dfin,IF(WEEKDAY(_xlpm.dfin,2)=5,14/24,17.5/24))-8/24)*24),_xlpm.hrs,IF(SCTR_Brokers[[#This Row],[Estado]]="FINALIZADO",MAX(0,_xlpm.hfin-_xlpm.hini),IF(SCTR_Brokers[[#This Row],[Horas_Transcurridas]]="",MAX(0,_xlpm.hfin-_xlpm.hini),SCTR_Brokers[[#This Row],[Horas_Transcurridas]])),IF(_xlpm.hrs<=LISTAS!$E$3,LISTAS!$J$3,LISTAS!$J$4))) -> Fuera | T51: =IF(SCTR_Brokers[[#This Row],[FechaRecepcion]]="","",TEXT(SCTR_Brokers[[#This Row],[FechaRecepcion]],"mmmm")&" "&YEAR(SCTR_Brokers[[#This Row],[FechaRecepcion]])) -> agosto 2026 | U51: =IF(SCTR_Brokers[[#This Row],[Estado]]="FINALIZADO",1,0) -> 1 | V51: =IF(SCTR_Brokers[[#This Row],[FechaRecepcion]]="","",IF(SCTR_Brokers[[#This Row],[Estado]]="FINALIZADO",0,1)) -> 0 | W51: =IF(AND(SCTR_Brokers[[#This Row],[Estado]]="FINALIZADO",SCTR_Brokers[[#This Row],[Plazo]]=LISTAS!$J$3),1,0) -> 0 | X51: =IF(AND(SCTR_Brokers[[#This Row],[Estado]]="FINALIZADO",SCTR_Brokers[[#This Row],[Plazo]]=LISTAS!$J$4),1,0) -> 1 | Y51: =IF(AND(SCTR_Brokers[[#This Row],[Estado]]<>"FINALIZADO",SCTR_Brokers[[#This Row],[Plazo]]=LISTAS!$J$4),1,0) -> 0 | Z51: =IF(SCTR_Brokers[[#This Row],[Fecha_Solic_Informe]]="",0,1) -> 0 | AA51: =IF(SCTR_Brokers[[#This Row],[Fecha_Informe]]="",0,1) -> 0 | AB51: =IF(AND(SCTR_Brokers[[#This Row],[Fecha_Solic_Informe]]<>"",SCTR_Brokers[[#This Row],[Fecha_Informe]]=""),1,0) -> 0 | AC51: =IF(AND(SCTR_Brokers[[#This Row],[Fecha_Solic_Informe]]<>"",SCTR_Brokers[[#This Row],[Fecha_Informe]]<>""),ROUND((SCTR_Brokers[[#This Row],[Fecha_Informe]]-SCTR_Brokers[[#This Row],[Fecha_Solic_Informe]])*24,1),"")
A52: AAQkADdkNThjNzFkLWM0ZmMtNDJhYS04MDVlLTIwNzE4ZDI1Mzg4YgAQAGw6SENGEkr8laV8SRm2o3o= | C52: =IF(SCTR_Brokers[[#This Row],[FechaRecepcion]]="","",SCTR_Brokers[[#This Row],[ConversationId]]&"-"&TEXT(SCTR_Brokers[[#This Row],[FechaRecepcion]],"aaaammddhhmmss")) -> AAQkADdkNThjNzFkLWM0ZmMtNDJhYS04MDVlLTIwNzE4ZDI1Mzg4YgAQAGw6SENGEkr8laV8SRm2o3o=-20260819120046 | D52: SNACKS -SCTR - SOLICITUD DE CARTA GARANTIA # 1131385 - CLINICA AUNA BELLAVISTA | E52: MARSH | F52: 46253.501 | G52: 46253.763 | H52: sctrsalud@mapfre.com.pe | I52: FINALIZADO | K52: SCTR SALUD | N52: =IF(SCTR_Brokers[[#This Row],[FechaRecepcion]]="","",IF(SCTR_Brokers[[#This Row],[Estado]]="FINALIZADO","",IF(SCTR_Brokers[[#This Row],[FechaUltimaRespuesta]]="","",_xlfn.LET(_xlpm.fer,LISTAS!$L$3:$L$100,_xlpm.ep,DATE(2000,1,1),_xlpm.ini,SCTR_Brokers[[#This Row],[FechaUltimaRespuesta]],_xlpm.fin,NOW(),_xlpm.dini,INT(_xlpm.ini),_xlpm.dfin,INT(_xlpm.fin),_xlpm.hini,9.5*NETWORKDAYS.INTL(_xlpm.ep,_xlpm.dini-1,"0000111",_xlpm.fer)+6*NETWORKDAYS.INTL(_xlpm.ep,_xlpm.dini-1,"1111011",_xlpm.fer)+IF(OR(WEEKDAY(_xlpm.dini,2)>5,COUNTIF(_xlpm.fer,_xlpm.dini)>0),0,MAX(0,MIN(_xlpm.ini-_xlpm.dini,IF(WEEKDAY(_xlpm.dini,2)=5,14/24,17.5/24))-8/24)*24),_xlpm.hfin,9.5*NETWORKDAYS.INTL(_xlpm.ep,_xlpm.dfin-1,"0000111",_xlpm.fer)+6*NETWORKDAYS.INTL(_xlpm.ep,_xlpm.dfin-1,"1111011",_xlpm.fer)+IF(OR(WEEKDAY(_xlpm.dfin,2)>5,COUNTIF(_xlpm.fer,_xlpm.dfin)>0),0,MAX(0,MIN(_xlpm.fin-_xlpm.dfin,IF(WEEKDAY(_xlpm.dfin,2)=5,14/24,17.5/24))-8/24)*24),ROUND(MAX(0,_xlpm.hfin-_xlpm.hini),1))))) | Q52: 46253.763 | R52: =IF(SCTR_Brokers[[#This Row],[FechaRecepcion]]="","",_xlfn.LET(_xlpm.fer,LISTAS!$L$3:$L$100,_xlpm.ep,DATE(2000,1,1),_xlpm.ini,SCTR_Brokers[[#This Row],[FechaRecepcion]],_xlpm.fin,IF(SCTR_Brokers[[#This Row],[Fecha_Cierre]]<>"",SCTR_Brokers[[#This Row],[Fecha_Cierre]],NOW()),_xlpm.dini,INT(_xlpm.ini),_xlpm.dfin,INT(_xlpm.fin),_xlpm.hini,9.5*NETWORKDAYS.INTL(_xlpm.ep,_xlpm.dini-1,"0000111",_xlpm.fer)+6*NETWORKDAYS.INTL(_xlpm.ep,_xlpm.dini-1,"1111011",_xlpm.fer)+IF(OR(WEEKDAY(_xlpm.dini,2)>5,COUNTIF(_xlpm.fer,_xlpm.dini)>0),0,MAX(0,MIN(_xlpm.ini-_xlpm.dini,IF(WEEKDAY(_xlpm.dini,2)=5,14/24,17.5/24))-8/24)*24),_xlpm.hfin,9.5*NETWORKDAYS.INTL(_xlpm.ep,_xlpm.dfin-1,"0000111",_xlpm.fer)+6*NETWORKDAYS.INTL(_xlpm.ep,_xlpm.dfin-1,"1111011",_xlpm.fer)+IF(OR(WEEKDAY(_xlpm.dfin,2)>5,COUNTIF(_xlpm.fer,_xlpm.dfin)>0),0,MAX(0,MIN(_xlpm.fin-_xlpm.dfin,IF(WEEKDAY(_xlpm.dfin,2)=5,14/24,17.5/24))-8/24)*24),_xlpm.hrs,IF(SCTR_Brokers[[#This Row],[Estado]]="FINALIZADO",MAX(0,_xlpm.hfin-_xlpm.hini),IF(SCTR_Brokers[[#This Row],[Horas_Transcurridas]]="",MAX(0,_xlpm.hfin-_xlpm.hini),SCTR_Brokers[[#This Row],[Horas_Transcurridas]])),IF(_xlpm.hrs<=LISTAS!$E$3,LISTAS!$J$3,LISTAS!$J$4))) -> Dentro | T52: =IF(SCTR_Brokers[[#This Row],[FechaRecepcion]]="","",TEXT(SCTR_Brokers[[#This Row],[FechaRecepcion]],"mmmm")&" "&YEAR(SCTR_Brokers[[#This Row],[FechaRecepcion]])) -> agosto 2026 | U52: =IF(SCTR_Brokers[[#This Row],[Estado]]="FINALIZADO",1,0) -> 1 | V52: =IF(SCTR_Brokers[[#This Row],[FechaRecepcion]]="","",IF(SCTR_Brokers[[#This Row],[Estado]]="FINALIZADO",0,1)) -> 0 | W52: =IF(AND(SCTR_Brokers[[#This Row],[Estado]]="FINALIZADO",SCTR_Brokers[[#This Row],[Plazo]]=LISTAS!$J$3),1,0) -> 1 | X52: =IF(AND(SCTR_Brokers[[#This Row],[Estado]]="FINALIZADO",SCTR_Brokers[[#This Row],[Plazo]]=LISTAS!$J$4),1,0) -> 0 | Y52: =IF(AND(SCTR_Brokers[[#This Row],[Estado]]<>"FINALIZADO",SCTR_Brokers[[#This Row],[Plazo]]=LISTAS!$J$4),1,0) -> 0 | Z52: =IF(SCTR_Brokers[[#This Row],[Fecha_Solic_Informe]]="",0,1) -> 0 | AA52: =IF(SCTR_Brokers[[#This Row],[Fecha_Informe]]="",0,1) -> 0 | AB52: =IF(AND(SCTR_Brokers[[#This Row],[Fecha_Solic_Informe]]<>"",SCTR_Brokers[[#This Row],[Fecha_Informe]]=""),1,0) -> 0 | AC52: =IF(AND(SCTR_Brokers[[#This Row],[Fecha_Solic_Informe]]<>"",SCTR_Brokers[[#This Row],[Fecha_Informe]]<>""),ROUND((SCTR_Brokers[[#This Row],[Fecha_Informe]]-SCTR_Brokers[[#This Row],[Fecha_Solic_Informe]])*24,1),"")
